Workbook

Sheet Cover
B2: NEW-AGE DEFENCE PRIME | 10-YEAR STRATEGIC PLAN
B3: Platform-Based Engineering - Multi-Domain (Air | Land | Sea | Cyber)
B5: Company thesis | C5: A new-age defense prime built on owned IP across six product verticals. All six are already designed; V2 EW/SIGINT is GSQR-compliant with a committed Rs.200 Cr iDEX MoQ for 10 airborne ESM units now in prototype trials. Capital deployed against prototyping, qualification, and production line stand-up - not greenfield invention. Five reusable platform modules (RF, DSP, SysEng, Embedded/SW, AI/ML) compound R&D leverage across verticals.
B6: Operating model | C6: Industrialise mature designs in parallel. Cross-functional product squads, short qualification cycles (12-24 months MVP-to-field) enabled by pre-existing design IP and 10% bank-confirmed BG cash margin. Concurrent development + production across verticals.
B7: Product verticals | C7: 1) AESA Radar (first ship Y2) | 2) EW & SIGINT (Rs.200 Cr iDEX MoQ in trials, ship Y1) | 3) Counter-UAS (Y3) | 4) MALE ISR UAS (end-Y3) | 5) Autonomous AUV/USV (Y3) | 6) Military AI modules (Y2)
B8: Core USP | C8: Owned IP across six fielded product lines inside Y3. Five reusable platform modules. Bank-confirmed 10% BG margin from Day 1 unlocks capital efficiency. iDEX-validated ESM anchor de-risks the funding ask. Cross-domain coverage Air/Land/Sea/Cyber from a single engineering org.
B9: Planning horizon | C9: 10 years | Currency: INR Crores | All cells with yellow background are inputs.
B10: Cell colour key | C10: Yellow = input | Light blue = calculated | Darker blue = total/subtotal | Navy bar = section header
B11: Read order | C11: Cover to KPIs to Strategy to MarketPositioning to Roadmap to Platform to ReuseMatrix to Assumptions to V1..V6 (per-vertical) to Revenue to Headcount to R&D_NRE to Capex to Opex to P&L to CashFlow to Funding to BreakEven
B13: Product verticals at a glance
B14: Code | C14: Vertical | D14: Domain | E14: Launch | F14: Sheet
B15: V1 | C15: AESA Radar | D15: Air/Land/Sea (RF) | E15: Y2 | F15: V1_AESA
B16: V2 | C16: Electronic Warfare & SIGINT | D16: Air/Land/Sea (RF + DSP) | E16: Y1 | F16: V2_EW_SIGINT
B17: V3 | C17: Counter-UAS (Anti-Drone) | D17: Land/Air (RF + AI fusion) | E17: Y2 | F17: V3_CUAS
B18: V4 | C18: MALE-class ISR UAS | D18: Air (SysEng + SW + AI) | E18: Y4 | F18: V4_UAS_MALE
B19: V5 | C19: Autonomous Systems (AUV/USV) | D19: Sea (SysEng + SW + AI) | E19: Y3 | F19: V5_Autonomous
B20: V6 | C20: Military AI Systems | D20: Cross-domain (AI/SW) | E20: Y1 | F20: V6_MilAI

Sheet KPIs
B2: CXO EXECUTIVE SUMMARY
B3: Year 10 Revenue | D3: Year 10 EBITDA (margin) | F3: 10-Yr Cumulative FCF | H3: IRR (10-Yr FCF) | J3: NPV @ Disc. Rate (WACC)
B4: ='P&L'!L5 -> 5055.32 | D4: ="₹ "&TEXT('P&L'!L16,"#,##0.0")&" Cr ("&TEXT(IFERROR('P&L'!L16/'P&L'!L5,0),"0.0%")&")" -> ₹ 2,347.1 Cr (46.4%) | F4: =SUM(CashFlow!C27:L27) -> 4803.2655 | H4: =IFERROR(IRR(CashFlow!C27:L27),0) -> 0.31896859 | J4: =NPV(Assumptions!$C$7,CashFlow!C27:L27) -> 747.15263
B6: Executive KPI Dashboard - Diversified Defense & Aerospace
B8: Metric | C8: Y1 | D8: Y2 | E8: Y3 | F8: Y4 | G8: Y5 | H8: Y6 | I8: Y7 | J8: Y8 | K8: Y9 | L8: Y10
B9: Total revenue | C9: ='P&L'!C5 -> 52.5 | D9: ='P&L'!D5 -> 203.4075 | E9: ='P&L'!E5 -> 491.02541 | F9: ='P&L'!F5 -> 855.20352 | G9: ='P&L'!G5 -> 1447.7017 | H9: ='P&L'!H5 -> 2180.2274 | I9: ='P&L'!I5 -> 2883.8462 | J9: ='P&L'!J5 -> 3659.344 | ... L9: ='P&L'!L5 -> 5055.32
B10: Revenue growth Y/Y | C10: =0 -> 0 | D10: =IFERROR(D9/C9-1,0) -> 2.8744286 | E10: =IFERROR(E9/D9-1,0) -> 1.4139985 | F10: =IFERROR(F9/E9-1,0) -> 0.74166858 | G10: =IFERROR(G9/F9-1,0) -> 0.69281543 | H10: =IFERROR(H9/G9-1,0) -> 0.50599213 | I10: =IFERROR(I9/H9-1,0) -> 0.32272726 | J10: =IFERROR(J9/I9-1,0) -> 0.26891092 | K10: =IFERROR(K9/J9-1,0) -> 0.19711563 | L10: =IFERROR(L9/K9-1,0) -> 0.15400931
B11: Gross profit | C11: ='P&L'!C9 -> 27.011617 | D11: ='P&L'!D9 -> 117.73007 | E11: ='P&L'!E9 -> 311.47721 | F11: ='P&L'!F9 -> 533.2586 | G11: ='P&L'!G9 -> 918.76581 | H11: ='P&L'!H9 -> 1408.7692 | I11: ='P&L'!I9 -> 1885.4316 | J11: ='P&L'!J9 -> 2410.6944 | ... L11: ='P&L'!L9 -> 3377.3479
B12: Gross margin % | C12: =IFERROR(C11/C9,0) -> 0.51450699 | D12: =IFERROR(D11/D9,0) -> 0.57878921 | E12: =IFERROR(E11/E9,0) -> 0.63434031 | F12: =IFERROR(F11/F9,0) -> 0.62354584 | G12: =IFERROR(G11/G9,0) -> 0.63463751 | H12: =IFERROR(H11/H9,0) -> 0.646157 | I12: =IFERROR(I11/I9,0) -> 0.65379063 | J12: =IFERROR(J11/J9,0) -> 0.65877776 | ... L12: =IFERROR(L11/L9,0) -> 0.66807798
B13: R&D / NRE expense | C13: ='P&L'!C12 -> 301.93624 | D13: ='P&L'!D12 -> 347.80873 | E13: ='P&L'!E12 -> 185.21737 | F13: ='P&L'!F12 -> 118.02114 | G13: ='P&L'!G12 -> 80.586228 | H13: ='P&L'!H12 -> 66.911876 | I13: ='P&L'!I12 -> 63.404198 | J13: ='P&L'!J12 -> 65.917668 | ... L13: ='P&L'!L12 -> 68.640795
B14: Counterfactual: NRE avoided by platform reuse (NOT realized cash) | C14: ='R&D_NRE'!D8-'R&D_NRE'!D6 -> 119.89713 | D14: ='R&D_NRE'!E8-'R&D_NRE'!E6 -> 198.60082 | E14: ='R&D_NRE'!F8-'R&D_NRE'!F6 -> 210.94554 | F14: ='R&D_NRE'!G8-'R&D_NRE'!G6 -> 179.76992 | G14: ='R&D_NRE'!H8-'R&D_NRE'!H6 -> 123.16721 | H14: ='R&D_NRE'!I8-'R&D_NRE'!I6 -> 71.689147 | I14: ='R&D_NRE'!J8-'R&D_NRE'!J6 -> 45.874046 | J14: ='R&D_NRE'!K8-'R&D_NRE'!K6 -> 26.464991 | ... L14: ='R&D_NRE'!M8-'R&D_NRE'!M6 -> 8.699625
B15: EBITDA | C15: ='P&L'!C16 -> -324.49623 | D15: ='P&L'!D16 -> -316.78236 | E15: ='P&L'!E16 -> -22.7994 | F15: ='P&L'!F16 -> 190.46392 | G15: ='P&L'!G16 -> 501.69301 | H15: ='P&L'!H16 -> 876.56194 | I15: ='P&L'!I16 -> 1232.8939 | J15: ='P&L'!J16 -> 1622.8415 | ... L15: ='P&L'!L16 -> 2347.0901
B16: EBITDA margin % | C16: =IFERROR(C15/C9,0) -> -6.1808806 | D16: =IFERROR(D15/D9,0) -> -1.557378 | E16: =IFERROR(E15/E9,0) -> -0.046432221 | F16: =IFERROR(F15/F9,0) -> 0.2227118 | G16: =IFERROR(G15/G9,0) -> 0.34654446 | H16: =IFERROR(H15/H9,0) -> 0.40205069 | I16: =IFERROR(I15/I9,0) -> 0.4275172 | J16: =IFERROR(J15/J9,0) -> 0.44347882 | ... L16: =IFERROR(L15/L9,0) -> 0.46428122
B17: Net income | C17: ='P&L'!C24 -> -335.06825 | D17: ='P&L'!D24 -> -355.71344 | E17: ='P&L'!E24 -> -91.417614 | F17: ='P&L'!F24 -> 99.488086 | G17: ='P&L'!G24 -> 400.12777 | H17: ='P&L'!H24 -> 671.23238 | I17: ='P&L'!I24 -> 844.0913 | J17: ='P&L'!J24 -> 1154.5239 | ... L17: ='P&L'!L24 -> 1717.3482
B18: Free cash flow | C18: =CashFlow!C27 -> -359.92178 | D18: =CashFlow!D27 -> -467.73337 | E18: =CashFlow!E27 -> -234.12709 | F18: =CashFlow!F27 -> 2.9927111 | G18: =CashFlow!G27 -> 265.53479 | H18: =CashFlow!H27 -> 571.97389 | I18: =CashFlow!I27 -> 925.83481 | J18: =CashFlow!J27 -> 1071.8306 | ... L18: =CashFlow!L27 -> 1660.8948
B19: Cumulative FCF | C19: =CashFlow!C28 -> -359.92178 | D19: =CashFlow!D28 -> -827.65515 | E19: =CashFlow!E28 -> -1061.7822 | F19: =CashFlow!F28 -> -1058.7895 | G19: =CashFlow!G28 -> -793.25474 | H19: =CashFlow!H28 -> -221.28085 | I19: =CashFlow!I28 -> 704.55396 | J19: =CashFlow!J28 -> 1776.3845 | ... L19: =CashFlow!L28 -> 4803.2655
B20: Cash balance (EoY, deployable) | C20: =CashFlow!C30 -> 110.07822 | D20: =CashFlow!D30 -> 142.34485 | E20: =CashFlow!E30 -> 238.21776 | F20: =CashFlow!F30 -> 241.21047 | G20: =CashFlow!G30 -> 470.74526 | H20: =CashFlow!H30 -> 1006.7191 | I20: =CashFlow!I30 -> 1877.554 | J20: =CashFlow!J30 -> 2884.3845 | ... L20: =CashFlow!L30 -> 5903.2655
B21: Restricted cash (BG collateral) | C21: =Backlog!D63 -> 7.65099 | D21: =Backlog!E63 -> 20.300722 | E21: =Backlog!F63 -> 38.334047 | F21: =Backlog!G63 -> 68.285291 | G21: =Backlog!H63 -> 105.98933 | H21: =Backlog!I63 -> 143.59794 | I21: =Backlog!J63 -> 185.37943 | J21: =Backlog!K63 -> 225.30466 | ... L21: =Backlog!M63 -> 300.23537
B22: Total cash (incl. restricted) | C22: =CashFlow!C30+Backlog!D63 -> 117.72921 | D22: =CashFlow!D30+Backlog!E63 -> 162.64557 | E22: =CashFlow!E30+Backlog!F63 -> 276.5518 | F22: =CashFlow!F30+Backlog!G63 -> 309.49576 | G22: =CashFlow!G30+Backlog!H63 -> 576.73459 | H22: =CashFlow!H30+Backlog!I63 -> 1150.3171 | I22: =CashFlow!I30+Backlog!J63 -> 2062.9334 | J22: =CashFlow!J30+Backlog!K63 -> 3109.6892 | ... L22: =CashFlow!L30+Backlog!M63 -> 6203.5009
B23: Net cash (deployable = Total − Restricted) | C23: =CashFlow!C30 -> 110.07822 | D23: =CashFlow!D30 -> 142.34485 | E23: =CashFlow!E30 -> 238.21776 | F23: =CashFlow!F30 -> 241.21047 | G23: =CashFlow!G30 -> 470.74526 | H23: =CashFlow!H30 -> 1006.7191 | I23: =CashFlow!I30 -> 1877.554 | J23: =CashFlow!J30 -> 2884.3845 | ... L23: =CashFlow!L30 -> 5903.2655
B24: Contract liabilities (customer advances, EoY) | C24: =Backlog!D56 -> 63.75825 | D24: =Backlog!E56 -> 169.17268 | E24: =Backlog!F56 -> 319.45039 | F24: =Backlog!G56 -> 569.04409 | G24: =Backlog!H56 -> 883.24441 | H24: =Backlog!I56 -> 1196.6495 | I24: =Backlog!J56 -> 1544.8286 | J24: =Backlog!K56 -> 1877.5388 | ... L24: =Backlog!M56 -> 2501.9615
B25: Bank guarantees outstanding (PBG + ABG) | C25: =Backlog!D62 -> 76.5099 | D25: =Backlog!E62 -> 203.00722 | E25: =Backlog!F62 -> 383.34047 | F25: =Backlog!G62 -> 682.85291 | G25: =Backlog!H62 -> 1059.8933 | H25: =Backlog!I62 -> 1435.9794 | I25: =Backlog!J62 -> 1853.7943 | J25: =Backlog!K62 -> 2253.0466 | ... L25: =Backlog!M62 -> 3002.3537
B26: Equity raised | C26: =Funding!D9 -> 450 | D26: =Funding!E9 -> 400 | E26: =Funding!F9 -> 250 | F26: =Funding!G9 -> 0 | G26: =Funding!H9 -> 0 | H26: =Funding!I9 -> 0 | I26: =Funding!J9 -> 0 | J26: =Funding!K9 -> 0 | ... L26: =Funding!M9 -> 0
B27: Debt balance (EoY) | C27: =Funding!D16 -> 20 | D27: =Funding!E16 -> 120 | E27: =Funding!F16 -> 200 | F27: =Funding!G16 -> 200 | G27: =Funding!H16 -> 164 | H27: =Funding!I16 -> 128 | I27: =Funding!J16 -> 73 | J27: =Funding!K16 -> 8 | ... L27: =Funding!M16 -> 0
B28: Total headcount (EoY) | C28: =Headcount!D34 -> 91 | D28: =Headcount!E34 -> 156 | E28: =Headcount!F34 -> 216 | F28: =Headcount!G34 -> 287 | G28: =Headcount!H34 -> 349 | H28: =Headcount!I34 -> 414 | I28: =Headcount!J34 -> 475 | J28: =Headcount!K34 -> 506 | ... L28: =Headcount!M34 -> 543
B29: Revenue per employee | C29: =IFERROR(C9/C28,0) -> 0.57692308 | D29: =IFERROR(D9/D28,0) -> 1.3038942 | E29: =IFERROR(E9/E28,0) -> 2.2732658 | F29: =IFERROR(F9/F28,0) -> 2.9798032 | G29: =IFERROR(G9/G28,0) -> 4.1481425 | H29: =IFERROR(H9/H28,0) -> 5.2662498 | I29: =IFERROR(I9/I28,0) -> 6.0712552 | J29: =IFERROR(J9/J28,0) -> 7.2319051 | ... L29: =IFERROR(L9/L28,0) -> 9.3099815
B30: Capex (gross) | C30: =Capex!D21 -> 35.45 | D30: =Capex!E21 -> 67.225 | E30: =Capex!F21 -> 118.15 | F30: =Capex!G21 -> 135.7 | G30: =Capex!H21 -> 94.375 | H30: =Capex!I21 -> 47.1 | I30: =Capex!J21 -> 19.95 | J30: =Capex!K21 -> 29.45 | ... L30: =Capex!M21 -> 22.8
B31: Current ratio (CA / CL = AP + Customer Advances) | C31: =BalanceSheet!C33 -> 2.2407019 | D31: =BalanceSheet!D33 -> 1.5805548 | E31: =BalanceSheet!E33 -> 1.6481141 | F31: =BalanceSheet!F33 -> 1.3316507 | G31: =BalanceSheet!G33 -> 1.4983222 | H31: =BalanceSheet!H33 -> 1.8700988 | I31: =BalanceSheet!I33 -> 2.2370897 | J31: =BalanceSheet!J33 -> 2.5706275 | ... L31: =BalanceSheet!L33 -> 3.3631738
B32: ROIC (NOPAT / Debt+Equity) | C32: =BalanceSheet!C35 -> -1.8579852 | D32: =BalanceSheet!D35 -> -0.94042929 | E32: =BalanceSheet!E35 -> -0.11387241 | F32: =BalanceSheet!F35 -> 0.14031693 | G32: =BalanceSheet!G35 -> 0.31690502 | H32: =BalanceSheet!H35 -> 0.36365647 | I32: =BalanceSheet!I35 -> 0.35666961 | J32: =BalanceSheet!J35 -> 0.33243642 | ... L32: =BalanceSheet!L35 -> 0.25862396
B33: Net Working Capital | C33: =CashFlow!C11 -> 29.032814 | D33: =CashFlow!D11 -> 110.87352 | E33: =CashFlow!E11 -> 264.28559 | F33: =CashFlow!F11 -> 461.43604 | G33: =CashFlow!G11 -> 779.14637 | H33: =CashFlow!H11 -> 1170.2919 | I33: =CashFlow!I11 -> 1545.2629 | J33: =CashFlow!J11 -> 1958.5511 | ... L33: =CashFlow!L11 -> 2699.9078
B35: 10-year cumulative & strategic indicators
B36: Cumulative revenue (10 yr) | C36: =SUM('P&L'!C5:L5) -> 21209.234
B37: Cumulative EBITDA (10 yr) | C37: =SUM('P&L'!C16:L16) -> 8100.0525
B38: Cumulative net income (10 yr) | C38: =SUM('P&L'!C24:L24) -> 5548.2439
B39: Cumulative R&D / NRE expense | C39: =SUM('R&D_NRE'!D12:M12) -> 1365.9421
B40: Cumulative NRE saved by platform | C40: =SUM('R&D_NRE'!D8:M8)-SUM('R&D_NRE'!D6:M6) -> 994.32373
B41: Total equity raised | C41: =SUM(Funding!D9:M9) -> 1100
B42: Total Capex (10 yr) | C42: =SUM(Capex!D21:M21) -> 600.125
B43: NPV of FCF (WACC) | C43: =NPV(Assumptions!$C$7,CashFlow!C27:L27) -> 747.15263
B44: IRR of FCF | C44: =IFERROR(IRR(CashFlow!C27:L27),0) -> 0.31896859
B45: Peak cumulative cash deficit | C45: =MIN(CashFlow!C28:L28) -> -1061.7822
B46: First EBITDA-positive year | C46: =IFERROR(MATCH(TRUE(),INDEX('P&L'!C16:L16>0,0),0),"n/a") -> 4
B47: First FCF-positive year | C47: =IFERROR(MATCH(TRUE(),INDEX(CashFlow!C27:L27>0,0),0),"n/a") -> 4
B49: R&D bucket accounting summary
B50: Weighted Platform R&D capitalisation % | C50: ='R&D_Buckets'!D89 -> 0.25990099 | D50: ='R&D_Buckets'!E89 -> 0.42404762 | E50: ='R&D_Buckets'!F89 -> 0.55336449 | F50: ='R&D_Buckets'!G89 -> 0.62811594 | G50: ='R&D_Buckets'!H89 -> 0.68394737 | H50: ='R&D_Buckets'!I89 -> 0.71365854 | I50: ='R&D_Buckets'!J89 -> 0.74026549 | J50: ='R&D_Buckets'!K89 -> 0.75130952 | ... L50: ='R&D_Buckets'!M89 -> 0.73258065
B51: Research expensed | C51: ='R&D_Buckets'!D60 -> 48.2 | D51: ='R&D_Buckets'!E60 -> 74.75 | E51: ='R&D_Buckets'!F60 -> 24.69 | F51: ='R&D_Buckets'!G60 -> 11.26 | G51: ='R&D_Buckets'!H60 -> 4.42 | H51: ='R&D_Buckets'!I60 -> 1.74 | I51: ='R&D_Buckets'!J60 -> 0.74 | J51: ='R&D_Buckets'!K60 -> 0.474 | ... L51: ='R&D_Buckets'!M60 -> 0.209
B52: Development capitalised | C52: ='R&D_Buckets'!D88 -> 26.25 | D52: ='R&D_Buckets'!E88 -> 89.05 | E52: ='R&D_Buckets'!F88 -> 59.21 | F52: ='R&D_Buckets'!G88 -> 43.34 | G52: ='R&D_Buckets'!H88 -> 25.99 | H52: ='R&D_Buckets'!I88 -> 14.63 | I52: ='R&D_Buckets'!J88 -> 8.365 | J52: ='R&D_Buckets'!K88 -> 6.311 | ... L52: ='R&D_Buckets'!M88 -> 2.271
B53: Development expensed / not capitalisation eligible | C53: ='R&D_Buckets'!D82 -> 26.55 | D53: ='R&D_Buckets'!E82 -> 46.2 | E53: ='R&D_Buckets'!F82 -> 23.1 | F53: ='R&D_Buckets'!G82 -> 14.4 | G53: ='R&D_Buckets'!H82 -> 7.59 | H53: ='R&D_Buckets'!I82 -> 4.13 | I53: ='R&D_Buckets'!J82 -> 2.195 | J53: ='R&D_Buckets'!K82 -> 1.615 | ... L53: ='R&D_Buckets'!M82 -> 0.62
B54: Net capitalised R&D intangible asset | C54: =BalanceSheet!C39 -> 21.875 | D54: =BalanceSheet!D39 -> 91.708333 | E54: =BalanceSheet!E39 -> 121.83333 | F54: =BalanceSheet!F39 -> 128.865 | G54: =BalanceSheet!G39 -> 114.215 | H54: =BalanceSheet!H39 -> 85.766667 | I54: =BalanceSheet!I39 -> 54.034167 | J54: =BalanceSheet!J39 -> 34.0375 | ... L54: =BalanceSheet!L39 -> 13.732
B56: Terminal Value & Equity Returns (memo)
B57: Y10 EBITDA (₹ Cr) | C57: =L15 -> 2347.0901
B58: Y10 FCF (₹ Cr) | C58: =L18 -> 1660.8948
B59: TV @ 12x Y10 EBITDA | C59: =12*C57 -> 28165.081
B60: TV @ Gordon (g=3%, r=WACC) | C60: =C58*1.03/(Assumptions!C7-0.03) -> 11404.811
B61: PV of TV @ Y0 (12x case) | C61: =C59/(1+Assumptions!C7)^10 -> 5381.3463
B62: PV of TV @ Y0 (Gordon case) | C62: =C60/(1+Assumptions!C7)^10 -> 2179.0541
B63: Equity NPV incl. TV (12x case) | C63: =C43+C61 -> 6128.4989
B64: Equity NPV incl. TV (Gordon case) | C64: =C43+C62 -> 2926.2067
B65: Note | C65: IRR incl. TV not auto-computed; with PV of TV ~Rs.5-7K Cr against Rs.1,100 Cr deployed, IRR incl. TV typically jumps 8-12 percentage points vs 10-yr FCF-only IRR.

Sheet Strategy
B2: Strategic Narrative - New-Age Defense Prime
B4: Vision (10-yr) | C4: Become the reference multi-domain defense technology firm of the new-age prime model - supplier of RF, autonomy and AI products across Air, Land, Sea and Cyber, anchored on a single, deeply reusable engineering platform and shipped on commercial-software cycle times.
B5: Mission | C5: Industrialise six pre-designed defense product lines on commercial-software cycle times. Convert owned IP and the iDEX-anchored ESM contract into a defensible new-age prime: lower NRE per product, faster qualification, compounding gross margin from Year 1.
B6: New-age prime - operating model | C6: Product-focused, software-defined, asset-light. Cross-functional product squads instead of program directorates. Short cycles (12-24 month MVP to field) replace multi-year legacy programs. Concurrent development across verticals while ESM (already partly developed at Day 1) is in production and sales - funding subsequent product lines from operating cash, not just equity. Capex deferred via partner anechoic / EMI / range facilities until volumes justify owned infra.
B7: Operating thesis vs. legacy primes | C7: Legacy primes carry the full NRE burden and the full bureaucracy overhead on every product, on 5-7 year cycles. This firm amortizes RF, DSP, SysEng, SW and AI investment across 6 product lines on 1-3 year cycles, with a productized ESM business funding adjacent products - driving lower NRE per product, faster qualification, and compounding gross margin from Year 1.
B8: Core USP | C8: Multi-domain autonomous + RF systems provider operating like a software company. One certifiable platform, six product lines fielded in 5 years, three domains. We out-cycle single-point vendors on cost-to-deliver and time-to-fielding, and out-scale narrow startups on capability breadth.
B9: Strategic pillars | C9: 1) Platform Engineering - five reusable tech modules (RF · DSP · SysEng · SW · AI). 2) Multi-Domain Coverage - Air (UAS, EW pods, AESA), Land (C-UAS, SIGINT, Mil AI), Sea (AUV, USV). 3) Concurrent Dev + Production - ESM cash funds adjacent product development. 4) IP + Sovereign Capability - cleared workforce + retained data rights + IP-led licensing. 5) Allied + FMS Export - DCS/FMS-eligible product variants from Day 1.
B10: Capability waves (compressed) | C10: Wave 1 (Y1-Y2): Deliver Rs.210 Cr iDEX ESM MoQ; ship V6 Military AI modules; V1 AESA + V3 C-UAS + V4 MALE prototype trials. Wave 2 (Y3): V1 AESA first delivery + V3 C-UAS first orders + V4 MALE end-Y3 first delivery + V5 AUV first delivery. Wave 3 (Y4-Y6): Production ramp across all six verticals + export/FMS variants. Wave 4 (Y7+): Scale, replenishment cycles, allied bids.
B11: Margin trajectory (model output) | C11: Gross margin expands from ~25% (Y1, low BoM scale) toward 70-80% (Y10) as: (a) BoM learning, (b) platform reuse, (c) growing software/AI revenue mix. EBITDA crosses positive earlier than a legacy prime would achieve thanks to concurrent ESM revenue; FCF turns positive shortly after.
B12: Funding strategy | C12: Three stage-gated equity rounds totalling Rs.1,100 Cr (Seed 450, Series A 400, Series B 250) plus Rs.200 Cr venture/PSU debt and Rs.26.5 Cr iDEX/ADITI non-dilutive. BG cash margin 10% (existing facility) frees ~Rs.374 Cr of deployable cash vs legacy 100% margin assumption. No reliance on grant capital for survival - all milestones cash-self-sustaining post-Series B.
B13: Key risks & mitigants | C13: Schedule slip on hardware qualification (mitigant: small cert team + partner-lab leverage + MVP-first releases). Export-control restrictions (mitigant: dual variant ITAR/EAR99 builds, DCS workflow). Talent (mitigant: cleared-engineer pipeline + remote-first software roles + university programs). Customer concentration (mitigant: 6-vertical diversification + allied FMS pipeline from Y2).
B14: How to read this workbook | C14: Strategy to Roadmap to Platform to ReuseMatrix to V1..V6 (verticals) to Revenue (consolidated) to Headcount to R&D_NRE (with reuse savings) to Capex to Opex to P&L to CashFlow to Funding to BreakEven to KPIs.

Sheet MarketPositioning
B2: Competitive landscape - multi-domain platform vs. single-point vendors
B4: Capability dimension | C4: Our platform firm | D4: Tier-1 prime (broad) | E4: Specialty RF vendor | F4: C-UAS pure-play | G4: UAS pure-play | H4: AUV/USV specialist | I4: Defense AI startup
B5: Multi-domain coverage (Air/Land/Sea) | C5: 4 | D5: 4 | E5: 1 | F5: 1 | G5: 2 | H5: 2 | I5: 2
B6: RF / AESA capability | C6: 4 | D6: 4 | E6: 4 | F6: 2 | G6: 1 | H6: 1 | I6: 0
B7: EW / SIGINT capability | C7: 4 | D7: 4 | E7: 3 | F7: 2 | G7: 1 | H7: 1 | I7: 0
B8: Counter-UAS integrated solutions | C8: 3 | D8: 3 | E8: 1 | F8: 4 | G8: 1 | H8: 0 | I8: 1
B9: MALE-class UAS platforms | C9: 3 | D9: 4 | E9: 0 | F9: 0 | G9: 4 | H9: 0 | I9: 0
B10: Autonomous AUV/USV | C10: 3 | D10: 2 | E10: 0 | F10: 0 | G10: 1 | H10: 4 | I10: 0
B11: Military AI / sensor fusion | C11: 4 | D11: 3 | E11: 1 | F11: 2 | G11: 2 | H11: 2 | I11: 4
B12: Platform reuse / amortized NRE | C12: 4 | D12: 2 | E12: 1 | F12: 1 | G12: 1 | H12: 1 | I12: 2
B13: Time-to-market for new variants | C13: 4 | D13: 1 | E13: 2 | F13: 2 | G13: 1 | H13: 2 | I13: 3
B14: Cost-to-deliver (NRE per $ revenue) | C14: 4 | D14: 1 | E14: 3 | F14: 3 | G14: 2 | H14: 3 | I14: 4
B15: Cleared workforce / accredited facilities | C15: 3 | D15: 4 | E15: 3 | F15: 2 | G15: 3 | H15: 2 | I15: 1
B16: Export / FMS readiness | C16: 3 | D16: 4 | E16: 3 | F16: 2 | G16: 3 | H16: 2 | I16: 1
... B19: Capital efficiency (rev per $ raised) | C19: 4 | D19: 2 | E19: 3 | F19: 3 | G19: 1 | H19: 2 | I19: 3
B20: Composite score | C20: =SUM(C5:C19) -> 55 | D20: =SUM(D5:D19) -> 42 | E20: =SUM(E5:E19) -> 29 | F20: =SUM(F5:F19) -> 29 | G20: =SUM(G5:G19) -> 27 | H20: =SUM(H5:H19) -> 27 | I20: =SUM(I5:I19) -> 28
B22: Positioning summary
B23: Score legend | C23: 0 = absent | 1 = weak | 2 = partial | 3 = strong | 4 = leader
B24: Differentiation | C24: Only the platform firm spans all three domains AND amortizes RF/DSP/SysEng/SW/AI across six product lines. Pure-plays may lead in their narrow niche, but pay full NRE per product and lack cross-domain pull-through revenue.
B25: Primes vs. us | C25: Primes lead in scale, customer access and clearances; we lead in cost-to-deliver, time-to-market, and platform reuse. We compete on the 'mid-tier program' tier (sub-INR 500 Cr) where T1 primes are unprofitable.
B26: Path to category leadership | C26: Win 1 marquee program per vertical in Y2-Y5; convert into reference accounts; build allied/FMS pipeline; monetize the Mil-AI / autonomy stack as a software product attached to all hardware lines.

Sheet Roadmap
B2: 10-Year Strategic Roadmap - Platform Waves & Vertical Milestones
B4: Track | C4: Phase / focus | D4: Y1 | E4: Y2 | F4: Y3 | G4: Y4 | H4: Y5 | I4: Y6 | J4: Y7 | K4: Y8 | L4: Y9 | M4: Y10
B5: Platform M1: RF | C5: Carried over from ESM - productize | D5: Q | E5: S | F5: S | G5: S | H5: X | I5: X | J5: X | K5: X | L5: X | M5: X
B6: Platform M2: DSP | C6: Carried over from ESM - productize | D6: Q | E6: S | F6: S | G6: S | H6: X | I6: X | J6: X | K6: X | L6: X | M6: X
B7: Platform M3: SysEng | C7: MIL-STD / integration framework | D7: D | E7: Q | F7: S | G7: S | H7: S | I7: X | J7: X | K7: X | L7: X | M7: X
B8: Platform M4: SW | C8: Mission SW / C2 - productize | D8: Q | E8: S | F8: S | G8: S | H8: X | I8: X | J8: X | K8: X | L8: X | M8: X
B9: Platform M5: AI/ML | C9: Autonomy / fusion (new build) | D9: D | E9: Q | F9: S | G9: S | H9: S | I9: X | J9: X | K9: X | L9: X | M9: X
B10: V2 EW & SIGINT | C10: ESM in production Day-1 + scale-up | D10: S | E10: S | F10: S | G10: X | H10: X | I10: X | J10: X | K10: X | L10: X | M10: X
B11: V6 Military AI | C11: Edge AI + Cloud SaaS - ship Y1 | D11: S | E11: S | F11: S | G11: S | H11: X | I11: X | J11: X | K11: X | L11: X | M11: X
B12: V1 AESA Radar | C12: Variants A/B/C - qualify Y1 ship Y2 | D12: D | E12: Q | F12: S | G12: S | H12: S | I12: X | J12: X | K12: X | L12: X | M12: X
B13: V3 C-UAS | C13: MVP Y2 - multi-layer integrated | D13: D | E13: Q | F13: S | G13: S | H13: S | I13: X | J13: X | K13: X | L13: X | M13: X
B14: V5 Autonomous AUV/USV | C14: Small AUV Y3 to large AUV + USV | D14: R | E14: D | F14: Q | G14: S | H14: S | I14: S | J14: X | K14: X | L14: X | M14: X
B15: V4 MALE UAS | C15: Airframe + airworthiness (longest) | D15: R | E15: D | F15: D | G15: Q | H15: S | I15: S | J15: S | K15: X | L15: X | M15: X
B16: Facilities & cert | C16: Partner labs Y1-Y2 to owned Y3+ | D16: S | E16: S | F16: D | G16: Q | H16: S | I16: S | J16: S | K16: S | L16: S | M16: S
B17: Funding milestones | C17: SeedtoAtoBtoCtoD (smaller late stages) | D17: S | E17: S | F17: S | H17: S | J17: S
B18: Export / FMS | C18: DCS approvals + allied bids from Y2 | D18: R | E18: D | F18: Q | G18: S | H18: S | I18: X | J18: X | K18: X | L18: X | M18: X
B20: Legend
B21: R | C21: Research / seed | D21: D | E21: Develop | F21: Q | G21: Qualify / cert | H21: S | I21: Ship / scale | J21: X | K21: Export / scale-out

Sheet Platform
B2: Shared Platform Modules - Investment Profile & Maturity (TRL-style 0..1)
B4: Module | C4: Scope | D4: Y1 | E4: Y2 | F4: Y3 | G4: Y4 | H4: Y5 | I4: Y6 | J4: Y7 | K4: Y8 | L4: Y9 | M4: Y10
B5: A. Platform NRE investment by module (₹ Cr)
B6: RF / Microwave (T/R modules, receivers, antennas, GaN MMICs) | C6: X/S/Ku-band T/R modules, GaN PA/LNA, beamforming, antenna design - carried over from ESM, now extended to AESA and C-UAS. | D6: 45 | E6: 45 | F6: 25 | G6: 18 | H6: 9 | I6: 4.5 | J6: 2.5 | K6: 2.5 | L6: 2.5 | M6: 0
B7: DSP / Signal Processing (FPGA, SDR, beamforming) | C7: Real-time FPGA pipelines, SDR firmware, DBF - already fielded in ESM; reused across Radar, C-UAS, AI sensor fusion. | D7: 28 | E7: 30 | F7: 13 | G7: 8 | H7: 5 | I7: 3 | J7: 1.5 | K7: 1.5 | L7: 0 | M7: 0
B8: Systems Engineering (mech, thermal, MIL-STD, integration) | C8: MIL-STD-810/461/704 hardening, mechanical/thermal, V&V - every product line consumes this. | D8: 12 | E8: 28 | F8: 17 | G8: 12 | H8: 7 | I8: 3.5 | J8: 2.5 | K8: 1.3 | L8: 1.3 | M8: 1.3
B9: Embedded & Mission Software (RTOS, mission systems, C2) | C9: RTOS, mission computer SW, C2 interfaces, cybersecurity, MOSA/FACE - productized early, shipped with ESM and Mil-AI in Y1. | D9: 6 | E9: 42 | F9: 17 | G9: 9 | H9: 5 | I9: 2.5 | J9: 1.3 | K9: 1.3 | L9: 1.3 | M9: 0
B10: AI / ML (computer vision, sensor fusion, autonomy, MLOps) | C10: CV, sensor fusion, autonomy stack, MLOps - fastest-growing module; heaviest reuse in C-UAS, UAS, AUV/USV, MilAI. | D10: 10 | E10: 65 | F10: 35 | G10: 22 | H10: 12 | I10: 7 | J10: 3.5 | K10: 1.8 | L10: 1.8 | M10: 1.8
B11: Total platform NRE | C11: Sum of all module investment | D11: =SUM(D6:D10) -> 101 | E11: =SUM(E6:E10) -> 210 | F11: =SUM(F6:F10) -> 107 | G11: =SUM(G6:G10) -> 69 | H11: =SUM(H6:H10) -> 38 | I11: =SUM(I6:I10) -> 20.5 | J11: =SUM(J6:J10) -> 11.3 | K11: =SUM(K6:K10) -> 8.4 | ... M11: =SUM(M6:M10) -> 3.1
B12: Cumulative platform NRE | D12: =D11 -> 101 | E12: =D12+E11 -> 311 | F12: =E12+F11 -> 418 | G12: =F12+G11 -> 487 | H12: =G12+H11 -> 525 | I12: =H12+I11 -> 545.5 | J12: =I12+J11 -> 556.8 | K12: =J12+K11 -> 565.2 | L12: =K12+L11 -> 572.1 | M12: =L12+M11 -> 575.2
B14: B. Platform module maturity (0..1) × global reuse multiplier
B15: RF / Microwave (T/R modules, receivers, antennas, GaN MMICs) | C15: TRL-style progression - used as reuse strength | D15: 0.55 | E15: 0.7 | F15: 0.82 | G15: 0.9 | H15: 0.94 | I15: 0.96 | J15: 0.97 | K15: 0.98 | L15: 0.99 | M15: 0.99
B16: DSP / Signal Processing (FPGA, SDR, beamforming) | C16: TRL-style progression - used as reuse strength | D16: 0.6 | E16: 0.75 | F16: 0.85 | G16: 0.91 | H16: 0.95 | I16: 0.97 | J16: 0.98 | K16: 0.99 | L16: 0.99 | M16: 0.99
B17: Systems Engineering (mech, thermal, MIL-STD, integration) | C17: TRL-style progression - used as reuse strength | D17: 0.4 | E17: 0.6 | F17: 0.75 | G17: 0.85 | H17: 0.91 | I17: 0.94 | J17: 0.96 | K17: 0.97 | L17: 0.98 | M17: 0.99
B18: Embedded & Mission Software (RTOS, mission systems, C2) | C18: TRL-style progression - used as reuse strength | D18: 0.5 | E18: 0.7 | F18: 0.83 | G18: 0.9 | H18: 0.94 | I18: 0.96 | J18: 0.97 | K18: 0.98 | L18: 0.99 | M18: 0.99
B19: AI / ML (computer vision, sensor fusion, autonomy, MLOps) | C19: TRL-style progression - used as reuse strength | D19: 0.25 | E19: 0.5 | F19: 0.7 | G19: 0.83 | H19: 0.9 | I19: 0.94 | J19: 0.96 | K19: 0.97 | L19: 0.98 | M19: 0.99
B20: C. Effective reuse strength per module (= maturity × multiplier, capped 1)
B21: RF / Microwave (T/R modules, receivers, antennas, GaN MMICs) - effective | D21: =MIN(1,D15*Assumptions!$C$26) -> 0.55 | E21: =MIN(1,E15*Assumptions!$C$26) -> 0.7 | F21: =MIN(1,F15*Assumptions!$C$26) -> 0.82 | G21: =MIN(1,G15*Assumptions!$C$26) -> 0.9 | H21: =MIN(1,H15*Assumptions!$C$26) -> 0.94 | I21: =MIN(1,I15*Assumptions!$C$26) -> 0.96 | J21: =MIN(1,J15*Assumptions!$C$26) -> 0.97 | K21: =MIN(1,K15*Assumptions!$C$26) -> 0.98 | ... M21: =MIN(1,M15*Assumptions!$C$26) -> 0.99
B22: DSP / Signal Processing (FPGA, SDR, beamforming) - effective | D22: =MIN(1,D16*Assumptions!$C$26) -> 0.6 | E22: =MIN(1,E16*Assumptions!$C$26) -> 0.75 | F22: =MIN(1,F16*Assumptions!$C$26) -> 0.85 | G22: =MIN(1,G16*Assumptions!$C$26) -> 0.91 | H22: =MIN(1,H16*Assumptions!$C$26) -> 0.95 | I22: =MIN(1,I16*Assumptions!$C$26) -> 0.97 | J22: =MIN(1,J16*Assumptions!$C$26) -> 0.98 | K22: =MIN(1,K16*Assumptions!$C$26) -> 0.99 | ... M22: =MIN(1,M16*Assumptions!$C$26) -> 0.99
B23: Systems Engineering (mech, thermal, MIL-STD, integration) - effective | D23: =MIN(1,D17*Assumptions!$C$26) -> 0.4 | E23: =MIN(1,E17*Assumptions!$C$26) -> 0.6 | F23: =MIN(1,F17*Assumptions!$C$26) -> 0.75 | G23: =MIN(1,G17*Assumptions!$C$26) -> 0.85 | H23: =MIN(1,H17*Assumptions!$C$26) -> 0.91 | I23: =MIN(1,I17*Assumptions!$C$26) -> 0.94 | J23: =MIN(1,J17*Assumptions!$C$26) -> 0.96 | K23: =MIN(1,K17*Assumptions!$C$26) -> 0.97 | ... M23: =MIN(1,M17*Assumptions!$C$26) -> 0.99
B24: Embedded & Mission Software (RTOS, mission systems, C2) - effective | D24: =MIN(1,D18*Assumptions!$C$26) -> 0.5 | E24: =MIN(1,E18*Assumptions!$C$26) -> 0.7 | F24: =MIN(1,F18*Assumptions!$C$26) -> 0.83 | G24: =MIN(1,G18*Assumptions!$C$26) -> 0.9 | H24: =MIN(1,H18*Assumptions!$C$26) -> 0.94 | I24: =MIN(1,I18*Assumptions!$C$26) -> 0.96 | J24: =MIN(1,J18*Assumptions!$C$26) -> 0.97 | K24: =MIN(1,K18*Assumptions!$C$26) -> 0.98 | ... M24: =MIN(1,M18*Assumptions!$C$26) -> 0.99
B25: AI / ML (computer vision, sensor fusion, autonomy, MLOps) - effective | D25: =MIN(1,D19*Assumptions!$C$26) -> 0.25 | E25: =MIN(1,E19*Assumptions!$C$26) -> 0.5 | F25: =MIN(1,F19*Assumptions!$C$26) -> 0.7 | G25: =MIN(1,G19*Assumptions!$C$26) -> 0.83 | H25: =MIN(1,H19*Assumptions!$C$26) -> 0.9 | I25: =MIN(1,I19*Assumptions!$C$26) -> 0.94 | J25: =MIN(1,J19*Assumptions!$C$26) -> 0.96 | K25: =MIN(1,K19*Assumptions!$C$26) -> 0.97 | ... M25: =MIN(1,M19*Assumptions!$C$26) -> 0.99

Sheet R&D_Buckets
B2: R&D Buckets - Evidence-led Platform NRE Capitalisation
B3: Policy | C3: Evidence-led: research is expensed; only qualifying development is capitalised; non-eligible development is expensed.
B5: A. Source Platform NRE by module (from Platform sheet)
B6: Module | C6: Source / Check | D6: Y1 | E6: Y2 | F6: Y3 | G6: Y4 | H6: Y5 | I6: Y6 | J6: Y7 | K6: Y8 | L6: Y9 | M6: Y10
B7: RF / Microwave | C7: =Platform!C6 -> X/S/Ku-band T/R modules, GaN PA/LNA, beamforming, antenna design - carried over from ESM, now extended to AESA and C-UAS. | D7: =Platform!D6 -> 45 | E7: =Platform!E6 -> 45 | F7: =Platform!F6 -> 25 | G7: =Platform!G6 -> 18 | H7: =Platform!H6 -> 9 | I7: =Platform!I6 -> 4.5 | J7: =Platform!J6 -> 2.5 | ... M7: =Platform!M6 -> 0
B8: DSP / Signal Processing | C8: =Platform!C7 -> Real-time FPGA pipelines, SDR firmware, DBF - already fielded in ESM; reused across Radar, C-UAS, AI sensor fusion. | D8: =Platform!D7 -> 28 | E8: =Platform!E7 -> 30 | F8: =Platform!F7 -> 13 | G8: =Platform!G7 -> 8 | H8: =Platform!H7 -> 5 | I8: =Platform!I7 -> 3 | J8: =Platform!J7 -> 1.5 | ... M8: =Platform!M7 -> 0
B9: Systems Engineering | C9: =Platform!C8 -> MIL-STD-810/461/704 hardening, mechanical/thermal, V&V - every product line consumes this. | D9: =Platform!D8 -> 12 | E9: =Platform!E8 -> 28 | F9: =Platform!F8 -> 17 | G9: =Platform!G8 -> 12 | H9: =Platform!H8 -> 7 | I9: =Platform!I8 -> 3.5 | J9: =Platform!J8 -> 2.5 | ... M9: =Platform!M8 -> 1.3
B10: Embedded & Mission Software | C10: =Platform!C9 -> RTOS, mission computer SW, C2 interfaces, cybersecurity, MOSA/FACE - productized early, shipped with ESM and Mil-AI in Y1. | D10: =Platform!D9 -> 6 | E10: =Platform!E9 -> 42 | F10: =Platform!F9 -> 17 | G10: =Platform!G9 -> 9 | H10: =Platform!H9 -> 5 | I10: =Platform!I9 -> 2.5 | J10: =Platform!J9 -> 1.3 | ... M10: =Platform!M9 -> 0
B11: AI / ML | C11: =Platform!C10 -> CV, sensor fusion, autonomy stack, MLOps - fastest-growing module; heaviest reuse in C-UAS, UAS, AUV/USV, MilAI. | D11: =Platform!D10 -> 10 | E11: =Platform!E10 -> 65 | F11: =Platform!F10 -> 35 | G11: =Platform!G10 -> 22 | H11: =Platform!H10 -> 12 | I11: =Platform!I10 -> 7 | J11: =Platform!J10 -> 3.5 | ... M11: =Platform!M10 -> 1.8
B12: Total Platform NRE | C12: Check to Platform!D11:M11 | D12: =SUM(D7:D11) -> 101 | E12: =SUM(E7:E11) -> 210 | F12: =SUM(F7:F11) -> 107 | G12: =SUM(G7:G11) -> 69 | H12: =SUM(H7:H11) -> 38 | I12: =SUM(I7:I11) -> 20.5 | J12: =SUM(J7:J11) -> 11.3 | K12: =SUM(K7:K11) -> 8.4 | ... M12: =SUM(M7:M11) -> 3.1
B14: B. Research - expensed % (input)
B15: Module | C15: Accounting treatment | D15: Y1 | E15: Y2 | F15: Y3 | G15: Y4 | H15: Y5 | I15: Y6 | J15: Y7 | K15: Y8 | L15: Y9 | M15: Y10
B16: RF / Microwave | C16: Research phase - expense immediately | D16: 0.5 | E16: 0.35 | F16: 0.2 | G16: 0.15 | H16: 0.1 | I16: 0.1 | J16: 0.05 | K16: 0.05 | L16: 0.05 | M16: 0.05
B17: DSP / Signal Processing | C17: Research phase - expense immediately | D17: 0.45 | E17: 0.3 | F17: 0.18 | G17: 0.12 | H17: 0.08 | I17: 0.05 | J17: 0.05 | K17: 0.05 | L17: 0.05 | M17: 0.05
B18: Systems Engineering | C18: Research phase - expense immediately | D18: 0.35 | E18: 0.25 | F18: 0.15 | G18: 0.1 | H18: 0.08 | I18: 0.05 | J18: 0.05 | K18: 0.05 | L18: 0.05 | M18: 0.05
B19: Embedded & Mission Software | C19: Research phase - expense immediately | D19: 0.4 | E19: 0.25 | F19: 0.15 | G19: 0.1 | H19: 0.08 | I19: 0.05 | J19: 0.05 | K19: 0.05 | L19: 0.05 | M19: 0.05
B20: AI / ML | C20: Research phase - expense immediately | D20: 0.65 | E20: 0.5 | F20: 0.35 | G20: 0.25 | H20: 0.18 | I20: 0.12 | J20: 0.1 | K20: 0.08 | L20: 0.08 | M20: 0.08
B23: C. Development - capitalised % (input)
B24: Module | C24: Accounting treatment | D24: Y1 | E24: Y2 | F24: Y3 | G24: Y4 | H24: Y5 | I24: Y6 | J24: Y7 | K24: Y8 | L24: Y9 | M24: Y10
B25: RF / Microwave | C25: Qualifying development - capitalise | D25: 0.25 | E25: 0.45 | F25: 0.6 | G25: 0.65 | H25: 0.7 | I25: 0.7 | J25: 0.75 | K25: 0.75 | L25: 0.75 | M25: 0.75
B26: DSP / Signal Processing | C26: Qualifying development - capitalise | D26: 0.3 | E26: 0.5 | F26: 0.62 | G26: 0.68 | H26: 0.72 | I26: 0.75 | J26: 0.75 | K26: 0.75 | L26: 0.75 | M26: 0.75
B27: Systems Engineering | C27: Qualifying development - capitalise | D27: 0.25 | E27: 0.4 | F27: 0.55 | G27: 0.65 | H27: 0.7 | I27: 0.72 | J27: 0.75 | K27: 0.75 | L27: 0.75 | M27: 0.75
B28: Embedded & Mission Software | C28: Qualifying development - capitalise | D28: 0.35 | E28: 0.55 | F28: 0.65 | G28: 0.7 | H28: 0.75 | I28: 0.78 | J28: 0.8 | K28: 0.8 | L28: 0.8 | M28: 0.8
B29: AI / ML | C29: Qualifying development - capitalise | D29: 0.15 | E29: 0.3 | F29: 0.45 | G29: 0.55 | H29: 0.62 | I29: 0.68 | J29: 0.7 | K29: 0.72 | L29: 0.72 | M29: 0.72
B32: D. Development - expensed / not capitalisation eligible % (calculated)
B33: Module | C33: Formula | D33: Y1 | E33: Y2 | F33: Y3 | G33: Y4 | H33: Y5 | I33: Y6 | J33: Y7 | K33: Y8 | L33: Y9 | M33: Y10
B34: RF / Microwave | C34: 1 - Research% - Capitalised% | D34: =1-D16-D25 -> 0.25 | E34: =1-E16-E25 -> 0.2 | F34: =1-F16-F25 -> 0.2 | G34: =1-G16-G25 -> 0.2 | H34: =1-H16-H25 -> 0.2 | I34: =1-I16-I25 -> 0.2 | J34: =1-J16-J25 -> 0.2 | K34: =1-K16-K25 -> 0.2 | ... M34: =1-M16-M25 -> 0.2
B35: DSP / Signal Processing | C35: 1 - Research% - Capitalised% | D35: =1-D17-D26 -> 0.25 | E35: =1-E17-E26 -> 0.2 | F35: =1-F17-F26 -> 0.2 | G35: =1-G17-G26 -> 0.2 | H35: =1-H17-H26 -> 0.2 | I35: =1-I17-I26 -> 0.2 | J35: =1-J17-J26 -> 0.2 | K35: =1-K17-K26 -> 0.2 | ... M35: =1-M17-M26 -> 0.2
B36: Systems Engineering | C36: 1 - Research% - Capitalised% | D36: =1-D18-D27 -> 0.4 | E36: =1-E18-E27 -> 0.35 | F36: =1-F18-F27 -> 0.3 | G36: =1-G18-G27 -> 0.25 | H36: =1-H18-H27 -> 0.22 | I36: =1-I18-I27 -> 0.23 | J36: =1-J18-J27 -> 0.2 | K36: =1-K18-K27 -> 0.2 | ... M36: =1-M18-M27 -> 0.2
B37: Embedded & Mission Software | C37: 1 - Research% - Capitalised% | D37: =1-D19-D28 -> 0.25 | E37: =1-E19-E28 -> 0.2 | F37: =1-F19-F28 -> 0.2 | G37: =1-G19-G28 -> 0.2 | H37: =1-H19-H28 -> 0.17 | I37: =1-I19-I28 -> 0.17 | J37: =1-J19-J28 -> 0.15 | K37: =1-K19-K28 -> 0.15 | ... M37: =1-M19-M28 -> 0.15
B38: AI / ML | C38: 1 - Research% - Capitalised% | D38: =1-D20-D29 -> 0.2 | E38: =1-E20-E29 -> 0.2 | F38: =1-F20-F29 -> 0.2 | G38: =1-G20-G29 -> 0.2 | H38: =1-H20-H29 -> 0.2 | I38: =1-I20-I29 -> 0.2 | J38: =1-J20-J29 -> 0.2 | K38: =1-K20-K29 -> 0.2 | ... M38: =1-M20-M29 -> 0.2
B41: E. Bucket % check (must equal 100%)
B42: Module | C42: Check | D42: Y1 | E42: Y2 | F42: Y3 | G42: Y4 | H42: Y5 | I42: Y6 | J42: Y7 | K42: Y8 | L42: Y9 | M42: Y10
B43: RF / Microwave | C43: Research + capitalised + non-eligible | D43: =D16+D25+D34 -> 1 | E43: =E16+E25+E34 -> 1 | F43: =F16+F25+F34 -> 1 | G43: =G16+G25+G34 -> 1 | H43: =H16+H25+H34 -> 1 | I43: =I16+I25+I34 -> 1 | J43: =J16+J25+J34 -> 1 | K43: =K16+K25+K34 -> 1 | ... M43: =M16+M25+M34 -> 1
B44: DSP / Signal Processing | C44: Research + capitalised + non-eligible | D44: =D17+D26+D35 -> 1 | E44: =E17+E26+E35 -> 1 | F44: =F17+F26+F35 -> 1 | G44: =G17+G26+G35 -> 1 | H44: =H17+H26+H35 -> 1 | I44: =I17+I26+I35 -> 1 | J44: =J17+J26+J35 -> 1 | K44: =K17+K26+K35 -> 1 | ... M44: =M17+M26+M35 -> 1
B45: Systems Engineering | C45: Research + capitalised + non-eligible | D45: =D18+D27+D36 -> 1 | E45: =E18+E27+E36 -> 1 | F45: =F18+F27+F36 -> 1 | G45: =G18+G27+G36 -> 1 | H45: =H18+H27+H36 -> 1 | I45: =I18+I27+I36 -> 1 | J45: =J18+J27+J36 -> 1 | K45: =K18+K27+K36 -> 1 | ... M45: =M18+M27+M36 -> 1
B46: Embedded & Mission Software | C46: Research + capitalised + non-eligible | D46: =D19+D28+D37 -> 1 | E46: =E19+E28+E37 -> 1 | F46: =F19+F28+F37 -> 1 | G46: =G19+G28+G37 -> 1 | H46: =H19+H28+H37 -> 1 | I46: =I19+I28+I37 -> 1 | J46: =J19+J28+J37 -> 1 | K46: =K19+K28+K37 -> 1 | ... M46: =M19+M28+M37 -> 1
B47: AI / ML | C47: Research + capitalised + non-eligible | D47: =D20+D29+D38 -> 1 | E47: =E20+E29+E38 -> 1 | F47: =F20+F29+F38 -> 1 | G47: =G20+G29+G38 -> 1 | H47: =H20+H29+H38 -> 1 | I47: =I20+I29+I38 -> 1 | J47: =J20+J29+J38 -> 1 | K47: =K20+K29+K38 -> 1 | ... M47: =M20+M29+M38 -> 1
B49: Check status | C49: OK if all years/modules = 100% | D49: =IF(AND(D43=1,D44=1,D45=1,D46=1,D47=1),"OK","CHECK") -> OK | E49: =IF(AND(E43=1,E44=1,E45=1,E46=1,E47=1),"OK","CHECK") -> OK | F49: =IF(AND(F43=1,F44=1,F45=1,F46=1,F47=1),"OK","CHECK") -> OK | G49: =IF(AND(G43=1,G44=1,G45=1,G46=1,G47=1),"OK","CHECK") -> OK | H49: =IF(AND(H43=1,H44=1,H45=1,H46=1,H47=1),"OK","CHECK") -> OK | I49: =IF(AND(I43=1,I44=1,I45=1,I46=1,I47=1),"OK","CHECK") -> OK | J49: =IF(AND(J43=1,J44=1,J45=1,J46=1,J47=1),"OK","CHECK") -> OK | K49: =IF(AND(K43=1,K44=1,K45=1,K46=1,K47=1),"OK","CHECK") -> OK | ... M49: =IF(AND(M43=1,M44=1,M45=1,M46=1,M47=1),"OK","CHECK") -> OK
B52: F. Research - expensed amount (INR Cr)
B53: Module | C53: Formula | D53: Y1 | E53: Y2 | F53: Y3 | G53: Y4 | H53: Y5 | I53: Y6 | J53: Y7 | K53: Y8 | L53: Y9 | M53: Y10
B54: RF / Microwave | C54: Source NRE x Research% | D54: =D7*D16 -> 22.5 | E54: =E7*E16 -> 15.75 | F54: =F7*F16 -> 5 | G54: =G7*G16 -> 2.7 | H54: =H7*H16 -> 0.9 | I54: =I7*I16 -> 0.45 | J54: =J7*J16 -> 0.125 | K54: =K7*K16 -> 0.125 | ... M54: =M7*M16 -> 0
B55: DSP / Signal Processing | C55: Source NRE x Research% | D55: =D8*D17 -> 12.6 | E55: =E8*E17 -> 9 | F55: =F8*F17 -> 2.34 | G55: =G8*G17 -> 0.96 | H55: =H8*H17 -> 0.4 | I55: =I8*I17 -> 0.15 | J55: =J8*J17 -> 0.075 | K55: =K8*K17 -> 0.075 | ... M55: =M8*M17 -> 0
B56: Systems Engineering | C56: Source NRE x Research% | D56: =D9*D18 -> 4.2 | E56: =E9*E18 -> 7 | F56: =F9*F18 -> 2.55 | G56: =G9*G18 -> 1.2 | H56: =H9*H18 -> 0.56 | I56: =I9*I18 -> 0.175 | J56: =J9*J18 -> 0.125 | K56: =K9*K18 -> 0.065 | ... M56: =M9*M18 -> 0.065
B57: Embedded & Mission Software | C57: Source NRE x Research% | D57: =D10*D19 -> 2.4 | E57: =E10*E19 -> 10.5 | F57: =F10*F19 -> 2.55 | G57: =G10*G19 -> 0.9 | H57: =H10*H19 -> 0.4 | I57: =I10*I19 -> 0.125 | J57: =J10*J19 -> 0.065 | K57: =K10*K19 -> 0.065 | ... M57: =M10*M19 -> 0
B58: AI / ML | C58: Source NRE x Research% | D58: =D11*D20 -> 6.5 | E58: =E11*E20 -> 32.5 | F58: =F11*F20 -> 12.25 | G58: =G11*G20 -> 5.5 | H58: =H11*H20 -> 2.16 | I58: =I11*I20 -> 0.84 | J58: =J11*J20 -> 0.35 | K58: =K11*K20 -> 0.144 | ... M58: =M11*M20 -> 0.144
B60: Total research expensed | D60: =SUM(D54:D58) -> 48.2 | E60: =SUM(E54:E58) -> 74.75 | F60: =SUM(F54:F58) -> 24.69 | G60: =SUM(G54:G58) -> 11.26 | H60: =SUM(H54:H58) -> 4.42 | I60: =SUM(I54:I58) -> 1.74 | J60: =SUM(J54:J58) -> 0.74 | K60: =SUM(K54:K58) -> 0.474 | ... M60: =SUM(M54:M58) -> 0.209
B63: G. Development - capitalised amount (INR Cr)
B64: Module | C64: Formula | D64: Y1 | E64: Y2 | F64: Y3 | G64: Y4 | H64: Y5 | I64: Y6 | J64: Y7 | K64: Y8 | L64: Y9 | M64: Y10
B65: RF / Microwave | C65: Source NRE x Capitalised% | D65: =D7*D25 -> 11.25 | E65: =E7*E25 -> 20.25 | F65: =F7*F25 -> 15 | G65: =G7*G25 -> 11.7 | H65: =H7*H25 -> 6.3 | I65: =I7*I25 -> 3.15 | J65: =J7*J25 -> 1.875 | K65: =K7*K25 -> 1.875 | ... M65: =M7*M25 -> 0
B66: DSP / Signal Processing | C66: Source NRE x Capitalised% | D66: =D8*D26 -> 8.4 | E66: =E8*E26 -> 15 | F66: =F8*F26 -> 8.06 | G66: =G8*G26 -> 5.44 | H66: =H8*H26 -> 3.6 | I66: =I8*I26 -> 2.25 | J66: =J8*J26 -> 1.125 | K66: =K8*K26 -> 1.125 | ... M66: =M8*M26 -> 0
B67: Systems Engineering | C67: Source NRE x Capitalised% | D67: =D9*D27 -> 3 | E67: =E9*E27 -> 11.2 | F67: =F9*F27 -> 9.35 | G67: =G9*G27 -> 7.8 | H67: =H9*H27 -> 4.9 | I67: =I9*I27 -> 2.52 | J67: =J9*J27 -> 1.875 | K67: =K9*K27 -> 0.975 | ... M67: =M9*M27 -> 0.975
B68: Embedded & Mission Software | C68: Source NRE x Capitalised% | D68: =D10*D28 -> 2.1 | E68: =E10*E28 -> 23.1 | F68: =F10*F28 -> 11.05 | G68: =G10*G28 -> 6.3 | H68: =H10*H28 -> 3.75 | I68: =I10*I28 -> 1.95 | J68: =J10*J28 -> 1.04 | K68: =K10*K28 -> 1.04 | ... M68: =M10*M28 -> 0
B69: AI / ML | C69: Source NRE x Capitalised% | D69: =D11*D29 -> 1.5 | E69: =E11*E29 -> 19.5 | F69: =F11*F29 -> 15.75 | G69: =G11*G29 -> 12.1 | H69: =H11*H29 -> 7.44 | I69: =I11*I29 -> 4.76 | J69: =J11*J29 -> 2.45 | K69: =K11*K29 -> 1.296 | ... M69: =M11*M29 -> 1.296
B71: Total development capitalised | D71: =SUM(D65:D69) -> 26.25 | E71: =SUM(E65:E69) -> 89.05 | F71: =SUM(F65:F69) -> 59.21 | G71: =SUM(G65:G69) -> 43.34 | H71: =SUM(H65:H69) -> 25.99 | I71: =SUM(I65:I69) -> 14.63 | J71: =SUM(J65:J69) -> 8.365 | K71: =SUM(K65:K69) -> 6.311 | ... M71: =SUM(M65:M69) -> 2.271
B74: H. Development - expensed / not capitalisation eligible amount (INR Cr)
B75: Module | C75: Formula | D75: Y1 | E75: Y2 | F75: Y3 | G75: Y4 | H75: Y5 | I75: Y6 | J75: Y7 | K75: Y8 | L75: Y9 | M75: Y10
B76: RF / Microwave | C76: Source NRE x Non-eligible development% | D76: =D7*D34 -> 11.25 | E76: =E7*E34 -> 9 | F76: =F7*F34 -> 5 | G76: =G7*G34 -> 3.6 | H76: =H7*H34 -> 1.8 | I76: =I7*I34 -> 0.9 | J76: =J7*J34 -> 0.5 | K76: =K7*K34 -> 0.5 | ... M76: =M7*M34 -> 0
B77: DSP / Signal Processing | C77: Source NRE x Non-eligible development% | D77: =D8*D35 -> 7 | E77: =E8*E35 -> 6 | F77: =F8*F35 -> 2.6 | G77: =G8*G35 -> 1.6 | H77: =H8*H35 -> 1 | I77: =I8*I35 -> 0.6 | J77: =J8*J35 -> 0.3 | K77: =K8*K35 -> 0.3 | ... M77: =M8*M35 -> 0
B78: Systems Engineering | C78: Source NRE x Non-eligible development% | D78: =D9*D36 -> 4.8 | E78: =E9*E36 -> 9.8 | F78: =F9*F36 -> 5.1 | G78: =G9*G36 -> 3 | H78: =H9*H36 -> 1.54 | I78: =I9*I36 -> 0.805 | J78: =J9*J36 -> 0.5 | K78: =K9*K36 -> 0.26 | ... M78: =M9*M36 -> 0.26
B79: Embedded & Mission Software | C79: Source NRE x Non-eligible development% | D79: =D10*D37 -> 1.5 | E79: =E10*E37 -> 8.4 | F79: =F10*F37 -> 3.4 | G79: =G10*G37 -> 1.8 | H79: =H10*H37 -> 0.85 | I79: =I10*I37 -> 0.425 | J79: =J10*J37 -> 0.195 | K79: =K10*K37 -> 0.195 | ... M79: =M10*M37 -> 0
B80: AI / ML | C80: Source NRE x Non-eligible development% | D80: =D11*D38 -> 2 | E80: =E11*E38 -> 13 | F80: =F11*F38 -> 7 | G80: =G11*G38 -> 4.4 | H80: =H11*H38 -> 2.4 | I80: =I11*I38 -> 1.4 | J80: =J11*J38 -> 0.7 | K80: =K11*K38 -> 0.36 | ... M80: =M11*M38 -> 0.36
B82: Total development expensed / not eligible | D82: =SUM(D76:D80) -> 26.55 | E82: =SUM(E76:E80) -> 46.2 | F82: =SUM(F76:F80) -> 23.1 | G82: =SUM(G76:G80) -> 14.4 | H82: =SUM(H76:H80) -> 7.59 | I82: =SUM(I76:I80) -> 4.13 | J82: =SUM(J76:J80) -> 2.195 | K82: =SUM(K76:K80) -> 1.615 | ... M82: =SUM(M76:M80) -> 0.62
B85: I. Financial statement outputs
B86: Output | C86: Formula / destination | D86: Y1 | E86: Y2 | F86: Y3 | G86: Y4 | H86: Y5 | I86: Y6 | J86: Y7 | K86: Y8 | L86: Y9 | M86: Y10
B87: Total book-expensed Platform R&D | C87: Research expensed + development expensed / not eligible | D87: =SUM(D60,D82) -> 74.75 | E87: =SUM(E60,E82) -> 120.95 | F87: =SUM(F60,F82) -> 47.79 | G87: =SUM(G60,G82) -> 25.66 | H87: =SUM(H60,H82) -> 12.01 | I87: =SUM(I60,I82) -> 5.87 | J87: =SUM(J60,J82) -> 2.935 | K87: =SUM(K60,K82) -> 2.089 | ... M87: =SUM(M60,M82) -> 0.829
B88: Capitalised R&D additions | C88: Feeds R&D_NRE row 16 and CashFlow CFI | D88: =D71 -> 26.25 | E88: =E71 -> 89.05 | F88: =F71 -> 59.21 | G88: =G71 -> 43.34 | H88: =H71 -> 25.99 | I88: =I71 -> 14.63 | J88: =J71 -> 8.365 | K88: =K71 -> 6.311 | ... M88: =M71 -> 2.271
B89: Weighted Platform R&D capitalisation % | C89: Capitalised R&D additions / Platform NRE | D89: =IFERROR(D88/D12,0) -> 0.25990099 | E89: =IFERROR(E88/E12,0) -> 0.42404762 | F89: =IFERROR(F88/F12,0) -> 0.55336449 | G89: =IFERROR(G88/G12,0) -> 0.62811594 | H89: =IFERROR(H88/H12,0) -> 0.68394737 | I89: =IFERROR(I88/I12,0) -> 0.71365854 | J89: =IFERROR(J88/J12,0) -> 0.74026549 | K89: =IFERROR(K88/K12,0) -> 0.75130952 | ... M89: =IFERROR(M88/M12,0) -> 0.73258065
B90: Amortisation of capitalised R&D | C90: Straight-line using Assumptions!C58 | D90: =SUM(OFFSET(D$88,0,-MIN(COLUMN(D$88)-COLUMN($D$88),Assumptions!$C$58-1),1,MIN(COLUMN(D$88)-COLUMN($D$88)+1,Assumptions!$C$58)))/Assumptions!$C$58 -> 4.375 | E90: =SUM(OFFSET(E$88,0,-MIN(COLUMN(E$88)-COLUMN($D$88),Assumptions!$C$58-1),1,MIN(COLUMN(E$88)-COLUMN($D$88)+1,Assumptions!$C$58)))/Assumptions!$C$58 -> 19.216667 | F90: =SUM(OFFSET(F$88,0,-MIN(COLUMN(F$88)-COLUMN($D$88),Assumptions!$C$58-1),1,MIN(COLUMN(F$88)-COLUMN($D$88)+1,Assumptions!$C$58)))/Assumptions!$C$58 -> 29.085 | G90: =SUM(OFFSET(G$88,0,-MIN(COLUMN(G$88)-COLUMN($D$88),Assumptions!$C$58-1),1,MIN(COLUMN(G$88)-COLUMN($D$88)+1,Assumptions!$C$58)))/Assumptions!$C$58 -> 36.308333 | H90: =SUM(OFFSET(H$88,0,-MIN(COLUMN(H$88)-COLUMN($D$88),Assumptions!$C$58-1),1,MIN(COLUMN(H$88)-COLUMN($D$88)+1,Assumptions!$C$58)))/Assumptions!$C$58 -> 40.64 | I90: =SUM(OFFSET(I$88,0,-MIN(COLUMN(I$88)-COLUMN($D$88),Assumptions!$C$58-1),1,MIN(COLUMN(I$88)-COLUMN($D$88)+1,Assumptions!$C$58)))/Assumptions!$C$58 -> 43.078333 | J90: =SUM(OFFSET(J$88,0,-MIN(COLUMN(J$88)-COLUMN($D$88),Assumptions!$C$58-1),1,MIN(COLUMN(J$88)-COLUMN($D$88)+1,Assumptions!$C$58)))/Assumptions!$C$58 -> 40.0975 | K90: =SUM(OFFSET(K$88,0,-MIN(COLUMN(K$88)-COLUMN($D$88),Assumptions!$C$58-1),1,MIN(COLUMN(K$88)-COLUMN($D$88)+1,Assumptions!$C$58)))/Assumptions!$C$58 -> 26.307667 | ... M90: =SUM(OFFSET(M$88,0,-MIN(COLUMN(M$88)-COLUMN($D$88),Assumptions!$C$58-1),1,MIN(COLUMN(M$88)-COLUMN($D$88)+1,Assumptions!$C$58)))/Assumptions!$C$58 -> 10.458833
B91: Gross capitalised R&D | C91: Cumulative capitalised development | D91: =SUM($D$88:D$88) -> 26.25 | E91: =SUM($D$88:E$88) -> 115.3 | F91: =SUM($D$88:F$88) -> 174.51 | G91: =SUM($D$88:G$88) -> 217.85 | H91: =SUM($D$88:H$88) -> 243.84 | I91: =SUM($D$88:I$88) -> 258.47 | J91: =SUM($D$88:J$88) -> 266.835 | K91: =SUM($D$88:K$88) -> 273.146 | ... M91: =SUM($D$88:M$88) -> 280.603
B92: Accumulated amortisation | C92: Cumulative amortisation | D92: =MIN(D91,SUM($D$90:D$90)) -> 4.375 | E92: =MIN(E91,SUM($D$90:E$90)) -> 23.591667 | F92: =MIN(F91,SUM($D$90:F$90)) -> 52.676667 | G92: =MIN(G91,SUM($D$90:G$90)) -> 88.985 | H92: =MIN(H91,SUM($D$90:H$90)) -> 129.625 | I92: =MIN(I91,SUM($D$90:I$90)) -> 172.70333 | J92: =MIN(J91,SUM($D$90:J$90)) -> 212.80083 | K92: =MIN(K91,SUM($D$90:K$90)) -> 239.1085 | ... M92: =MIN(M91,SUM($D$90:M$90)) -> 266.871
B93: Net capitalised R&D intangible asset | C93: Gross capitalised R&D - accumulated amortisation | D93: =D91-D92 -> 21.875 | E93: =E91-E92 -> 91.708333 | F93: =F91-F92 -> 121.83333 | G93: =G91-G92 -> 128.865 | H93: =H91-H92 -> 114.215 | I93: =I91-I92 -> 85.766667 | J93: =J91-J92 -> 54.034167 | K93: =K91-K92 -> 34.0375 | ... M93: =M91-M92 -> 13.732
B94: Bucketed Platform NRE check | C94: Should be zero | D94: =D60+D71+D82-D12 -> 0 | E94: =E60+E71+E82-E12 -> 0 | F94: =F60+F71+F82-F12 -> 0 | G94: =G60+G71+G82-G12 -> 0 | H94: =H60+H71+H82-H12 -> 0 | I94: =I60+I71+I82-I12 -> 0 | J94: =J60+J71+J82-J12 -> 0 | K94: =K60+K71+K82-K12 -> 0 | ... M94: =M60+M71+M82-M12 -> 0
B97: J. Tax bridge memo (for P&L tax section)
B98: Output | C98: Formula / destination | D98: Y1 | E98: Y2 | F98: Y3 | G98: Y4 | H98: Y5 | I98: Y6 | J98: Y7 | K98: Y8 | L98: Y9 | M98: Y10
B99: Book amortisation add-back | C99: Added back to book PBT for tax-basis PBT | D99: ='R&D_NRE'!D18 -> 4.375 | E99: ='R&D_NRE'!E18 -> 19.216667 | F99: ='R&D_NRE'!F18 -> 29.085 | G99: ='R&D_NRE'!G18 -> 36.308333 | H99: ='R&D_NRE'!H18 -> 40.64 | I99: ='R&D_NRE'!I18 -> 43.078333 | J99: ='R&D_NRE'!J18 -> 40.0975 | K99: ='R&D_NRE'!K18 -> 26.307667 | ... M99: ='R&D_NRE'!M18 -> 10.458833
B100: Eligible capitalised development R&D deduction | C100: Deducted in tax-basis PBT subject to CA review | D100: ='R&D_NRE'!D16 -> 26.25 | E100: ='R&D_NRE'!E16 -> 89.05 | F100: ='R&D_NRE'!F16 -> 59.21 | G100: ='R&D_NRE'!G16 -> 43.34 | H100: ='R&D_NRE'!H16 -> 25.99 | I100: ='R&D_NRE'!I16 -> 14.63 | J100: ='R&D_NRE'!J16 -> 8.365 | K100: ='R&D_NRE'!K16 -> 6.311 | ... M100: ='R&D_NRE'!M16 -> 2.271
B101: Tax-basis PBT after R&D bridge | C101: Book PBT + amortisation add-back - current cap R&D deduction | D101: ='P&L'!C27+D99-D100 -> -356.94325 | E101: ='P&L'!D27+E99-E100 -> -425.54677 | F101: ='P&L'!E27+F99-F100 -> -121.54261 | G101: ='P&L'!F27+G99-G100 -> 92.456419 | H101: ='P&L'!G27+H99-H100 -> 414.77777 | I101: ='P&L'!H27+I99-I100 -> 800.64146 | J101: ='P&L'!I27+J99-J100 -> 1167.7651 | K101: ='P&L'!J27+K99-K100 -> 1566.0274 | ... M101: ='P&L'!L27+M99-M100 -> 2300.7147
B104: Notes | C104: Research is expensed immediately. Capitalised development requires evidence under Ind AS 38 / AS 26. Non-eligible development is expensed for book purposes; tax treatment is modelled separately in the P&L bridge and remains subject to CA review.

Sheet ReuseMatrix
B2: gross x (1 - reuse savings); all values in INR Crores
B4: A. Module composition per vertical (rows sum to 100%) - input
B5: Vertical | C5: M1_RF | D5: M2_DSP | E5: M3_SYSENG | F5: M4_SW | G5: M5_AI | H5: Row total (check)
B6: V1 - AESA Radar | C6: 0.45 | D6: 0.25 | E6: 0.2 | F6: 0.08 | G6: 0.02 | H6: =SUM(C6:G6) -> 1
B7: V2 - Electronic Warfare & SIGINT | C7: 0.4 | D7: 0.3 | E7: 0.15 | F7: 0.1 | G7: 0.05 | H7: =SUM(C7:G7) -> 1
B8: V3 - Counter-UAS (Anti-Drone) | C8: 0.25 | D8: 0.2 | E8: 0.15 | F8: 0.15 | G8: 0.25 | H8: =SUM(C8:G8) -> 1
B9: V4 - MALE-class ISR UAS | C9: 0.05 | D9: 0.1 | E9: 0.4 | F9: 0.25 | G9: 0.2 | H9: =SUM(C9:G9) -> 1
B10: V5 - Autonomous Systems (AUV/USV) | C10: 0.05 | D10: 0.1 | E10: 0.35 | F10: 0.25 | G10: 0.25 | H10: =SUM(C10:G10) -> 1
B11: V6 - Military AI Systems | C11: 0 | D11: 0.1 | E11: 0.05 | F11: 0.25 | G11: 0.6 | H11: =SUM(C11:G11) -> 1
B13: B. Effective reuse savings % per vertical per year (= composition × platform maturity)
B14: Vertical | D14: Y1 | E14: Y2 | F14: Y3 | G14: Y4 | H14: Y5 | I14: Y6 | J14: Y7 | K14: Y8 | L14: Y9 | M14: Y10
B15: V1 - AESA Radar | D15: =C6*Platform!D21+D6*Platform!D22+E6*Platform!D23+F6*Platform!D24+G6*Platform!D25 -> 0.5225 | E15: =C6*Platform!E21+D6*Platform!E22+E6*Platform!E23+F6*Platform!E24+G6*Platform!E25 -> 0.6885 | F15: =C6*Platform!F21+D6*Platform!F22+E6*Platform!F23+F6*Platform!F24+G6*Platform!F25 -> 0.8119 | G15: =C6*Platform!G21+D6*Platform!G22+E6*Platform!G23+F6*Platform!G24+G6*Platform!G25 -> 0.8911 | H15: =C6*Platform!H21+D6*Platform!H22+E6*Platform!H23+F6*Platform!H24+G6*Platform!H25 -> 0.9357 | I15: =C6*Platform!I21+D6*Platform!I22+E6*Platform!I23+F6*Platform!I24+G6*Platform!I25 -> 0.9581 | J15: =C6*Platform!J21+D6*Platform!J22+E6*Platform!J23+F6*Platform!J24+G6*Platform!J25 -> 0.9703 | K15: =C6*Platform!K21+D6*Platform!K22+E6*Platform!K23+F6*Platform!K24+G6*Platform!K25 -> 0.9803 | L15: =C6*Platform!L21+D6*Platform!L22+E6*Platform!L23+F6*Platform!L24+G6*Platform!L25 -> 0.9878 | M15: =C6*Platform!M21+D6*Platform!M22+E6*Platform!M23+F6*Platform!M24+G6*Platform!M25 -> 0.99
B16: V2 - Electronic Warfare & SIGINT | D16: =C7*Platform!D21+D7*Platform!D22+E7*Platform!D23+F7*Platform!D24+G7*Platform!D25 -> 0.5225 | E16: =C7*Platform!E21+D7*Platform!E22+E7*Platform!E23+F7*Platform!E24+G7*Platform!E25 -> 0.69 | F16: =C7*Platform!F21+D7*Platform!F22+E7*Platform!F23+F7*Platform!F24+G7*Platform!F25 -> 0.8135 | G16: =C7*Platform!G21+D7*Platform!G22+E7*Platform!G23+F7*Platform!G24+G7*Platform!G25 -> 0.892 | H16: =C7*Platform!H21+D7*Platform!H22+E7*Platform!H23+F7*Platform!H24+G7*Platform!H25 -> 0.9365 | I16: =C7*Platform!I21+D7*Platform!I22+E7*Platform!I23+F7*Platform!I24+G7*Platform!I25 -> 0.959 | J16: =C7*Platform!J21+D7*Platform!J22+E7*Platform!J23+F7*Platform!J24+G7*Platform!J25 -> 0.971 | K16: =C7*Platform!K21+D7*Platform!K22+E7*Platform!K23+F7*Platform!K24+G7*Platform!K25 -> 0.981 | L16: =C7*Platform!L21+D7*Platform!L22+E7*Platform!L23+F7*Platform!L24+G7*Platform!L25 -> 0.988 | M16: =C7*Platform!M21+D7*Platform!M22+E7*Platform!M23+F7*Platform!M24+G7*Platform!M25 -> 0.99
B17: V3 - Counter-UAS (Anti-Drone) | D17: =C8*Platform!D21+D8*Platform!D22+E8*Platform!D23+F8*Platform!D24+G8*Platform!D25 -> 0.455 | E17: =C8*Platform!E21+D8*Platform!E22+E8*Platform!E23+F8*Platform!E24+G8*Platform!E25 -> 0.645 | F17: =C8*Platform!F21+D8*Platform!F22+E8*Platform!F23+F8*Platform!F24+G8*Platform!F25 -> 0.787 | G17: =C8*Platform!G21+D8*Platform!G22+E8*Platform!G23+F8*Platform!G24+G8*Platform!G25 -> 0.877 | H17: =C8*Platform!H21+D8*Platform!H22+E8*Platform!H23+F8*Platform!H24+G8*Platform!H25 -> 0.9275 | I17: =C8*Platform!I21+D8*Platform!I22+E8*Platform!I23+F8*Platform!I24+G8*Platform!I25 -> 0.954 | J17: =C8*Platform!J21+D8*Platform!J22+E8*Platform!J23+F8*Platform!J24+G8*Platform!J25 -> 0.968 | K17: =C8*Platform!K21+D8*Platform!K22+E8*Platform!K23+F8*Platform!K24+G8*Platform!K25 -> 0.978 | L17: =C8*Platform!L21+D8*Platform!L22+E8*Platform!L23+F8*Platform!L24+G8*Platform!L25 -> 0.986 | M17: =C8*Platform!M21+D8*Platform!M22+E8*Platform!M23+F8*Platform!M24+G8*Platform!M25 -> 0.99
B18: V4 - MALE-class ISR UAS | D18: =C9*Platform!D21+D9*Platform!D22+E9*Platform!D23+F9*Platform!D24+G9*Platform!D25 -> 0.4225 | E18: =C9*Platform!E21+D9*Platform!E22+E9*Platform!E23+F9*Platform!E24+G9*Platform!E25 -> 0.625 | F18: =C9*Platform!F21+D9*Platform!F22+E9*Platform!F23+F9*Platform!F24+G9*Platform!F25 -> 0.7735 | G18: =C9*Platform!G21+D9*Platform!G22+E9*Platform!G23+F9*Platform!G24+G9*Platform!G25 -> 0.867 | H18: =C9*Platform!H21+D9*Platform!H22+E9*Platform!H23+F9*Platform!H24+G9*Platform!H25 -> 0.921 | I18: =C9*Platform!I21+D9*Platform!I22+E9*Platform!I23+F9*Platform!I24+G9*Platform!I25 -> 0.949 | J18: =C9*Platform!J21+D9*Platform!J22+E9*Platform!J23+F9*Platform!J24+G9*Platform!J25 -> 0.965 | K18: =C9*Platform!K21+D9*Platform!K22+E9*Platform!K23+F9*Platform!K24+G9*Platform!K25 -> 0.975 | L18: =C9*Platform!L21+D9*Platform!L22+E9*Platform!L23+F9*Platform!L24+G9*Platform!L25 -> 0.984 | M18: =C9*Platform!M21+D9*Platform!M22+E9*Platform!M23+F9*Platform!M24+G9*Platform!M25 -> 0.99
B19: V5 - Autonomous Systems (AUV/USV) | D19: =C10*Platform!D21+D10*Platform!D22+E10*Platform!D23+F10*Platform!D24+G10*Platform!D25 -> 0.415 | E19: =C10*Platform!E21+D10*Platform!E22+E10*Platform!E23+F10*Platform!E24+G10*Platform!E25 -> 0.62 | F19: =C10*Platform!F21+D10*Platform!F22+E10*Platform!F23+F10*Platform!F24+G10*Platform!F25 -> 0.771 | G19: =C10*Platform!G21+D10*Platform!G22+E10*Platform!G23+F10*Platform!G24+G10*Platform!G25 -> 0.866 | H19: =C10*Platform!H21+D10*Platform!H22+E10*Platform!H23+F10*Platform!H24+G10*Platform!H25 -> 0.9205 | I19: =C10*Platform!I21+D10*Platform!I22+E10*Platform!I23+F10*Platform!I24+G10*Platform!I25 -> 0.949 | J19: =C10*Platform!J21+D10*Platform!J22+E10*Platform!J23+F10*Platform!J24+G10*Platform!J25 -> 0.965 | K19: =C10*Platform!K21+D10*Platform!K22+E10*Platform!K23+F10*Platform!K24+G10*Platform!K25 -> 0.975 | L19: =C10*Platform!L21+D10*Platform!L22+E10*Platform!L23+F10*Platform!L24+G10*Platform!L25 -> 0.984 | M19: =C10*Platform!M21+D10*Platform!M22+E10*Platform!M23+F10*Platform!M24+G10*Platform!M25 -> 0.99
B20: V6 - Military AI Systems | D20: =C11*Platform!D21+D11*Platform!D22+E11*Platform!D23+F11*Platform!D24+G11*Platform!D25 -> 0.355 | E20: =C11*Platform!E21+D11*Platform!E22+E11*Platform!E23+F11*Platform!E24+G11*Platform!E25 -> 0.58 | F20: =C11*Platform!F21+D11*Platform!F22+E11*Platform!F23+F11*Platform!F24+G11*Platform!F25 -> 0.75 | G20: =C11*Platform!G21+D11*Platform!G22+E11*Platform!G23+F11*Platform!G24+G11*Platform!G25 -> 0.8565 | H20: =C11*Platform!H21+D11*Platform!H22+E11*Platform!H23+F11*Platform!H24+G11*Platform!H25 -> 0.9155 | I20: =C11*Platform!I21+D11*Platform!I22+E11*Platform!I23+F11*Platform!I24+G11*Platform!I25 -> 0.948 | J20: =C11*Platform!J21+D11*Platform!J22+E11*Platform!J23+F11*Platform!J24+G11*Platform!J25 -> 0.9645 | K20: =C11*Platform!K21+D11*Platform!K22+E11*Platform!K23+F11*Platform!K24+G11*Platform!K25 -> 0.9745 | L20: =C11*Platform!L21+D11*Platform!L22+E11*Platform!L23+F11*Platform!L24+G11*Platform!L25 -> 0.9835 | M20: =C11*Platform!M21+D11*Platform!M22+E11*Platform!M23+F11*Platform!M24+G11*Platform!M25 -> 0.99
B22: C. Vertical-specific NRE - gross (standalone) vs leveraged (post platform reuse)
B23: Vertical / line | C23: Driver | D23: Y1 | E23: Y2 | F23: Y3 | G23: Y4 | H23: Y5 | I23: Y6 | J23: Y7 | K23: Y8 | L23: Y9 | M23: Y10
B24: AESA Gross NRE | C24: Total ~209 INR Cr over 10y | D24: 62.7 | E24: 62.7 | F24: 37.62 | G24: 20.9 | H24: 10.45 | I24: 6.27 | J24: 4.18 | K24: 2.09 | L24: 1.045 | M24: 1.045
A25: AESA Radar | B25: Gross NRE | C25: Gross = Standalone NRE × Gross Drivers, Net = Gross × (1 − Reuse Savings), where savings from 2026 onwards | D25: =D24*(1-D15) -> 29.93925 | E25: =E24*(1-E15) -> 19.53105 | F25: =F24*(1-F15) -> 7.076322 | G25: =G24*(1-G15) -> 2.27601 | H25: =H24*(1-H15) -> 0.671935 | I25: =I24*(1-I15) -> 0.262713 | J25: =J24*(1-J15) -> 0.124146 | K25: =K24*(1-K15) -> 0.041173 | ... M25: =M24*(1-M15) -> 0.01045
B26: V1 NRE savings from platform - ₹ Cr/yr | D26: =D24-D25 -> 32.76075 | E26: =E24-E25 -> 43.16895 | F26: =F24-F25 -> 30.543678 | G26: =G24-G25 -> 18.62399 | H26: =H24-H25 -> 9.778065 | I26: =I24-I25 -> 6.007287 | J26: =J24-J25 -> 4.055854 | K26: =K24-K25 -> 2.048827 | ... M26: =M24-M25 -> 1.03455
B27: EW/SIGINT Gross NRE | C27: Total ~114 INR Cr over 10y | D27: 45.6 | E27: 34.2 | F27: 17.1 | G27: 7.98 | H27: 4.56 | I27: 2.28 | J27: 1.14 | K27: 0.57 | L27: 0.57 | M27: 0
A28: EW/SIGINT | B28: Gross NRE | C28: Gross = Standalone NRE × Gross Drivers, Net = Gross × (1 − Reuse Savings) | D28: =D27*(1-D16) -> 21.774 | E28: =E27*(1-E16) -> 10.602 | F28: =F27*(1-F16) -> 3.18915 | G28: =G27*(1-G16) -> 0.86184 | H28: =H27*(1-H16) -> 0.28956 | I28: =I27*(1-I16) -> 0.09348 | J28: =J27*(1-J16) -> 0.03306 | K28: =K27*(1-K16) -> 0.01083 | ... M28: =M27*(1-M16) -> 0
B29: V2 NRE savings from platform - ₹ Cr/yr | D29: =D27-D28 -> 23.826 | E29: =E27-E28 -> 23.598 | F29: =F27-F28 -> 13.91085 | G29: =G27-G28 -> 7.11816 | H29: =H27-H28 -> 4.27044 | I29: =I27-I28 -> 2.18652 | J29: =J27-J28 -> 1.10694 | K29: =K27-K28 -> 0.55917 | ... M29: =M27-M28 -> 0
B30: C-UAS Gross NRE | C30: Total ~152 INR Cr over 10y | D30: 38 | E30: 45.6 | F30: 30.4 | G30: 15.2 | H30: 9.12 | I30: 6.08 | J30: 3.04 | K30: 2.28 | L30: 0.76 | M30: 0.76
A31: C-UAS | B31: Gross NRE | C31: Gross = Standalone NRE × Gross Drivers, Net = Gross × (1 − Reuse Savings) | D31: =D30*(1-D17) -> 20.71 | E31: =E30*(1-E17) -> 16.188 | F31: =F30*(1-F17) -> 6.4752 | G31: =G30*(1-G17) -> 1.8696 | H31: =H30*(1-H17) -> 0.6612 | I31: =I30*(1-I17) -> 0.27968 | J31: =J30*(1-J17) -> 0.09728 | K31: =K30*(1-K17) -> 0.05016 | ... M31: =M30*(1-M17) -> 0.0076
B32: V3 NRE savings from platform - ₹ Cr/yr | D32: =D30-D31 -> 17.29 | E32: =E30-E31 -> 29.412 | F32: =F30-F31 -> 23.9248 | G32: =G30-G31 -> 13.3304 | H32: =H30-H31 -> 8.4588 | I32: =I30-I31 -> 5.80032 | J32: =J30-J31 -> 2.94272 | K32: =K30-K31 -> 2.22984 | ... M32: =M30-M31 -> 0.7524
B33: MALE UAS Gross NRE | C33: Total ~523 INR Cr over 10y | D33: 41.8 | E33: 78.375 | F33: 114.95 | G33: 114.95 | H33: 78.375 | I33: 41.8 | J33: 26.125 | K33: 15.675 | L33: 5.225 | M33: 5.225
A34: MALE UAS | B34: Gross NRE | C34: Gross = Standalone NRE × Gross Drivers, Net = Gross × (1 − Reuse Savings) | D34: =D33*(1-D18) -> 24.1395 | E34: =E33*(1-E18) -> 29.390625 | F34: =F33*(1-F18) -> 26.036175 | G34: =G33*(1-G18) -> 15.28835 | H34: =H33*(1-H18) -> 6.191625 | I34: =I33*(1-I18) -> 2.1318 | J34: =J33*(1-J18) -> 0.914375 | K34: =K33*(1-K18) -> 0.391875 | ... M34: =M33*(1-M18) -> 0.05225
B35: V4 NRE savings from platform - ₹ Cr/yr | D35: =D33-D34 -> 17.6605 | E35: =E33-E34 -> 48.984375 | F35: =F33-F34 -> 88.913825 | G35: =G33-G34 -> 99.66165 | H35: =H33-H34 -> 72.183375 | I35: =I33-I34 -> 39.6682 | J35: =J33-J34 -> 25.210625 | K35: =K33-K34 -> 15.283125 | ... M35: =M33-M34 -> 5.17275
B36: Autonomous Gross NRE | C36: Total ~247 INR Cr over 10y | D36: 37.05 | E36: 61.75 | F36: 54.34 | G36: 37.05 | H36: 24.7 | I36: 14.82 | J36: 9.88 | K36: 4.94 | L36: 1.235 | M36: 1.235
A37: Autonomous Systems | B37: Gross NRE | C37: Gross = Standalone NRE × Gross Drivers, Net = Gross × (1 − Reuse Savings) | D37: =D36*(1-D19) -> 21.67425 | E37: =E36*(1-E19) -> 23.465 | F37: =F36*(1-F19) -> 12.44386 | G37: =G36*(1-G19) -> 4.9647 | H37: =H36*(1-H19) -> 1.96365 | I37: =I36*(1-I19) -> 0.75582 | J37: =J36*(1-J19) -> 0.3458 | K37: =K36*(1-K19) -> 0.1235 | ... M37: =M36*(1-M19) -> 0.01235
B38: V5 NRE savings from platform - ₹ Cr/yr | D38: =D36-D37 -> 15.37575 | E38: =E36-E37 -> 38.285 | F38: =F36-F37 -> 41.89614 | G38: =G36-G37 -> 32.0853 | H38: =H36-H37 -> 22.73635 | I38: =I36-I37 -> 14.06418 | J38: =J36-J37 -> 9.5342 | K38: =K36-K37 -> 4.8165 | ... M38: =M36-M37 -> 1.22265
B39: Mil AI Gross NRE | C39: Total ~105 INR Cr over 10y | D39: 36.575 | E39: 26.125 | F39: 15.675 | G39: 10.45 | H39: 6.27 | I39: 4.18 | J39: 3.135 | K39: 1.5675 | L39: 0.5225 | M39: 0.5225
A40: Mil AI / Analytics | B40: Gross NRE | C40: Gross = Standalone NRE × Gross Drivers, Net = Gross × (1 − Reuse Savings) | D40: =D39*(1-D20) -> 23.590875 | E40: =E39*(1-E20) -> 10.9725 | F40: =F39*(1-F20) -> 3.91875 | G40: =G39*(1-G20) -> 1.499575 | H40: =H39*(1-H20) -> 0.529815 | I40: =I39*(1-I20) -> 0.21736 | J40: =J39*(1-J20) -> 0.1112925 | K40: =K39*(1-K20) -> 0.03997125 | ... M40: =M39*(1-M20) -> 0.005225
B41: V6 NRE savings from platform - ₹ Cr/yr | D41: =D39-D40 -> 12.984125 | E41: =E39-E40 -> 15.1525 | F41: =F39-F40 -> 11.75625 | G41: =G39-G40 -> 8.950425 | H41: =H39-H40 -> 5.740185 | I41: =I39-I40 -> 3.96264 | J41: =J39-J40 -> 3.0237075 | K41: =K39-K40 -> 1.5275287 | ... M41: =M39-M40 -> 0.517275
B43: D. Portfolio NRE totals (sum across V1..V6 + standalone platform investment)
B44: Aggregate line | D44: Y1 | E44: Y2 | F44: Y3 | G44: Y4 | H44: Y5 | I44: Y6 | J44: Y7 | K44: Y8 | L44: Y9 | M44: Y10
B45: Σ Gross NRE (verticals, standalone) | D45: =D24+D27+D30+D33+D36+D39 -> 261.725 | E45: =E24+E27+E30+E33+E36+E39 -> 308.75 | F45: =F24+F27+F30+F33+F36+F39 -> 270.085 | G45: =G24+G27+G30+G33+G36+G39 -> 206.53 | H45: =H24+H27+H30+H33+H36+H39 -> 133.475 | I45: =I24+I27+I30+I33+I36+I39 -> 75.43 | J45: =J24+J27+J30+J33+J36+J39 -> 47.5 | K45: =K24+K27+K30+K33+K36+K39 -> 27.1225 | ... M45: =M24+M27+M30+M33+M36+M39 -> 8.7875
B46: Σ Leveraged NRE (verticals, post-reuse) | D46: =D25+D28+D31+D34+D37+D40 -> 141.82788 | E46: =E25+E28+E31+E34+E37+E40 -> 110.14918 | F46: =F25+F28+F31+F34+F37+F40 -> 59.139457 | G46: =G25+G28+G31+G34+G37+G40 -> 26.760075 | H46: =H25+H28+H31+H34+H37+H40 -> 10.307785 | I46: =I25+I28+I31+I34+I37+I40 -> 3.740853 | J46: =J25+J28+J31+J34+J37+J40 -> 1.6259535 | K46: =K25+K28+K31+K34+K37+K40 -> 0.65750925 | ... M46: =M25+M28+M31+M34+M37+M40 -> 0.087875
B47: Σ Reuse savings (verticals) | D47: =D45-D46 -> 119.89713 | E47: =E45-E46 -> 198.60082 | F47: =F45-F46 -> 210.94554 | G47: =G45-G46 -> 179.76992 | H47: =H45-H46 -> 123.16721 | I47: =I45-I46 -> 71.689147 | J47: =J45-J46 -> 45.874046 | K47: =K45-K46 -> 26.464991 | ... M47: =M45-M46 -> 8.699625
B48: + Platform NRE (shared, standalone) | D48: =Platform!D11 -> 101 | E48: =Platform!E11 -> 210 | F48: =Platform!F11 -> 107 | G48: =Platform!G11 -> 69 | H48: =Platform!H11 -> 38 | I48: =Platform!I11 -> 20.5 | J48: =Platform!J11 -> 11.3 | K48: =Platform!K11 -> 8.4 | ... M48: =Platform!M11 -> 3.1
B49: TOTAL R&D / NRE expense | D49: =D46+D48 -> 242.82788 | E49: =E46+E48 -> 320.14918 | F49: =F46+F48 -> 166.13946 | G49: =G46+G48 -> 95.760075 | H49: =H46+H48 -> 48.307785 | I49: =I46+I48 -> 24.240853 | J49: =J46+J48 -> 12.925954 | K49: =K46+K48 -> 9.0575092 | ... M49: =M46+M48 -> 3.187875

Sheet Assumptions
B2: Global planning assumptions
B3: Driver | C3: Value | D3: Note
B4: Planning currency | C4: INR Crores | D4: Displayed in INR Crores (₹ Cr). Underlying inputs in absolute INR; 1 Cr = 10^7 INR; 1 USD = 95 INR.
B5: Planning horizon (years) | C5: 10 | D5: 10-year strategic horizon.
B6: Corporate tax rate | C6: 0.25 | D6: Blended.
B7: Discount rate (WACC) | C7: 0.18 | D7: Used for NPV - 18% reflects unlisted Indian defense unlisted equity cost-of-capital (β~1.5, ERP 8-9%, Rf 7%).
B8: Cost escalation (annual) | C8: 0.04 | D8: General wages + opex inflator (COGS/S&M/G&A roles & opex).
B9: R&D salary escalation (annual) | C9: 0.04 | D9: [M9 fix: reduced from 12% to 4% - aligns with general Indian wage growth long-term. 12% was unsustainable over 10y.]
B10: BoM learning curve (per doubling) | C10: 0.92 | D10: Wright's-law: cost factor at double cumulative volume.
B11: DSO (days sales outstanding) | C11: 180 | D11: Realistic blended DSO: iDEX/Make-II ~90-120d, MoD CapEx ~240-365d, export ~120d. Blended 180d.
B12: DPO (days payable outstanding) | C12: 45 | D12: Supplier terms net-45 typical for cleared vendors.
B13: Inventory days | C13: 90 | D13: Long-lead RF/FPGA components offset by JIT mission-SW & VMI.
B14: - (row retired) | D14: Legacy WC% removed. WC is now driven by DSO/DPO/Inventory schedule. Row left blank to preserve cell references below.
B15: S&M as % of revenue | C15: 0.08 | D15: Sales, BD, demos, exhibitions.
B16: G&A as % of revenue | C16: 0.07 | D16: Finance/HR/Legal/Compliance.
B17: Bid & Proposal as % of revenue | C17: 0.03 | D17: Capture/B&P overhead in defense.
B18: Export control overhead | C18: 2 | D18: Annual base, escalating.
B19: Cybersecurity / CMMC L3 overhead | C19: 14.25 | D19: Annual base, escalating.
B20: Quality / AS9100 / CMMI overhead | C20: 8.55 | D20: Annual base, escalating.
B21: Performance guarantee rate (PBG) | C21: 0.03 | D21: PBG % of contract value held by customer's bank through delivery period.
B22: Advance payment rate | C22: 0.15 | D22: Mobilization advance from MoD typical 15% against ABG.
B23: Bank guarantee fee (annual) | C23: 0.011 | D23: Reduced from 1.5% given Rs.150 Cr land/factory collateral provides physical security to issuing bank.
B24: Cash collateral requirement | C24: See Backlog!63 | D24: Year-specific schedule applied in Backlog!D63:M63 - Y1 100%, Y2 100%, Y3 50%, Y4 30%, Y5-Y10 20% (full collateral while bank track-record is being built, tapering as PBG/ABG history matures).
B25: Min cash reserve target | C25: 100 | D25: Triggers funding rounds.
B26: Platform reuse maturity multiplier | C26: 1 | D26: Scenario lever on reuse savings (1.0 = base).
B28: Defense-specific operating context
A29: ASP_elasticity | B29: ASP price erosion exponent (ASP elasticity to BoM): 0.5 means ASP declines with sqrt(BoM). | C29: 0.5
A30: BoM_floor | B30: Minimum BoM as fraction of starting BoM (learning curve floor): 0.7 means BoM cannot fall below 70% of initial. | C30: 0.7
B31: Contract types | C31: Fixed-price (FP), Cost-plus-fixed-fee (CPFF), IDIQ, FMS/Direct Commercial Sale.
B32: Compliance baseline | C32: ITAR / EAR / CMMC L3 / AS9100 / CMMI L3 - modeled in Opex.
B33: Qualification cycles | C33: MIL-STD-810 (env), -461 (EMI/EMC), -704 (power), -1275/704 - modeled in Capex (test infra).
B34: Export model | C34: Direct Commercial Sale (DCS) + FMS-eligible variants; offset obligations factored in S&M.
B35: IP / data rights | C35: Default to retain Government-Purpose Rights; unlimited rights only when negotiated separately.
B36: Defensive moats | C36: Platform IP + qualified BoM + cleared personnel + accredited facilities + customer references.
B37: MAT rate (Minimum Alternate Tax) | C37: 0.15 | D37: India Sec 115JB book-profit floor. Excess over regular tax becomes MAT credit asset.
B38: Column convention (READ BEFORE EDITING) | C38: Y1 column varies by sheet | D38: Y1 = col C on: P&L, CashFlow, BalanceSheet, BreakEven, KPIs (metric rows). Y1 = col D on: Revenue, Headcount, Capex, Opex, Funding, Backlog, V1-V6, R&D_NRE, Platform, ReuseMatrix. Cross-sheet formulas compensate today. DO NOT INSERT COLUMNS without re-auditing every cross-sheet reference.
B39: ASP price-cost elasticity exponent | C39: 0.5 | D39: Exponent linking ASP reduction to BoM cost reduction. 0.5 = square-root relationship.
B40: BoM floor (% of initial) | C40: 0.7 | D40: Minimum BoM cost as % of initial BoM after full learning curve absorption.
B41: Learning curve doubling basis | C41: 2 | D41: Logarithm base for Wrights-law learning curve (doubles of cumulative volume).
B42: USD to INR conversion rate | C42: 95 | D42: Planning exchange rate for any USD-based inputs.
B43: Revenue recognition lag (months) | C43: 12 | D43: Average lag from booking to revenue recognition for hardware programs.
B44: MAT credit asset treatment | C44: On-BS | D44: MAT credit recognized as deferred tax asset on Balance Sheet per Ind AS 12.
B45: BoM learning-curve base (% of initial BoM) | C45: 1 | D45: Starting unit BoM relative to input. Used in MAX(floor, base × curve^LOG(cum_units,2)).
B46: Log base for cumulative units | C46: 2 | D46: Wright curve doubling basis. Fixed at 2.
B48: Backlog & revenue flow drivers
B49: Revenue lag from booking (months - HW) | C49: 15 | D49: Average months from booking to revenue recognition for hardware. Range 12-18 months.
A50: Product Pricing & Cost Assumptions | D50: Average months for software/SaaS. Range 3-12 months.
A51: ASP price-cost elasticity exponent (power applied to BoM ratio) | B51: ASP_Elasticity | C51: 0.5 | D51: % of prior-year backlog to be delivered in current year, smoothing uneven spikes.
A52: BoM learning curve floor (% of starting BoM) | B52: BoM_Floor_Pct | C52: 0.5
A53: Min BoM expressed as pct of starting | B53: BoM_Min_Pct | C53: =C52 -> 0.5
A54: BoM doubling basis for LOG | B54: BoM_Doubling_Base | C54: 2
A56: R&D Capitalization & Amortization
A57: Platform NRE capitalization rate | B57: Platform_NRE_Cap_Rate | C57: 0.6
A58: Capitalized NRE amortization life (years) | B58: NRE_Amort_Life | C58: 6
A59: Vertical NRE amortization life (years) | B59: Vertical_NRE_Amort_Life | C59: 5
A61: Working Capital & Funding
A62: BG collateral cash requirement (% of contract value) | B62: BG_Collateral_Pct | C62: 0.1 | D62: Bank-confirmed cash margin against PBG/ABG = 10% flat (existing facility).
A64: Manufacturing & Warranty
A65: Manufacturing overhead as % of direct material + labour | B65: Mfg_Overhead_Pct | C65: 0.2
A66: Warranty & support burden as % of COGS | B66: Warranty_Pct | C66: 0.02

Sheet V1_AESA
B1: READ ONLY SUPPORTING DETAIL - Revenue is recognized via Backlog!Section L (rows 89-95). Editing units/ASP here does NOT change consolidated revenue, but DOES rescale COGS (BoM x delivered_rev / V-sheet rev). Do not edit unless you intend to re-baseline the BoM ratio.
B2: V1 - AESA Radar | Domain: Air/Land/Sea (RF) | Launch: Y2
B3: Description | C3: Active Electronically Scanned Array radars - second product line; leverages partly-developed ESM RF & DSP front-end. First demo Y2, first deliveries Y2.
B5: Line | C5: Driver | D5: Y1 | E5: Y2 | F5: Y3 | G5: Y4 | H5: Y5 | I5: Y6 | J5: Y7 | K5: Y8 | L5: Y9 | M5: Y10
B6: Variant A - X-band Airborne
B7: ASP / unit (₹ Cr) | C7: yellow = input | D7: 26 | E7: =$D$7*(E8/$D$8)^Assumptions!$C$39 -> 22.637384 | F7: =$D$7*(F8/$D$8)^Assumptions!$C$39 -> 21.753161 | G7: =$D$7*(G8/$D$8)^Assumptions!$C$39 -> 21.753161 | H7: =$D$7*(H8/$D$8)^Assumptions!$C$39 -> 21.753161 | I7: =$D$7*(I8/$D$8)^Assumptions!$C$39 -> 21.753161 | J7: =$D$7*(J8/$D$8)^Assumptions!$C$39 -> 21.753161 | K7: =$D$7*(K8/$D$8)^Assumptions!$C$39 -> 21.753161 | L7: =$D$7*(L8/$D$8)^Assumptions!$C$39 -> 21.753161 | M7: =$D$7*(M8/$D$8)^Assumptions!$C$39 -> 21.753161
B8: BoM / unit (₹ Cr) | C8: yellow = input | D8: 11 | E8: =MAX($D$8*Assumptions!$C$40,$D$8*Assumptions!$C$10^LOG(MAX(1,SUM($D9:E9)),Assumptions!$C$41)) -> 8.338702 | F8: =MAX($D$8*Assumptions!$C$40,$D$8*Assumptions!$C$10^LOG(MAX(1,SUM($D9:F9)),Assumptions!$C$41)) -> 7.7 | G8: =MAX($D$8*Assumptions!$C$40,$D$8*Assumptions!$C$10^LOG(MAX(1,SUM($D9:G9)),Assumptions!$C$41)) -> 7.7 | H8: =MAX($D$8*Assumptions!$C$40,$D$8*Assumptions!$C$10^LOG(MAX(1,SUM($D9:H9)),Assumptions!$C$41)) -> 7.7 | I8: =MAX($D$8*Assumptions!$C$40,$D$8*Assumptions!$C$10^LOG(MAX(1,SUM($D9:I9)),Assumptions!$C$41)) -> 7.7 | J8: =MAX($D$8*Assumptions!$C$40,$D$8*Assumptions!$C$10^LOG(MAX(1,SUM($D9:J9)),Assumptions!$C$41)) -> 7.7 | K8: =MAX($D$8*Assumptions!$C$40,$D$8*Assumptions!$C$10^LOG(MAX(1,SUM($D9:K9)),Assumptions!$C$41)) -> 7.7 | L8: =MAX($D$8*Assumptions!$C$40,$D$8*Assumptions!$C$10^LOG(MAX(1,SUM($D9:L9)),Assumptions!$C$41)) -> 7.7 | M8: =MAX($D$8*Assumptions!$C$40,$D$8*Assumptions!$C$10^LOG(MAX(1,SUM($D9:M9)),Assumptions!$C$41)) -> 7.7
B9: Units shipped (#) | C9: yellow = input | D9: 2 | E9: 8 | F9: 10 | G9: 20 | H9: 50 | I9: 50 | J9: 60 | K9: 60 | L9: 80 | M9: 80
B10: Revenue (units × ASP) | D10: =D7*D9 -> 52 | E10: =E7*E9 -> 181.09907 | F10: =F7*F9 -> 217.53161 | G10: =G7*G9 -> 435.06321 | H10: =H7*H9 -> 1087.658 | I10: =I7*I9 -> 1087.658 | J10: =J7*J9 -> 1305.1896 | K10: =K7*K9 -> 1305.1896 | ... M10: =M7*M9 -> 1740.2529
B11: COGS - BoM (units × BoM) | D11: =D8*D9 -> 22 | E11: =E8*E9 -> 66.709616 | F11: =F8*F9 -> 77 | G11: =G8*G9 -> 154 | H11: =H8*H9 -> 385 | I11: =I8*I9 -> 385 | J11: =J8*J9 -> 462 | K11: =K8*K9 -> 462 | ... M11: =M8*M9 -> 616
B12: Contribution margin / unit | D12: =IF(D7=0,0,1-D8/D7) -> 0.57692308 | E12: =IF(E7=0,0,1-E8/E7) -> 0.63164021 | F12: =IF(F7=0,0,1-F8/F7) -> 0.64602845 | G12: =IF(G7=0,0,1-G8/G7) -> 0.64602845 | H12: =IF(H7=0,0,1-H8/H7) -> 0.64602845 | I12: =IF(I7=0,0,1-I8/I7) -> 0.64602845 | J12: =IF(J7=0,0,1-J8/J7) -> 0.64602845 | K12: =IF(K7=0,0,1-K8/K7) -> 0.64602845 | ... M12: =IF(M7=0,0,1-M8/M7) -> 0.64602845
B14: Variant B - S-band Ground Surveillance
B15: ASP / unit (₹ Cr) | C15: yellow = input | D15: 45 | E15: =$D$15*(E16/$D$16)^Assumptions!$C$39 -> 45 | F15: =$D$15*(F16/$D$16)^Assumptions!$C$39 -> 42.122588 | G15: =$D$15*(G16/$D$16)^Assumptions!$C$39 -> 40.402567 | H15: =$D$15*(H16/$D$16)^Assumptions!$C$39 -> 39.180087 | I15: =$D$15*(I16/$D$16)^Assumptions!$C$39 -> 38.236138 | J15: =$D$15*(J16/$D$16)^Assumptions!$C$39 -> 37.649701 | K15: =$D$15*(K16/$D$16)^Assumptions!$C$39 -> 37.649701 | L15: =$D$15*(L16/$D$16)^Assumptions!$C$39 -> 37.649701 | M15: =$D$15*(M16/$D$16)^Assumptions!$C$39 -> 37.649701
B16: BoM / unit (₹ Cr) | C16: yellow = input | D16: 17.765 | E16: =MAX($D$16*Assumptions!$C$40,$D$16*Assumptions!$C$10^LOG(MAX(1,SUM($D17:E17)),Assumptions!$C$41)) -> 17.765 | F16: =MAX($D$16*Assumptions!$C$40,$D$16*Assumptions!$C$10^LOG(MAX(1,SUM($D17:F17)),Assumptions!$C$41)) -> 15.565758 | G16: =MAX($D$16*Assumptions!$C$40,$D$16*Assumptions!$C$10^LOG(MAX(1,SUM($D17:G17)),Assumptions!$C$41)) -> 14.320497 | H16: =MAX($D$16*Assumptions!$C$40,$D$16*Assumptions!$C$10^LOG(MAX(1,SUM($D17:H17)),Assumptions!$C$41)) -> 13.467004 | I16: =MAX($D$16*Assumptions!$C$40,$D$16*Assumptions!$C$10^LOG(MAX(1,SUM($D17:I17)),Assumptions!$C$41)) -> 12.825911 | J16: =MAX($D$16*Assumptions!$C$40,$D$16*Assumptions!$C$10^LOG(MAX(1,SUM($D17:J17)),Assumptions!$C$41)) -> 12.4355 | K16: =MAX($D$16*Assumptions!$C$40,$D$16*Assumptions!$C$10^LOG(MAX(1,SUM($D17:K17)),Assumptions!$C$41)) -> 12.4355 | L16: =MAX($D$16*Assumptions!$C$40,$D$16*Assumptions!$C$10^LOG(MAX(1,SUM($D17:L17)),Assumptions!$C$41)) -> 12.4355 | M16: =MAX($D$16*Assumptions!$C$40,$D$16*Assumptions!$C$10^LOG(MAX(1,SUM($D17:M17)),Assumptions!$C$41)) -> 12.4355
B17: Units shipped (#) | C17: yellow = input | D17: 0 | E17: 1 | F17: 2 | G17: 3 | H17: 4 | I17: 5 | J17: 6 | K17: 7 | L17: 8 | M17: 8
B18: Revenue (units × ASP) | D18: =D15*D17 -> 0 | E18: =E15*E17 -> 45 | F18: =F15*F17 -> 84.245176 | G18: =G15*G17 -> 121.2077 | H18: =H15*H17 -> 156.72035 | I18: =I15*I17 -> 191.18069 | J18: =J15*J17 -> 225.89821 | K18: =K15*K17 -> 263.54791 | ... M18: =M15*M17 -> 301.19761
B19: COGS - BoM (units × BoM) | D19: =D16*D17 -> 0 | E19: =E16*E17 -> 17.765 | F19: =F16*F17 -> 31.131516 | G19: =G16*G17 -> 42.961492 | H19: =H16*H17 -> 53.868015 | I19: =I16*I17 -> 64.129554 | J19: =J16*J17 -> 74.613 | K19: =K16*K17 -> 87.0485 | ... M19: =M16*M17 -> 99.484
B20: Contribution margin / unit | D20: =IF(D15=0,0,1-D16/D15) -> 0.60522222 | E20: =IF(E15=0,0,1-E16/E15) -> 0.60522222 | F20: =IF(F15=0,0,1-F16/F15) -> 0.6304653 | G20: =IF(G15=0,0,1-G16/G15) -> 0.64555476 | H20: =IF(H15=0,0,1-H16/H15) -> 0.65627938 | I20: =IF(I15=0,0,1-I16/I15) -> 0.6645605 | J20: =IF(J15=0,0,1-J16/J15) -> 0.66970521 | K20: =IF(K15=0,0,1-K16/K15) -> 0.66970521 | ... M20: =IF(M15=0,0,1-M16/M15) -> 0.66970521
B22: Variant C - X-band Naval Multi-function
B23: ASP / unit (₹ Cr) | C23: yellow = input | D23: 36 | E23: =$D$23*(E24/$D$24)^Assumptions!$C$39 -> 36 | F23: =$D$23*(F24/$D$24)^Assumptions!$C$39 -> 34.529987 | G23: =$D$23*(G24/$D$24)^Assumptions!$C$39 -> 33.12 | H23: =$D$23*(H24/$D$24)^Assumptions!$C$39 -> 32.023758 | I23: =$D$23*(I24/$D$24)^Assumptions!$C$39 -> 31.1649 | J23: =$D$23*(J24/$D$24)^Assumptions!$C$39 -> 30.4704 | K23: =$D$23*(K24/$D$24)^Assumptions!$C$39 -> 30.119761 | L23: =$D$23*(L24/$D$24)^Assumptions!$C$39 -> 30.119761 | M23: =$D$23*(M24/$D$24)^Assumptions!$C$39 -> 30.119761
B24: BoM / unit (₹ Cr) | C24: yellow = input | D24: 14.6775 | E24: =MAX($D$24*Assumptions!$C$40,$D$24*Assumptions!$C$10^LOG(MAX(1,SUM($D25:E25)),Assumptions!$C$41)) -> 14.6775 | F24: =MAX($D$24*Assumptions!$C$40,$D$24*Assumptions!$C$10^LOG(MAX(1,SUM($D25:F25)),Assumptions!$C$41)) -> 13.5033 | G24: =MAX($D$24*Assumptions!$C$40,$D$24*Assumptions!$C$10^LOG(MAX(1,SUM($D25:G25)),Assumptions!$C$41)) -> 12.423036 | H24: =MAX($D$24*Assumptions!$C$40,$D$24*Assumptions!$C$10^LOG(MAX(1,SUM($D25:H25)),Assumptions!$C$41)) -> 11.614263 | I24: =MAX($D$24*Assumptions!$C$40,$D$24*Assumptions!$C$10^LOG(MAX(1,SUM($D25:I25)),Assumptions!$C$41)) -> 10.999642 | J24: =MAX($D$24*Assumptions!$C$40,$D$24*Assumptions!$C$10^LOG(MAX(1,SUM($D25:J25)),Assumptions!$C$41)) -> 10.514858 | K24: =MAX($D$24*Assumptions!$C$40,$D$24*Assumptions!$C$10^LOG(MAX(1,SUM($D25:K25)),Assumptions!$C$41)) -> 10.27425 | L24: =MAX($D$24*Assumptions!$C$40,$D$24*Assumptions!$C$10^LOG(MAX(1,SUM($D25:L25)),Assumptions!$C$41)) -> 10.27425 | M24: =MAX($D$24*Assumptions!$C$40,$D$24*Assumptions!$C$10^LOG(MAX(1,SUM($D25:M25)),Assumptions!$C$41)) -> 10.27425
B25: Units shipped (#) | C25: yellow = input | D25: 0 | E25: 1 | F25: 1 | G25: 2 | H25: 3 | I25: 4 | J25: 5 | K25: 6 | L25: 6 | M25: 7
B26: Revenue (units × ASP) | D26: =D23*D25 -> 0 | E26: =E23*E25 -> 36 | F26: =F23*F25 -> 34.529987 | G26: =G23*G25 -> 66.24 | H26: =H23*H25 -> 96.071273 | I26: =I23*I25 -> 124.6596 | J26: =J23*J25 -> 152.352 | K26: =K23*K25 -> 180.71857 | ... M26: =M23*M25 -> 210.83833
B27: COGS - BoM (units × BoM) | D27: =D24*D25 -> 0 | E27: =E24*E25 -> 14.6775 | F27: =F24*F25 -> 13.5033 | G27: =G24*G25 -> 24.846072 | H27: =H24*H25 -> 34.84279 | I27: =I24*I25 -> 43.998568 | J27: =J24*J25 -> 52.574288 | K27: =K24*K25 -> 61.6455 | ... M27: =M24*M25 -> 71.91975
B28: Contribution margin / unit | D28: =IF(D23=0,0,1-D24/D23) -> 0.59229167 | E28: =IF(E23=0,0,1-E24/E23) -> 0.59229167 | F28: =IF(F23=0,0,1-F24/F23) -> 0.6089399 | G28: =IF(G23=0,0,1-G24/G23) -> 0.62490833 | H28: =IF(H23=0,0,1-H24/H23) -> 0.63732353 | I28: =IF(I23=0,0,1-I24/I23) -> 0.6470503 | J28: =IF(J23=0,0,1-J24/J23) -> 0.65491567 | K28: =IF(K23=0,0,1-K24/K23) -> 0.65888674 | ... M28: =IF(M23=0,0,1-M24/M23) -> 0.65888674
B30: V1 totals
B31: Total revenue | D31: =D10+D18+D26 -> 52 | E31: =E10+E18+E26 -> 262.09907 | F31: =F10+F18+F26 -> 336.30677 | G31: =G10+G18+G26 -> 622.51091 | H31: =H10+H18+H26 -> 1340.4497 | I31: =I10+I18+I26 -> 1403.4983 | J31: =J10+J18+J26 -> 1683.4398 | K31: =K10+K18+K26 -> 1749.4561 | ... M31: =M10+M18+M26 -> 2252.2888
B32: Total COGS (BoM) | D32: =D11+D19+D27 -> 22 | E32: =E11+E19+E27 -> 99.152116 | F32: =F11+F19+F27 -> 121.63482 | G32: =G11+G19+G27 -> 221.80756 | H32: =H11+H19+H27 -> 473.7108 | I32: =I11+I19+I27 -> 493.12812 | J32: =J11+J19+J27 -> 589.18729 | K32: =K11+K19+K27 -> 610.694 | ... M32: =M11+M19+M27 -> 787.40375
B33: Total units shipped | D33: =D9+D17+D25 -> 2 | E33: =E9+E17+E25 -> 10 | F33: =F9+F17+F25 -> 13 | G33: =G9+G17+G25 -> 25 | H33: =H9+H17+H25 -> 57 | I33: =I9+I17+I25 -> 59 | J33: =J9+J17+J25 -> 71 | K33: =K9+K17+K25 -> 73 | ... M33: =M9+M17+M25 -> 95
B34: Gross profit (Revenue − BoM COGS) | D34: =D31-D32 -> 30 | E34: =E31-E32 -> 162.94695 | F34: =F31-F32 -> 214.67195 | G34: =G31-G32 -> 400.70335 | H34: =H31-H32 -> 866.73885 | I34: =I31-I32 -> 910.3702 | J34: =J31-J32 -> 1094.2526 | K34: =K31-K32 -> 1138.7621 | ... M34: =M31-M32 -> 1464.885
B35: Gross margin % | D35: =IFERROR((D31-D32)/D31,0) -> 0.57692308 | E35: =IFERROR((E31-E32)/E31,0) -> 0.62169986 | F35: =IFERROR((F31-F32)/F31,0) -> 0.63832183 | G35: =IFERROR((G31-G32)/G31,0) -> 0.64368888 | H35: =IFERROR((H31-H32)/H31,0) -> 0.64660306 | I35: =IFERROR((I31-I32)/I31,0) -> 0.6486436 | J35: =IFERROR((J31-J32)/J31,0) -> 0.6500099 | K35: =IFERROR((K31-K32)/K31,0) -> 0.65092351 | ... M35: =IFERROR((M31-M32)/M31,0) -> 0.65039841
B36: Cumulative revenue | D36: =D31 -> 52 | E36: =D36+E31 -> 314.09907 | F36: =E36+F31 -> 650.40584 | G36: =F36+G31 -> 1272.9168 | H36: =G36+H31 -> 2613.3664 | I36: =H36+I31 -> 4016.8647 | J36: =I36+J31 -> 5700.3046 | K36: =J36+K31 -> 7449.7607 | L36: =K36+L31 -> 9671.9297 | M36: =L36+M31 -> 11924.219

Sheet V2_EW_SIGINT
B1: READ ONLY SUPPORTING DETAIL - Revenue is recognized via Backlog!Section L (rows 89-95). Editing units/ASP here does NOT change consolidated revenue, but DOES rescale COGS (BoM x delivered_rev / V-sheet rev). Do not edit unless you intend to re-baseline the BoM ratio.
B2: V2 - Electronic Warfare & SIGINT | Domain: Air/Land/Sea (RF + DSP) | Launch: Y1
B3: Description | C3: ESM/ELINT - already partly developed at start of plan. Day-1 focus is industrialization, qualification of remaining variants, and concurrent scale-up of production & sales while other verticals are still in development.
B5: Line | C5: Driver | D5: Y1 | E5: Y2 | F5: Y3 | G5: Y4 | H5: Y5 | I5: Y6 | J5: Y7 | K5: Y8 | L5: Y9 | M5: Y10
B6: EW-A - Naval ESM/ELINT Suite
B7: ASP / unit (₹ Cr) | C7: yellow = input | D7: 30 | E7: =$D$7*(E8/$D$8)^Assumptions!$C$39 -> 26.47299 | F7: =$D$7*(F8/$D$8)^Assumptions!$C$39 -> 25.596758 | G7: =$D$7*(G8/$D$8)^Assumptions!$C$39 -> 25.099801 | H7: =$D$7*(H8/$D$8)^Assumptions!$C$39 -> 25.099801 | I7: =$D$7*(I8/$D$8)^Assumptions!$C$39 -> 25.099801 | J7: =$D$7*(J8/$D$8)^Assumptions!$C$39 -> 25.099801 | K7: =$D$7*(K8/$D$8)^Assumptions!$C$39 -> 25.099801 | L7: =$D$7*(L8/$D$8)^Assumptions!$C$39 -> 25.099801 | M7: =$D$7*(M8/$D$8)^Assumptions!$C$39 -> 25.099801
B8: BoM / unit (₹ Cr) | C8: yellow = input | D8: 14 | E8: =MAX($D$8*Assumptions!$C$40,$D$8*Assumptions!$C$10^LOG(MAX(1,SUM($D9:E9)),Assumptions!$C$41)) -> 10.901632 | F8: =MAX($D$8*Assumptions!$C$40,$D$8*Assumptions!$C$10^LOG(MAX(1,SUM($D9:F9)),Assumptions!$C$41)) -> 10.191907 | G8: =MAX($D$8*Assumptions!$C$40,$D$8*Assumptions!$C$10^LOG(MAX(1,SUM($D9:G9)),Assumptions!$C$41)) -> 9.8 | H8: =MAX($D$8*Assumptions!$C$40,$D$8*Assumptions!$C$10^LOG(MAX(1,SUM($D9:H9)),Assumptions!$C$41)) -> 9.8 | I8: =MAX($D$8*Assumptions!$C$40,$D$8*Assumptions!$C$10^LOG(MAX(1,SUM($D9:I9)),Assumptions!$C$41)) -> 9.8 | J8: =MAX($D$8*Assumptions!$C$40,$D$8*Assumptions!$C$10^LOG(MAX(1,SUM($D9:J9)),Assumptions!$C$41)) -> 9.8 | K8: =MAX($D$8*Assumptions!$C$40,$D$8*Assumptions!$C$10^LOG(MAX(1,SUM($D9:K9)),Assumptions!$C$41)) -> 9.8 | L8: =MAX($D$8*Assumptions!$C$40,$D$8*Assumptions!$C$10^LOG(MAX(1,SUM($D9:L9)),Assumptions!$C$41)) -> 9.8 | M8: =MAX($D$8*Assumptions!$C$40,$D$8*Assumptions!$C$10^LOG(MAX(1,SUM($D9:M9)),Assumptions!$C$41)) -> 9.8
B9: Units shipped (#) | C9: yellow = input | D9: 4 | E9: 4 | F9: 6 | G9: 6 | H9: 8 | I9: 10 | J9: 12 | K9: 12 | L9: 12 | M9: 15
B10: Revenue (units × ASP) | D10: =D7*D9 -> 120 | E10: =E7*E9 -> 105.89196 | F10: =F7*F9 -> 153.58055 | G10: =G7*G9 -> 150.5988 | H10: =H7*H9 -> 200.79841 | I10: =I7*I9 -> 250.99801 | J10: =J7*J9 -> 301.19761 | K10: =K7*K9 -> 301.19761 | ... M10: =M7*M9 -> 376.49701
B11: COGS - BoM (units × BoM) | D11: =D8*D9 -> 56 | E11: =E8*E9 -> 43.606528 | F11: =F8*F9 -> 61.151441 | G11: =G8*G9 -> 58.8 | H11: =H8*H9 -> 78.4 | I11: =I8*I9 -> 98 | J11: =J8*J9 -> 117.6 | K11: =K8*K9 -> 117.6 | ... M11: =M8*M9 -> 147
B12: Contribution margin / unit | D12: =IF(D7=0,0,1-D8/D7) -> 0.53333333 | E12: =IF(E7=0,0,1-E8/E7) -> 0.58819793 | F12: =IF(F7=0,0,1-F8/F7) -> 0.60182821 | G12: =IF(G7=0,0,1-G8/G7) -> 0.60955865 | H12: =IF(H7=0,0,1-H8/H7) -> 0.60955865 | I12: =IF(I7=0,0,1-I8/I7) -> 0.60955865 | J12: =IF(J7=0,0,1-J8/J7) -> 0.60955865 | K12: =IF(K7=0,0,1-K8/K7) -> 0.60955865 | ... M12: =IF(M7=0,0,1-M8/M7) -> 0.60955865
B14: EW-B - Aerial ESM Pod (UAV/Manned)
B15: ASP / unit (₹ Cr) | C15: yellow = input | D15: 35 | E15: =$D$15*(E16/$D$16)^Assumptions!$C$39 -> 31.770717 | F15: =$D$15*(F16/$D$16)^Assumptions!$C$39 -> 29.996291 | G15: =$D$15*(G16/$D$16)^Assumptions!$C$39 -> 29.283101 | H15: =$D$15*(H16/$D$16)^Assumptions!$C$39 -> 29.283101 | I15: =$D$15*(I16/$D$16)^Assumptions!$C$39 -> 29.283101 | J15: =$D$15*(J16/$D$16)^Assumptions!$C$39 -> 29.283101 | K15: =$D$15*(K16/$D$16)^Assumptions!$C$39 -> 29.283101 | L15: =$D$15*(L16/$D$16)^Assumptions!$C$39 -> 29.283101 | M15: =$D$15*(M16/$D$16)^Assumptions!$C$39 -> 29.283101
B16: BoM / unit (₹ Cr) | C16: yellow = input | D16: 13.775 | E16: =MAX($D$16*Assumptions!$C$40,$D$16*Assumptions!$C$10^LOG(MAX(1,SUM($D17:E17)),Assumptions!$C$41)) -> 11.350358 | F16: =MAX($D$16*Assumptions!$C$40,$D$16*Assumptions!$C$10^LOG(MAX(1,SUM($D17:F17)),Assumptions!$C$41)) -> 10.117906 | G16: =MAX($D$16*Assumptions!$C$40,$D$16*Assumptions!$C$10^LOG(MAX(1,SUM($D17:G17)),Assumptions!$C$41)) -> 9.6425 | H16: =MAX($D$16*Assumptions!$C$40,$D$16*Assumptions!$C$10^LOG(MAX(1,SUM($D17:H17)),Assumptions!$C$41)) -> 9.6425 | I16: =MAX($D$16*Assumptions!$C$40,$D$16*Assumptions!$C$10^LOG(MAX(1,SUM($D17:I17)),Assumptions!$C$41)) -> 9.6425 | J16: =MAX($D$16*Assumptions!$C$40,$D$16*Assumptions!$C$10^LOG(MAX(1,SUM($D17:J17)),Assumptions!$C$41)) -> 9.6425 | K16: =MAX($D$16*Assumptions!$C$40,$D$16*Assumptions!$C$10^LOG(MAX(1,SUM($D17:K17)),Assumptions!$C$41)) -> 9.6425 | L16: =MAX($D$16*Assumptions!$C$40,$D$16*Assumptions!$C$10^LOG(MAX(1,SUM($D17:L17)),Assumptions!$C$41)) -> 9.6425 | M16: =MAX($D$16*Assumptions!$C$40,$D$16*Assumptions!$C$10^LOG(MAX(1,SUM($D17:M17)),Assumptions!$C$41)) -> 9.6425
B17: Units shipped (#) | C17: yellow = input | D17: 1 | E17: 4 | F17: 8 | G17: 12 | H17: 12 | I17: 12 | J17: 15 | K17: 15 | L17: 20 | M17: 20
B18: Revenue (units × ASP) | D18: =D15*D17 -> 35 | E18: =E15*E17 -> 127.08287 | F18: =F15*F17 -> 239.97033 | G18: =G15*G17 -> 351.39721 | H18: =H15*H17 -> 351.39721 | I18: =I15*I17 -> 351.39721 | J18: =J15*J17 -> 439.24651 | K18: =K15*K17 -> 439.24651 | ... M18: =M15*M17 -> 585.66202
B19: COGS - BoM (units × BoM) | D19: =D16*D17 -> 13.775 | E19: =E16*E17 -> 45.401431 | F19: =F16*F17 -> 80.943249 | G19: =G16*G17 -> 115.71 | H19: =H16*H17 -> 115.71 | I19: =I16*I17 -> 115.71 | J19: =J16*J17 -> 144.6375 | K19: =K16*K17 -> 144.6375 | ... M19: =M16*M17 -> 192.85
B20: Contribution margin / unit | D20: =IF(D15=0,0,1-D16/D15) -> 0.60642857 | E20: =IF(E15=0,0,1-E16/E15) -> 0.64274153 | F20: =IF(F15=0,0,1-F16/F15) -> 0.66269476 | G20: =IF(G15=0,0,1-G16/G15) -> 0.67071452 | H20: =IF(H15=0,0,1-H16/H15) -> 0.67071452 | I20: =IF(I15=0,0,1-I16/I15) -> 0.67071452 | J20: =IF(J15=0,0,1-J16/J15) -> 0.67071452 | K20: =IF(K15=0,0,1-K16/K15) -> 0.67071452 | ... M20: =IF(M15=0,0,1-M16/M15) -> 0.67071452
B22: EW-C - Anti-Drone Jammer (tactical)
B23: ASP / unit (₹ Cr) | C23: yellow = input | D23: 2 | E23: =$D$23*(E24/$D$24)^Assumptions!$C$39 -> 1.6808501 | F23: =$D$23*(F24/$D$24)^Assumptions!$C$39 -> 1.6733201 | G23: =$D$23*(G24/$D$24)^Assumptions!$C$39 -> 1.6733201 | H23: =$D$23*(H24/$D$24)^Assumptions!$C$39 -> 1.6733201 | I23: =$D$23*(I24/$D$24)^Assumptions!$C$39 -> 1.6733201 | J23: =$D$23*(J24/$D$24)^Assumptions!$C$39 -> 1.6733201 | K23: =$D$23*(K24/$D$24)^Assumptions!$C$39 -> 1.6733201 | L23: =$D$23*(L24/$D$24)^Assumptions!$C$39 -> 1.6733201 | M23: =$D$23*(M24/$D$24)^Assumptions!$C$39 -> 1.6733201
B24: BoM / unit (₹ Cr) | C24: yellow = input | D24: 0.8075 | E24: =MAX($D$24*Assumptions!$C$40,$D$24*Assumptions!$C$10^LOG(MAX(1,SUM($D25:E25)),Assumptions!$C$41)) -> 0.57034874 | F24: =MAX($D$24*Assumptions!$C$40,$D$24*Assumptions!$C$10^LOG(MAX(1,SUM($D25:F25)),Assumptions!$C$41)) -> 0.56525 | G24: =MAX($D$24*Assumptions!$C$40,$D$24*Assumptions!$C$10^LOG(MAX(1,SUM($D25:G25)),Assumptions!$C$41)) -> 0.56525 | H24: =MAX($D$24*Assumptions!$C$40,$D$24*Assumptions!$C$10^LOG(MAX(1,SUM($D25:H25)),Assumptions!$C$41)) -> 0.56525 | I24: =MAX($D$24*Assumptions!$C$40,$D$24*Assumptions!$C$10^LOG(MAX(1,SUM($D25:I25)),Assumptions!$C$41)) -> 0.56525 | J24: =MAX($D$24*Assumptions!$C$40,$D$24*Assumptions!$C$10^LOG(MAX(1,SUM($D25:J25)),Assumptions!$C$41)) -> 0.56525 | K24: =MAX($D$24*Assumptions!$C$40,$D$24*Assumptions!$C$10^LOG(MAX(1,SUM($D25:K25)),Assumptions!$C$41)) -> 0.56525 | L24: =MAX($D$24*Assumptions!$C$40,$D$24*Assumptions!$C$10^LOG(MAX(1,SUM($D25:L25)),Assumptions!$C$41)) -> 0.56525 | M24: =MAX($D$24*Assumptions!$C$40,$D$24*Assumptions!$C$10^LOG(MAX(1,SUM($D25:M25)),Assumptions!$C$41)) -> 0.56525
B25: Units shipped (#) | C25: yellow = input | D25: 6 | E25: 12 | F25: 20 | G25: 30 | H25: 40 | I25: 50 | J25: 60 | K25: 70 | L25: 75 | M25: 80
B26: Revenue (units × ASP) | D26: =D23*D25 -> 12 | E26: =E23*E25 -> 20.170201 | F26: =F23*F25 -> 33.466401 | G26: =G23*G25 -> 50.199602 | H26: =H23*H25 -> 66.932802 | I26: =I23*I25 -> 83.666003 | J26: =J23*J25 -> 100.3992 | K26: =K23*K25 -> 117.1324 | ... M26: =M23*M25 -> 133.8656
B27: COGS - BoM (units × BoM) | D27: =D24*D25 -> 4.845 | E27: =E24*E25 -> 6.8441849 | F27: =F24*F25 -> 11.305 | G27: =G24*G25 -> 16.9575 | H27: =H24*H25 -> 22.61 | I27: =I24*I25 -> 28.2625 | J27: =J24*J25 -> 33.915 | K27: =K24*K25 -> 39.5675 | ... M27: =M24*M25 -> 45.22
B28: Contribution margin / unit | D28: =IF(D23=0,0,1-D24/D23) -> 0.59625 | E28: =IF(E23=0,0,1-E24/E23) -> 0.66067839 | F28: =IF(F23=0,0,1-F24/F23) -> 0.66219851 | G28: =IF(G23=0,0,1-G24/G23) -> 0.66219851 | H28: =IF(H23=0,0,1-H24/H23) -> 0.66219851 | I28: =IF(I23=0,0,1-I24/I23) -> 0.66219851 | J28: =IF(J23=0,0,1-J24/J23) -> 0.66219851 | K28: =IF(K23=0,0,1-K24/K23) -> 0.66219851 | ... M28: =IF(M23=0,0,1-M24/M23) -> 0.66219851
B30: EW-D - Ground SIGINT Station (strategic)
B31: ASP / unit (₹ Cr) | C31: yellow = input | D31: 114 | E31: =$D$31*(E32/$D$32)^Assumptions!$C$39 -> 114 | F31: =$D$31*(F32/$D$32)^Assumptions!$C$39 -> 106.71056 | G31: =$D$31*(G32/$D$32)^Assumptions!$C$39 -> 101.40857 | H31: =$D$31*(H32/$D$32)^Assumptions!$C$39 -> 98.688849 | I31: =$D$31*(I32/$D$32)^Assumptions!$C$39 -> 96.864882 | J31: =$D$31*(J32/$D$32)^Assumptions!$C$39 -> 95.497392 | K31: =$D$31*(K32/$D$32)^Assumptions!$C$39 -> 95.379243 | L31: =$D$31*(L32/$D$32)^Assumptions!$C$39 -> 95.379243 | M31: =$D$31*(M32/$D$32)^Assumptions!$C$39 -> 95.379243
B32: BoM / unit (₹ Cr) | C32: yellow = input | D32: 60 | E32: =MAX($D$32*Assumptions!$C$40,$D$32*Assumptions!$C$10^LOG(MAX(1,SUM($D33:E33)),Assumptions!$C$41)) -> 60 | F32: =MAX($D$32*Assumptions!$C$40,$D$32*Assumptions!$C$10^LOG(MAX(1,SUM($D33:F33)),Assumptions!$C$41)) -> 52.57222 | G32: =MAX($D$32*Assumptions!$C$40,$D$32*Assumptions!$C$10^LOG(MAX(1,SUM($D33:G33)),Assumptions!$C$41)) -> 47.477827 | H32: =MAX($D$32*Assumptions!$C$40,$D$32*Assumptions!$C$10^LOG(MAX(1,SUM($D33:H33)),Assumptions!$C$41)) -> 44.965323 | I32: =MAX($D$32*Assumptions!$C$40,$D$32*Assumptions!$C$10^LOG(MAX(1,SUM($D33:I33)),Assumptions!$C$41)) -> 43.318584 | J32: =MAX($D$32*Assumptions!$C$40,$D$32*Assumptions!$C$10^LOG(MAX(1,SUM($D33:J33)),Assumptions!$C$41)) -> 42.104117 | K32: =MAX($D$32*Assumptions!$C$40,$D$32*Assumptions!$C$10^LOG(MAX(1,SUM($D33:K33)),Assumptions!$C$41)) -> 42 | L32: =MAX($D$32*Assumptions!$C$40,$D$32*Assumptions!$C$10^LOG(MAX(1,SUM($D33:L33)),Assumptions!$C$41)) -> 42 | M32: =MAX($D$32*Assumptions!$C$40,$D$32*Assumptions!$C$10^LOG(MAX(1,SUM($D33:M33)),Assumptions!$C$41)) -> 42
B33: Units shipped (#) | C33: yellow = input | D33: 0 | E33: 1 | F33: 2 | G33: 4 | H33: 4 | I33: 4 | J33: 4 | K33: 8 | L33: 8 | M33: 8
B34: Revenue (units × ASP) | D34: =D31*D33 -> 0 | E34: =E31*E33 -> 114 | F34: =F31*F33 -> 213.42111 | G34: =G31*G33 -> 405.63426 | H34: =H31*H33 -> 394.7554 | I34: =I31*I33 -> 387.45953 | J34: =J31*J33 -> 381.98957 | K34: =K31*K33 -> 763.03394 | ... M34: =M31*M33 -> 763.03394
B35: COGS - BoM (units × BoM) | D35: =D32*D33 -> 0 | E35: =E32*E33 -> 60 | F35: =F32*F33 -> 105.14444 | G35: =G32*G33 -> 189.91131 | H35: =H32*H33 -> 179.86129 | I35: =I32*I33 -> 173.27434 | J35: =J32*J33 -> 168.41647 | K35: =K32*K33 -> 336 | ... M35: =M32*M33 -> 336
B36: Contribution margin / unit | D36: =IF(D31=0,0,1-D32/D31) -> 0.47368421 | E36: =IF(E31=0,0,1-E32/E31) -> 0.47368421 | F36: =IF(F31=0,0,1-F32/F31) -> 0.50733815 | G36: =IF(G31=0,0,1-G32/G31) -> 0.53181641 | H36: =IF(H31=0,0,1-H32/H31) -> 0.54437281 | I36: =IF(I31=0,0,1-I32/I31) -> 0.55279371 | J36: =IF(J31=0,0,1-J32/J31) -> 0.55910715 | K36: =IF(K31=0,0,1-K32/K31) -> 0.55965262 | ... M36: =IF(M31=0,0,1-M32/M31) -> 0.55965262
B38: V2 totals
B39: Total revenue | D39: =D10+D18+D26+D34 -> 167 | E39: =E10+E18+E26+E34 -> 367.14503 | F39: =F10+F18+F26+F34 -> 640.43839 | G39: =G10+G18+G26+G34 -> 957.82988 | H39: =H10+H18+H26+H34 -> 1013.8838 | I39: =I10+I18+I26+I34 -> 1073.5207 | J39: =J10+J18+J26+J34 -> 1222.8329 | K39: =K10+K18+K26+K34 -> 1620.6105 | ... M39: =M10+M18+M26+M34 -> 1859.0586
B40: Total COGS (BoM) | D40: =D11+D19+D27+D35 -> 74.62 | E40: =E11+E19+E27+E35 -> 155.85214 | F40: =F11+F19+F27+F35 -> 258.54413 | G40: =G11+G19+G27+G35 -> 381.37881 | H40: =H11+H19+H27+H35 -> 396.58129 | I40: =I11+I19+I27+I35 -> 415.24684 | J40: =J11+J19+J27+J35 -> 464.56897 | K40: =K11+K19+K27+K35 -> 637.805 | ... M40: =M11+M19+M27+M35 -> 721.07
B41: Total units shipped | D41: =D9+D17+D25+D33 -> 11 | E41: =E9+E17+E25+E33 -> 21 | F41: =F9+F17+F25+F33 -> 36 | G41: =G9+G17+G25+G33 -> 52 | H41: =H9+H17+H25+H33 -> 64 | I41: =I9+I17+I25+I33 -> 76 | J41: =J9+J17+J25+J33 -> 91 | K41: =K9+K17+K25+K33 -> 105 | ... M41: =M9+M17+M25+M33 -> 123
B42: Gross profit (Revenue − BoM COGS) | D42: =D39-D40 -> 92.38 | E42: =E39-E40 -> 211.29288 | F42: =F39-F40 -> 381.89426 | G42: =G39-G40 -> 576.45107 | H42: =H39-H40 -> 617.30252 | I42: =I39-I40 -> 658.27391 | J42: =J39-J40 -> 758.26392 | K42: =K39-K40 -> 982.80547 | ... M42: =M39-M40 -> 1137.9886
B43: Gross margin % | D43: =IFERROR((D39-D40)/D39,0) -> 0.55317365 | E43: =IFERROR((E39-E40)/E39,0) -> 0.57550251 | F43: =IFERROR((F39-F40)/F39,0) -> 0.59630133 | G43: =IFERROR((G39-G40)/G39,0) -> 0.60183033 | H43: =IFERROR((H39-H40)/H39,0) -> 0.60884937 | I43: =IFERROR((I39-I40)/I39,0) -> 0.61319161 | J43: =IFERROR((J39-J40)/J39,0) -> 0.62008794 | K43: =IFERROR((K39-K40)/K39,0) -> 0.60644152 | ... M43: =IFERROR((M39-M40)/M39,0) -> 0.61213164
B44: Cumulative revenue | D44: =D39 -> 167 | E44: =D44+E39 -> 534.14503 | F44: =E44+F39 -> 1174.5834 | G44: =F44+G39 -> 2132.4133 | H44: =G44+H39 -> 3146.2971 | I44: =H44+I39 -> 4219.8179 | J44: =I44+J39 -> 5442.6508 | K44: =J44+K39 -> 7063.2612 | L44: =K44+L39 -> 8838.6538 | M44: =L44+M39 -> 10697.712

Sheet V3_CUAS
B1: READ ONLY SUPPORTING DETAIL - Revenue is recognized via Backlog!Section L (rows 89-95). Editing units/ASP here does NOT change consolidated revenue, but DOES rescale COGS (BoM x delivered_rev / V-sheet rev). Do not edit unless you intend to re-baseline the BoM ratio.
B2: V3 - Counter-UAS (Anti-Drone) | Domain: Land/Air (RF + AI fusion) | Launch: Y2
B3: Description | C3: Multi-layered C-UAS: radar + RF + EO/IR + AI fusion + soft- and hard-kill effectors. Rapid product cycle - MVP fielded Y2 using shared RF/DSP/AI stack, scaled Y3+.
B5: Line | C5: Driver | D5: Y1 | E5: Y2 | F5: Y3 | G5: Y4 | H5: Y5 | I5: Y6 | J5: Y7 | K5: Y8 | L5: Y9 | M5: Y10
B6: CUAS-A - Dismounted Soldier Kit
B7: ASP / unit (₹ Cr) | C7: yellow = input | D7: 1.5 | E7: =$D$7*(E8/$D$8)^Assumptions!$C$39 -> 1.3060029 | F7: =$D$7*(F8/$D$8)^Assumptions!$C$39 -> 1.25499 | G7: =$D$7*(G8/$D$8)^Assumptions!$C$39 -> 1.25499 | H7: =$D$7*(H8/$D$8)^Assumptions!$C$39 -> 1.25499 | I7: =$D$7*(I8/$D$8)^Assumptions!$C$39 -> 1.25499 | J7: =$D$7*(J8/$D$8)^Assumptions!$C$39 -> 1.25499 | K7: =$D$7*(K8/$D$8)^Assumptions!$C$39 -> 1.25499 | L7: =$D$7*(L8/$D$8)^Assumptions!$C$39 -> 1.25499 | M7: =$D$7*(M8/$D$8)^Assumptions!$C$39 -> 1.25499
B8: BoM / unit (₹ Cr) | C8: yellow = input | D8: 0.9 | E8: =MAX($D$8*Assumptions!$C$40,$D$8*Assumptions!$C$10^LOG(MAX(1,SUM($D9:E9)),Assumptions!$C$41)) -> 0.68225743 | F8: =MAX($D$8*Assumptions!$C$40,$D$8*Assumptions!$C$10^LOG(MAX(1,SUM($D9:F9)),Assumptions!$C$41)) -> 0.63 | G8: =MAX($D$8*Assumptions!$C$40,$D$8*Assumptions!$C$10^LOG(MAX(1,SUM($D9:G9)),Assumptions!$C$41)) -> 0.63 | H8: =MAX($D$8*Assumptions!$C$40,$D$8*Assumptions!$C$10^LOG(MAX(1,SUM($D9:H9)),Assumptions!$C$41)) -> 0.63 | I8: =MAX($D$8*Assumptions!$C$40,$D$8*Assumptions!$C$10^LOG(MAX(1,SUM($D9:I9)),Assumptions!$C$41)) -> 0.63 | J8: =MAX($D$8*Assumptions!$C$40,$D$8*Assumptions!$C$10^LOG(MAX(1,SUM($D9:J9)),Assumptions!$C$41)) -> 0.63 | K8: =MAX($D$8*Assumptions!$C$40,$D$8*Assumptions!$C$10^LOG(MAX(1,SUM($D9:K9)),Assumptions!$C$41)) -> 0.63 | L8: =MAX($D$8*Assumptions!$C$40,$D$8*Assumptions!$C$10^LOG(MAX(1,SUM($D9:L9)),Assumptions!$C$41)) -> 0.63 | M8: =MAX($D$8*Assumptions!$C$40,$D$8*Assumptions!$C$10^LOG(MAX(1,SUM($D9:M9)),Assumptions!$C$41)) -> 0.63
B9: Units shipped (#) | C9: yellow = input | D9: 0 | E9: 10 | F9: 40 | G9: 80 | H9: 130 | I9: 180 | J9: 220 | K9: 260 | L9: 290 | M9: 320
B10: Revenue (units × ASP) | D10: =D7*D9 -> 0 | E10: =E7*E9 -> 13.060029 | F10: =F7*F9 -> 50.199602 | G10: =G7*G9 -> 100.3992 | H10: =H7*H9 -> 163.14871 | I10: =I7*I9 -> 225.89821 | J10: =J7*J9 -> 276.09781 | K10: =K7*K9 -> 326.29741 | ... M10: =M7*M9 -> 401.59681
B11: COGS - BoM (units × BoM) | D11: =D8*D9 -> 0 | E11: =E8*E9 -> 6.8225743 | F11: =F8*F9 -> 25.2 | G11: =G8*G9 -> 50.4 | H11: =H8*H9 -> 81.9 | I11: =I8*I9 -> 113.4 | J11: =J8*J9 -> 138.6 | K11: =K8*K9 -> 163.8 | ... M11: =M8*M9 -> 201.6
B12: Contribution margin / unit | D12: =IF(D7=0,0,1-D8/D7) -> 0.4 | E12: =IF(E7=0,0,1-E8/E7) -> 0.47759884 | F12: =IF(F7=0,0,1-F8/F7) -> 0.49800398 | G12: =IF(G7=0,0,1-G8/G7) -> 0.49800398 | H12: =IF(H7=0,0,1-H8/H7) -> 0.49800398 | I12: =IF(I7=0,0,1-I8/I7) -> 0.49800398 | J12: =IF(J7=0,0,1-J8/J7) -> 0.49800398 | K12: =IF(K7=0,0,1-K8/K7) -> 0.49800398 | ... M12: =IF(M7=0,0,1-M8/M7) -> 0.49800398
B14: CUAS-B - Vehicle-Mounted System
B15: ASP / unit (₹ Cr) | C15: yellow = input | D15: 14.25 | E15: =$D$15*(E16/$D$16)^Assumptions!$C$39 -> 13.33882 | F15: =$D$15*(F16/$D$16)^Assumptions!$C$39 -> 12.407028 | G15: =$D$15*(G16/$D$16)^Assumptions!$C$39 -> 11.922405 | H15: =$D$15*(H16/$D$16)^Assumptions!$C$39 -> 11.922405 | I15: =$D$15*(I16/$D$16)^Assumptions!$C$39 -> 11.922405 | J15: =$D$15*(J16/$D$16)^Assumptions!$C$39 -> 11.922405 | K15: =$D$15*(K16/$D$16)^Assumptions!$C$39 -> 11.922405 | L15: =$D$15*(L16/$D$16)^Assumptions!$C$39 -> 11.922405 | M15: =$D$15*(M16/$D$16)^Assumptions!$C$39 -> 11.922405
B16: BoM / unit (₹ Cr) | C16: yellow = input | D16: 8 | E16: =MAX($D$16*Assumptions!$C$40,$D$16*Assumptions!$C$10^LOG(MAX(1,SUM($D17:E17)),Assumptions!$C$41)) -> 7.0096293 | F16: =MAX($D$16*Assumptions!$C$40,$D$16*Assumptions!$C$10^LOG(MAX(1,SUM($D17:F17)),Assumptions!$C$41)) -> 6.0645105 | G16: =MAX($D$16*Assumptions!$C$40,$D$16*Assumptions!$C$10^LOG(MAX(1,SUM($D17:G17)),Assumptions!$C$41)) -> 5.6 | H16: =MAX($D$16*Assumptions!$C$40,$D$16*Assumptions!$C$10^LOG(MAX(1,SUM($D17:H17)),Assumptions!$C$41)) -> 5.6 | I16: =MAX($D$16*Assumptions!$C$40,$D$16*Assumptions!$C$10^LOG(MAX(1,SUM($D17:I17)),Assumptions!$C$41)) -> 5.6 | J16: =MAX($D$16*Assumptions!$C$40,$D$16*Assumptions!$C$10^LOG(MAX(1,SUM($D17:J17)),Assumptions!$C$41)) -> 5.6 | K16: =MAX($D$16*Assumptions!$C$40,$D$16*Assumptions!$C$10^LOG(MAX(1,SUM($D17:K17)),Assumptions!$C$41)) -> 5.6 | L16: =MAX($D$16*Assumptions!$C$40,$D$16*Assumptions!$C$10^LOG(MAX(1,SUM($D17:L17)),Assumptions!$C$41)) -> 5.6 | M16: =MAX($D$16*Assumptions!$C$40,$D$16*Assumptions!$C$10^LOG(MAX(1,SUM($D17:M17)),Assumptions!$C$41)) -> 5.6
B17: Units shipped (#) | C17: yellow = input | D17: 0 | E17: 3 | F17: 7 | G17: 14 | H17: 22 | I17: 30 | J17: 38 | K17: 46 | L17: 52 | M17: 56
B18: Revenue (units × ASP) | D18: =D15*D17 -> 0 | E18: =E15*E17 -> 40.016459 | F18: =F15*F17 -> 86.849193 | G18: =G15*G17 -> 166.91368 | H18: =H15*H17 -> 262.29292 | I18: =I15*I17 -> 357.67216 | J18: =J15*J17 -> 453.0514 | K18: =K15*K17 -> 548.43065 | ... M18: =M15*M17 -> 667.6547
B19: COGS - BoM (units × BoM) | D19: =D16*D17 -> 0 | E19: =E16*E17 -> 21.028888 | F19: =F16*F17 -> 42.451574 | G19: =G16*G17 -> 78.4 | H19: =H16*H17 -> 123.2 | I19: =I16*I17 -> 168 | J19: =J16*J17 -> 212.8 | K19: =K16*K17 -> 257.6 | ... M19: =M16*M17 -> 313.6
B20: Contribution margin / unit | D20: =IF(D15=0,0,1-D16/D15) -> 0.43859649 | E20: =IF(E15=0,0,1-E16/E15) -> 0.47449403 | F20: =IF(F15=0,0,1-F16/F15) -> 0.51120359 | G20: =IF(G15=0,0,1-G16/G15) -> 0.53029613 | H20: =IF(H15=0,0,1-H16/H15) -> 0.53029613 | I20: =IF(I15=0,0,1-I16/I15) -> 0.53029613 | J20: =IF(J15=0,0,1-J16/J15) -> 0.53029613 | K20: =IF(K15=0,0,1-K16/K15) -> 0.53029613 | ... M20: =IF(M15=0,0,1-M16/M15) -> 0.53029613
B22: CUAS-C - Fixed Site Integrated C-UAS
B23: ASP / unit (₹ Cr) | C23: yellow = input | D23: 65 | E23: =$D$23*(E24/$D$24)^Assumptions!$C$39 -> 65 | F23: =$D$23*(F24/$D$24)^Assumptions!$C$39 -> 65 | G23: =$D$23*(G24/$D$24)^Assumptions!$C$39 -> 60.843738 | H23: =$D$23*(H24/$D$24)^Assumptions!$C$39 -> 58.359264 | I23: =$D$23*(I24/$D$24)^Assumptions!$C$39 -> 56.593459 | J23: =$D$23*(J24/$D$24)^Assumptions!$C$39 -> 55.229976 | K23: =$D$23*(K24/$D$24)^Assumptions!$C$39 -> 54.382902 | L23: =$D$23*(L24/$D$24)^Assumptions!$C$39 -> 54.382902 | M23: =$D$23*(M24/$D$24)^Assumptions!$C$39 -> 54.382902
B24: BoM / unit (₹ Cr) | C24: yellow = input | D24: 27.075 | E24: =MAX($D$24*Assumptions!$C$40,$D$24*Assumptions!$C$10^LOG(MAX(1,SUM($D25:E25)),Assumptions!$C$41)) -> 27.075 | F24: =MAX($D$24*Assumptions!$C$40,$D$24*Assumptions!$C$10^LOG(MAX(1,SUM($D25:F25)),Assumptions!$C$41)) -> 27.075 | G24: =MAX($D$24*Assumptions!$C$40,$D$24*Assumptions!$C$10^LOG(MAX(1,SUM($D25:G25)),Assumptions!$C$41)) -> 23.723214 | H24: =MAX($D$24*Assumptions!$C$40,$D$24*Assumptions!$C$10^LOG(MAX(1,SUM($D25:H25)),Assumptions!$C$41)) -> 21.825357 | I24: =MAX($D$24*Assumptions!$C$40,$D$24*Assumptions!$C$10^LOG(MAX(1,SUM($D25:I25)),Assumptions!$C$41)) -> 20.524578 | J24: =MAX($D$24*Assumptions!$C$40,$D$24*Assumptions!$C$10^LOG(MAX(1,SUM($D25:J25)),Assumptions!$C$41)) -> 19.547511 | K24: =MAX($D$24*Assumptions!$C$40,$D$24*Assumptions!$C$10^LOG(MAX(1,SUM($D25:K25)),Assumptions!$C$41)) -> 18.9525 | L24: =MAX($D$24*Assumptions!$C$40,$D$24*Assumptions!$C$10^LOG(MAX(1,SUM($D25:L25)),Assumptions!$C$41)) -> 18.9525 | M24: =MAX($D$24*Assumptions!$C$40,$D$24*Assumptions!$C$10^LOG(MAX(1,SUM($D25:M25)),Assumptions!$C$41)) -> 18.9525
B25: Units shipped (#) | C25: yellow = input | D25: 0 | E25: 0 | F25: 1 | G25: 2 | H25: 3 | I25: 4 | J25: 5 | K25: 6 | L25: 6 | M25: 7
B26: Revenue (units × ASP) | D26: =D23*D25 -> 0 | E26: =E23*E25 -> 0 | F26: =F23*F25 -> 65 | G26: =G23*G25 -> 121.68748 | H26: =H23*H25 -> 175.07779 | I26: =I23*I25 -> 226.37384 | J26: =J23*J25 -> 276.14988 | K26: =K23*K25 -> 326.29741 | ... M26: =M23*M25 -> 380.68031
B27: COGS - BoM (units × BoM) | D27: =D24*D25 -> 0 | E27: =E24*E25 -> 0 | F27: =F24*F25 -> 27.075 | G27: =G24*G25 -> 47.446428 | H27: =H24*H25 -> 65.476071 | I27: =I24*I25 -> 82.098311 | J27: =J24*J25 -> 97.737556 | K27: =K24*K25 -> 113.715 | ... M27: =M24*M25 -> 132.6675
B28: Contribution margin / unit | D28: =IF(D23=0,0,1-D24/D23) -> 0.58346154 | E28: =IF(E23=0,0,1-E24/E23) -> 0.58346154 | F28: =IF(F23=0,0,1-F24/F23) -> 0.58346154 | G28: =IF(G23=0,0,1-G24/G23) -> 0.61009604 | H28: =IF(H23=0,0,1-H24/H23) -> 0.62601726 | I28: =IF(I23=0,0,1-I24/I23) -> 0.63733304 | J28: =IF(J23=0,0,1-J24/J23) -> 0.64607062 | K28: =IF(K23=0,0,1-K24/K23) -> 0.65149892 | ... M28: =IF(M23=0,0,1-M24/M23) -> 0.65149892
B30: V3 totals
B31: Total revenue | D31: =D10+D18+D26 -> 0 | E31: =E10+E18+E26 -> 53.076488 | F31: =F10+F18+F26 -> 202.04879 | G31: =G10+G18+G26 -> 389.00035 | H31: =H10+H18+H26 -> 600.51941 | I31: =I10+I18+I26 -> 809.9442 | J31: =J10+J18+J26 -> 1005.2991 | K31: =K10+K18+K26 -> 1201.0255 | ... M31: =M10+M18+M26 -> 1449.9318
B32: Total COGS (BoM) | D32: =D11+D19+D27 -> 0 | E32: =E11+E19+E27 -> 27.851462 | F32: =F11+F19+F27 -> 94.726574 | G32: =G11+G19+G27 -> 176.24643 | H32: =H11+H19+H27 -> 270.57607 | I32: =I11+I19+I27 -> 363.49831 | J32: =J11+J19+J27 -> 449.13756 | K32: =K11+K19+K27 -> 535.115 | ... M32: =M11+M19+M27 -> 647.8675
B33: Total units shipped | D33: =D9+D17+D25 -> 0 | E33: =E9+E17+E25 -> 13 | F33: =F9+F17+F25 -> 48 | G33: =G9+G17+G25 -> 96 | H33: =H9+H17+H25 -> 155 | I33: =I9+I17+I25 -> 214 | J33: =J9+J17+J25 -> 263 | K33: =K9+K17+K25 -> 312 | ... M33: =M9+M17+M25 -> 383
B34: Gross profit (Revenue − BoM COGS) | D34: =D31-D32 -> 0 | E34: =E31-E32 -> 25.225025 | F34: =F31-F32 -> 107.32222 | G34: =G31-G32 -> 212.75393 | H34: =H31-H32 -> 329.94334 | I34: =I31-I32 -> 446.44589 | J34: =J31-J32 -> 556.16154 | K34: =K31-K32 -> 665.91047 | ... M34: =M31-M32 -> 802.06433
B35: Gross margin % | D35: =IFERROR((D31-D32)/D31,0) -> 0 | E35: =IFERROR((E31-E32)/E31,0) -> 0.475258 | F35: =IFERROR((F31-F32)/F31,0) -> 0.53116982 | G35: =IFERROR((G31-G32)/G31,0) -> 0.54692476 | H35: =IFERROR((H31-H32)/H31,0) -> 0.54942994 | I35: =IFERROR((I31-I32)/I31,0) -> 0.55120574 | J35: =IFERROR((J31-J32)/J31,0) -> 0.55322992 | K35: =IFERROR((K31-K32)/K31,0) -> 0.55445158 | ... M35: =IFERROR((M31-M32)/M31,0) -> 0.55317382
B36: Cumulative revenue | D36: =D31 -> 0 | E36: =D36+E31 -> 53.076488 | F36: =E36+F31 -> 255.12528 | G36: =F36+G31 -> 644.12564 | H36: =G36+H31 -> 1244.6451 | I36: =H36+I31 -> 2054.5893 | J36: =I36+J31 -> 3059.8884 | K36: =J36+K31 -> 4260.9138 | L36: =K36+L31 -> 5571.1234 | M36: =L36+M31 -> 7021.0552

Sheet V4_UAS_MALE
B1: READ ONLY SUPPORTING DETAIL - Revenue is recognized via Backlog!Section L (rows 89-95). Editing units/ASP here does NOT change consolidated revenue, but DOES rescale COGS (BoM x delivered_rev / V-sheet rev). Do not edit unless you intend to re-baseline the BoM ratio.
B2: V4 - MALE-class ISR UAS | Domain: Air (SysEng + SW + AI) | Launch: Y4
B3: Description | C3: MALE UAV - longest cycle in the portfolio (airframe + airworthiness). Compressed via MOSA architecture and reuse of mission-computer/AI stack; baseline ISR ships Y4, mission variants Y5+.
B5: Line | C5: Driver | D5: Y1 | E5: Y2 | F5: Y3 | G5: Y4 | H5: Y5 | I5: Y6 | J5: Y7 | K5: Y8 | L5: Y9 | M5: Y10
B6: UAS-A - MALE ISR baseline
B7: ASP / unit (₹ Cr) | C7: yellow = input | D7: 150 | E7: =$D$7*(E8/$D$8)^Assumptions!$C$39 -> 150 | F7: =$D$7*(F8/$D$8)^Assumptions!$C$39 -> 150 | G7: =$D$7*(G8/$D$8)^Assumptions!$C$39 -> 150 | H7: =$D$7*(H8/$D$8)^Assumptions!$C$39 -> 140.40863 | I7: =$D$7*(I8/$D$8)^Assumptions!$C$39 -> 134.67522 | J7: =$D$7*(J8/$D$8)^Assumptions!$C$39 -> 130.60029 | K7: =$D$7*(K8/$D$8)^Assumptions!$C$39 -> 127.45379 | L7: =$D$7*(L8/$D$8)^Assumptions!$C$39 -> 125.499 | M7: =$D$7*(M8/$D$8)^Assumptions!$C$39 -> 125.499
B8: BoM / unit (₹ Cr) | C8: yellow = input | D8: 51.3 | E8: =MAX($D$8*Assumptions!$C$40,$D$8*Assumptions!$C$10^LOG(MAX(1,SUM($D9:E9)),Assumptions!$C$41)) -> 51.3 | F8: =MAX($D$8*Assumptions!$C$40,$D$8*Assumptions!$C$10^LOG(MAX(1,SUM($D9:F9)),Assumptions!$C$41)) -> 51.3 | G8: =MAX($D$8*Assumptions!$C$40,$D$8*Assumptions!$C$10^LOG(MAX(1,SUM($D9:G9)),Assumptions!$C$41)) -> 51.3 | H8: =MAX($D$8*Assumptions!$C$40,$D$8*Assumptions!$C$10^LOG(MAX(1,SUM($D9:H9)),Assumptions!$C$41)) -> 44.949248 | I8: =MAX($D$8*Assumptions!$C$40,$D$8*Assumptions!$C$10^LOG(MAX(1,SUM($D9:I9)),Assumptions!$C$41)) -> 41.353308 | J8: =MAX($D$8*Assumptions!$C$40,$D$8*Assumptions!$C$10^LOG(MAX(1,SUM($D9:J9)),Assumptions!$C$41)) -> 38.888674 | K8: =MAX($D$8*Assumptions!$C$40,$D$8*Assumptions!$C$10^LOG(MAX(1,SUM($D9:K9)),Assumptions!$C$41)) -> 37.037389 | L8: =MAX($D$8*Assumptions!$C$40,$D$8*Assumptions!$C$10^LOG(MAX(1,SUM($D9:L9)),Assumptions!$C$41)) -> 35.91 | M8: =MAX($D$8*Assumptions!$C$40,$D$8*Assumptions!$C$10^LOG(MAX(1,SUM($D9:M9)),Assumptions!$C$41)) -> 35.91
B9: Units shipped (#) | C9: yellow = input | D9: 0 | E9: 0 | F9: 0 | G9: 1 | H9: 2 | I9: 3 | J9: 4 | K9: 5 | L9: 6 | M9: 7
B10: Revenue (units × ASP) | D10: =D7*D9 -> 0 | E10: =E7*E9 -> 0 | F10: =F7*F9 -> 0 | G10: =G7*G9 -> 150 | H10: =H7*H9 -> 280.81725 | I10: =I7*I9 -> 404.02567 | J10: =J7*J9 -> 522.40116 | K10: =K7*K9 -> 637.26896 | ... M10: =M7*M9 -> 878.49303
B11: COGS - BoM (units × BoM) | D11: =D8*D9 -> 0 | E11: =E8*E9 -> 0 | F11: =F8*F9 -> 0 | G11: =G8*G9 -> 51.3 | H11: =H8*H9 -> 89.898496 | I11: =I8*I9 -> 124.05992 | J11: =J8*J9 -> 155.55469 | K11: =K8*K9 -> 185.18695 | ... M11: =M8*M9 -> 251.37
B12: Contribution margin / unit | D12: =IF(D7=0,0,1-D8/D7) -> 0.658 | E12: =IF(E7=0,0,1-E8/E7) -> 0.658 | F12: =IF(F7=0,0,1-F8/F7) -> 0.658 | G12: =IF(G7=0,0,1-G8/G7) -> 0.658 | H12: =IF(H7=0,0,1-H8/H7) -> 0.67986833 | I12: =IF(I7=0,0,1-I8/I7) -> 0.69294049 | J12: =IF(J7=0,0,1-J8/J7) -> 0.70223134 | K12: =IF(K7=0,0,1-K8/K7) -> 0.70940535 | ... M12: =IF(M7=0,0,1-M8/M7) -> 0.71386227
B14: UAS-B - MALE strike-capable
B15: ASP / unit (₹ Cr) | C15: yellow = input | D15: 210 | E15: =$D$15*(E16/$D$16)^Assumptions!$C$39 -> 210 | F15: =$D$15*(F16/$D$16)^Assumptions!$C$39 -> 210 | G15: =$D$15*(G16/$D$16)^Assumptions!$C$39 -> 210 | H15: =$D$15*(H16/$D$16)^Assumptions!$C$39 -> 210 | I15: =$D$15*(I16/$D$16)^Assumptions!$C$39 -> 201.42492 | J15: =$D$15*(J16/$D$16)^Assumptions!$C$39 -> 193.2 | K15: =$D$15*(K16/$D$16)^Assumptions!$C$39 -> 188.54531 | L15: =$D$15*(L16/$D$16)^Assumptions!$C$39 -> 184.00277 | M15: =$D$15*(M16/$D$16)^Assumptions!$C$39 -> 180.84631
B16: BoM / unit (₹ Cr) | C16: yellow = input | D16: 75.05 | E16: =MAX($D$16*Assumptions!$C$40,$D$16*Assumptions!$C$10^LOG(MAX(1,SUM($D17:E17)),Assumptions!$C$41)) -> 75.05 | F16: =MAX($D$16*Assumptions!$C$40,$D$16*Assumptions!$C$10^LOG(MAX(1,SUM($D17:F17)),Assumptions!$C$41)) -> 75.05 | G16: =MAX($D$16*Assumptions!$C$40,$D$16*Assumptions!$C$10^LOG(MAX(1,SUM($D17:G17)),Assumptions!$C$41)) -> 75.05 | H16: =MAX($D$16*Assumptions!$C$40,$D$16*Assumptions!$C$10^LOG(MAX(1,SUM($D17:H17)),Assumptions!$C$41)) -> 75.05 | I16: =MAX($D$16*Assumptions!$C$40,$D$16*Assumptions!$C$10^LOG(MAX(1,SUM($D17:I17)),Assumptions!$C$41)) -> 69.046 | J16: =MAX($D$16*Assumptions!$C$40,$D$16*Assumptions!$C$10^LOG(MAX(1,SUM($D17:J17)),Assumptions!$C$41)) -> 63.52232 | K16: =MAX($D$16*Assumptions!$C$40,$D$16*Assumptions!$C$10^LOG(MAX(1,SUM($D17:K17)),Assumptions!$C$41)) -> 60.498358 | L16: =MAX($D$16*Assumptions!$C$40,$D$16*Assumptions!$C$10^LOG(MAX(1,SUM($D17:L17)),Assumptions!$C$41)) -> 57.618351 | M16: =MAX($D$16*Assumptions!$C$40,$D$16*Assumptions!$C$10^LOG(MAX(1,SUM($D17:M17)),Assumptions!$C$41)) -> 55.658489
B17: Units shipped (#) | C17: yellow = input | D17: 0 | E17: 0 | F17: 0 | G17: 0 | H17: 1 | I17: 1 | J17: 2 | K17: 2 | L17: 3 | M17: 3
B18: Revenue (units × ASP) | D18: =D15*D17 -> 0 | E18: =E15*E17 -> 0 | F18: =F15*F17 -> 0 | G18: =G15*G17 -> 0 | H18: =H15*H17 -> 210 | I18: =I15*I17 -> 201.42492 | J18: =J15*J17 -> 386.4 | K18: =K15*K17 -> 377.09063 | ... M18: =M15*M17 -> 542.53893
B19: COGS - BoM (units × BoM) | D19: =D16*D17 -> 0 | E19: =E16*E17 -> 0 | F19: =F16*F17 -> 0 | G19: =G16*G17 -> 0 | H19: =H16*H17 -> 75.05 | I19: =I16*I17 -> 69.046 | J19: =J16*J17 -> 127.04464 | K19: =K16*K17 -> 120.99672 | ... M19: =M16*M17 -> 166.97547
B20: Contribution margin / unit | D20: =IF(D15=0,0,1-D16/D15) -> 0.64261905 | E20: =IF(E15=0,0,1-E16/E15) -> 0.64261905 | F20: =IF(F15=0,0,1-F16/F15) -> 0.64261905 | G20: =IF(G15=0,0,1-G16/G15) -> 0.64261905 | H20: =IF(H15=0,0,1-H16/H15) -> 0.64261905 | I20: =IF(I15=0,0,1-I16/I15) -> 0.65721223 | J20: =IF(J15=0,0,1-J16/J15) -> 0.67120952 | K20: =IF(K15=0,0,1-K16/K15) -> 0.67913094 | ... M20: =IF(M15=0,0,1-M16/M15) -> 0.69223321
B22: UAS-C - MALE SIGINT/EW mission variant
B23: ASP / unit (₹ Cr) | C23: yellow = input | D23: 200 | E23: =$D$23*(E24/$D$24)^Assumptions!$C$39 -> 200 | F23: =$D$23*(F24/$D$24)^Assumptions!$C$39 -> 200 | G23: =$D$23*(G24/$D$24)^Assumptions!$C$39 -> 200 | H23: =$D$23*(H24/$D$24)^Assumptions!$C$39 -> 191.83326 | I23: =$D$23*(I24/$D$24)^Assumptions!$C$39 -> 184 | J23: =$D$23*(J24/$D$24)^Assumptions!$C$39 -> 179.56696 | K23: =$D$23*(K24/$D$24)^Assumptions!$C$39 -> 175.24073 | L23: =$D$23*(L24/$D$24)^Assumptions!$C$39 -> 172.23458 | M23: =$D$23*(M24/$D$24)^Assumptions!$C$39 -> 169.28
B24: BoM / unit (₹ Cr) | C24: yellow = input | D24: 64.6 | E24: =MAX($D$24*Assumptions!$C$40,$D$24*Assumptions!$C$10^LOG(MAX(1,SUM($D25:E25)),Assumptions!$C$41)) -> 64.6 | F24: =MAX($D$24*Assumptions!$C$40,$D$24*Assumptions!$C$10^LOG(MAX(1,SUM($D25:F25)),Assumptions!$C$41)) -> 64.6 | G24: =MAX($D$24*Assumptions!$C$40,$D$24*Assumptions!$C$10^LOG(MAX(1,SUM($D25:G25)),Assumptions!$C$41)) -> 64.6 | H24: =MAX($D$24*Assumptions!$C$40,$D$24*Assumptions!$C$10^LOG(MAX(1,SUM($D25:H25)),Assumptions!$C$41)) -> 59.432 | I24: =MAX($D$24*Assumptions!$C$40,$D$24*Assumptions!$C$10^LOG(MAX(1,SUM($D25:I25)),Assumptions!$C$41)) -> 54.67744 | J24: =MAX($D$24*Assumptions!$C$40,$D$24*Assumptions!$C$10^LOG(MAX(1,SUM($D25:J25)),Assumptions!$C$41)) -> 52.074536 | K24: =MAX($D$24*Assumptions!$C$40,$D$24*Assumptions!$C$10^LOG(MAX(1,SUM($D25:K25)),Assumptions!$C$41)) -> 49.595543 | L24: =MAX($D$24*Assumptions!$C$40,$D$24*Assumptions!$C$10^LOG(MAX(1,SUM($D25:L25)),Assumptions!$C$41)) -> 47.908573 | M24: =MAX($D$24*Assumptions!$C$40,$D$24*Assumptions!$C$10^LOG(MAX(1,SUM($D25:M25)),Assumptions!$C$41)) -> 46.278985
B25: Units shipped (#) | C25: yellow = input | D25: 0 | E25: 0 | F25: 0 | G25: 1 | H25: 1 | I25: 2 | J25: 2 | K25: 3 | L25: 3 | M25: 4
B26: Revenue (units × ASP) | D26: =D23*D25 -> 0 | E26: =E23*E25 -> 0 | F26: =F23*F25 -> 0 | G26: =G23*G25 -> 200 | H26: =H23*H25 -> 191.83326 | I26: =I23*I25 -> 368 | J26: =J23*J25 -> 359.13393 | K26: =K23*K25 -> 525.7222 | ... M26: =M23*M25 -> 677.12
B27: COGS - BoM (units × BoM) | D27: =D24*D25 -> 0 | E27: =E24*E25 -> 0 | F27: =F24*F25 -> 0 | G27: =G24*G25 -> 64.6 | H27: =H24*H25 -> 59.432 | I27: =I24*I25 -> 109.35488 | J27: =J24*J25 -> 104.14907 | K27: =K24*K25 -> 148.78663 | ... M27: =M24*M25 -> 185.11594
B28: Contribution margin / unit | D28: =IF(D23=0,0,1-D24/D23) -> 0.677 | E28: =IF(E23=0,0,1-E24/E23) -> 0.677 | F28: =IF(F23=0,0,1-F24/F23) -> 0.677 | G28: =IF(G23=0,0,1-G24/G23) -> 0.677 | H28: =IF(H23=0,0,1-H24/H23) -> 0.69018928 | I28: =IF(I23=0,0,1-I24/I23) -> 0.70284 | J28: =IF(J23=0,0,1-J24/J23) -> 0.70999935 | K28: =IF(K23=0,0,1-K24/K23) -> 0.71698622 | ... M28: =IF(M23=0,0,1-M24/M23) -> 0.7266128
B30: V4 totals
B31: Total revenue | D31: =D10+D18+D26 -> 0 | E31: =E10+E18+E26 -> 0 | F31: =F10+F18+F26 -> 0 | G31: =G10+G18+G26 -> 350 | H31: =H10+H18+H26 -> 682.65051 | I31: =I10+I18+I26 -> 973.45059 | J31: =J10+J18+J26 -> 1267.9351 | K31: =K10+K18+K26 -> 1540.0818 | ... M31: =M10+M18+M26 -> 2098.152
B32: Total COGS (BoM) | D32: =D11+D19+D27 -> 0 | E32: =E11+E19+E27 -> 0 | F32: =F11+F19+F27 -> 0 | G32: =G11+G19+G27 -> 115.9 | H32: =H11+H19+H27 -> 224.3805 | I32: =I11+I19+I27 -> 302.4608 | J32: =J11+J19+J27 -> 386.74841 | K32: =K11+K19+K27 -> 454.97029 | ... M32: =M11+M19+M27 -> 603.46141
B33: Total units shipped | D33: =D9+D17+D25 -> 0 | E33: =E9+E17+E25 -> 0 | F33: =F9+F17+F25 -> 0 | G33: =G9+G17+G25 -> 2 | H33: =H9+H17+H25 -> 4 | I33: =I9+I17+I25 -> 6 | J33: =J9+J17+J25 -> 8 | K33: =K9+K17+K25 -> 10 | ... M33: =M9+M17+M25 -> 14
B34: Gross profit (Revenue − BoM COGS) | D34: =D31-D32 -> 0 | E34: =E31-E32 -> 0 | F34: =F31-F32 -> 0 | G34: =G31-G32 -> 234.1 | H34: =H31-H32 -> 458.27002 | I34: =I31-I32 -> 670.98979 | J34: =J31-J32 -> 881.18668 | K34: =K31-K32 -> 1085.1115 | ... M34: =M31-M32 -> 1494.6906
B35: Gross margin % | D35: =IFERROR((D31-D32)/D31,0) -> 0 | E35: =IFERROR((E31-E32)/E31,0) -> 0 | F35: =IFERROR((F31-F32)/F31,0) -> 0 | G35: =IFERROR((G31-G32)/G31,0) -> 0.66885714 | H35: =IFERROR((H31-H32)/H31,0) -> 0.67130986 | I35: =IFERROR((I31-I32)/I31,0) -> 0.68929003 | J35: =IFERROR((J31-J32)/J31,0) -> 0.69497776 | K35: =IFERROR((K31-K32)/K31,0) -> 0.70458043 | ... M35: =IFERROR((M31-M32)/M31,0) -> 0.71238432
B36: Cumulative revenue | D36: =D31 -> 0 | E36: =D36+E31 -> 0 | F36: =E36+F31 -> 0 | G36: =F36+G31 -> 350 | H36: =G36+H31 -> 1032.6505 | I36: =H36+I31 -> 2006.1011 | J36: =I36+J31 -> 3274.0362 | K36: =J36+K31 -> 4814.118 | L36: =K36+L31 -> 6635.8241 | M36: =L36+M31 -> 8733.976

Sheet V5_Autonomous
B1: READ ONLY SUPPORTING DETAIL - Revenue is recognized via Backlog!Section L (rows 89-95). Editing units/ASP here does NOT change consolidated revenue, but DOES rescale COGS (BoM x delivered_rev / V-sheet rev). Do not edit unless you intend to re-baseline the BoM ratio.
B2: V5 - Autonomous Systems (AUV/USV) | Domain: Sea (SysEng + SW + AI) | Launch: Y3
B3: Description | C3: AUVs (small mine-hunting + large ASW) and USVs for persistent maritime surveillance. Rapid hull-iteration, autonomy stack reused from V6; small AUV ships Y3, large platforms Y4+.
B5: Line | C5: Driver | D5: Y1 | E5: Y2 | F5: Y3 | G5: Y4 | H5: Y5 | I5: Y6 | J5: Y7 | K5: Y8 | L5: Y9 | M5: Y10
B6: AUV-A - Small AUV (mine-hunting / survey)
B7: ASP / unit (₹ Cr) | C7: yellow = input | D7: 15 | E7: =$D$7*(E8/$D$8)^Assumptions!$C$39 -> 15 | F7: =$D$7*(F8/$D$8)^Assumptions!$C$39 -> 15 | G7: =$D$7*(G8/$D$8)^Assumptions!$C$39 -> 13.8 | H7: =$D$7*(H8/$D$8)^Assumptions!$C$39 -> 12.985375 | I7: =$D$7*(I8/$D$8)^Assumptions!$C$39 -> 12.5499 | J7: =$D$7*(J8/$D$8)^Assumptions!$C$39 -> 12.5499 | K7: =$D$7*(K8/$D$8)^Assumptions!$C$39 -> 12.5499 | L7: =$D$7*(L8/$D$8)^Assumptions!$C$39 -> 12.5499 | M7: =$D$7*(M8/$D$8)^Assumptions!$C$39 -> 12.5499
B8: BoM / unit (₹ Cr) | C8: yellow = input | D8: 4.085 | E8: =MAX($D$8*Assumptions!$C$40,$D$8*Assumptions!$C$10^LOG(MAX(1,SUM($D9:E9)),Assumptions!$C$41)) -> 4.085 | F8: =MAX($D$8*Assumptions!$C$40,$D$8*Assumptions!$C$10^LOG(MAX(1,SUM($D9:F9)),Assumptions!$C$41)) -> 4.085 | G8: =MAX($D$8*Assumptions!$C$40,$D$8*Assumptions!$C$10^LOG(MAX(1,SUM($D9:G9)),Assumptions!$C$41)) -> 3.457544 | H8: =MAX($D$8*Assumptions!$C$40,$D$8*Assumptions!$C$10^LOG(MAX(1,SUM($D9:H9)),Assumptions!$C$41)) -> 3.0613891 | I8: =MAX($D$8*Assumptions!$C$40,$D$8*Assumptions!$C$10^LOG(MAX(1,SUM($D9:I9)),Assumptions!$C$41)) -> 2.8595 | J8: =MAX($D$8*Assumptions!$C$40,$D$8*Assumptions!$C$10^LOG(MAX(1,SUM($D9:J9)),Assumptions!$C$41)) -> 2.8595 | K8: =MAX($D$8*Assumptions!$C$40,$D$8*Assumptions!$C$10^LOG(MAX(1,SUM($D9:K9)),Assumptions!$C$41)) -> 2.8595 | L8: =MAX($D$8*Assumptions!$C$40,$D$8*Assumptions!$C$10^LOG(MAX(1,SUM($D9:L9)),Assumptions!$C$41)) -> 2.8595 | M8: =MAX($D$8*Assumptions!$C$40,$D$8*Assumptions!$C$10^LOG(MAX(1,SUM($D9:M9)),Assumptions!$C$41)) -> 2.8595
B9: Units shipped (#) | C9: yellow = input | D9: 0 | E9: 0 | F9: 1 | G9: 3 | H9: 7 | I9: 12 | J9: 18 | K9: 24 | L9: 28 | M9: 32
B10: Revenue (units × ASP) | D10: =D7*D9 -> 0 | E10: =E7*E9 -> 0 | F10: =F7*F9 -> 15 | G10: =G7*G9 -> 41.4 | H10: =H7*H9 -> 90.897624 | I10: =I7*I9 -> 150.5988 | J10: =J7*J9 -> 225.89821 | K10: =K7*K9 -> 301.19761 | ... M10: =M7*M9 -> 401.59681
B11: COGS - BoM (units × BoM) | D11: =D8*D9 -> 0 | E11: =E8*E9 -> 0 | F11: =F8*F9 -> 4.085 | G11: =G8*G9 -> 10.372632 | H11: =H8*H9 -> 21.429723 | I11: =I8*I9 -> 34.314 | J11: =J8*J9 -> 51.471 | K11: =K8*K9 -> 68.628 | ... M11: =M8*M9 -> 91.504
B12: Contribution margin / unit | D12: =IF(D7=0,0,1-D8/D7) -> 0.72766667 | E12: =IF(E7=0,0,1-E8/E7) -> 0.72766667 | F12: =IF(F7=0,0,1-F8/F7) -> 0.72766667 | G12: =IF(G7=0,0,1-G8/G7) -> 0.74945333 | H12: =IF(H7=0,0,1-H8/H7) -> 0.76424331 | I12: =IF(I7=0,0,1-I8/I7) -> 0.77214959 | J12: =IF(J7=0,0,1-J8/J7) -> 0.77214959 | K12: =IF(K7=0,0,1-K8/K7) -> 0.77214959 | ... M12: =IF(M7=0,0,1-M8/M7) -> 0.77214959
B14: AUV-B - Large ASW-capable AUV
B15: ASP / unit (₹ Cr) | C15: yellow = input | D15: 60 | E15: =$D$15*(E16/$D$16)^Assumptions!$C$39 -> 60 | F15: =$D$15*(F16/$D$16)^Assumptions!$C$39 -> 60 | G15: =$D$15*(G16/$D$16)^Assumptions!$C$39 -> 60 | H15: =$D$15*(H16/$D$16)^Assumptions!$C$39 -> 60 | I15: =$D$15*(I16/$D$16)^Assumptions!$C$39 -> 57.549978 | J15: =$D$15*(J16/$D$16)^Assumptions!$C$39 -> 55.2 | K15: =$D$15*(K16/$D$16)^Assumptions!$C$39 -> 53.372929 | L15: =$D$15*(L16/$D$16)^Assumptions!$C$39 -> 52.240116 | M15: =$D$15*(M16/$D$16)^Assumptions!$C$39 -> 51.193515
B16: BoM / unit (₹ Cr) | C16: yellow = input | D16: 20.425 | E16: =MAX($D$16*Assumptions!$C$40,$D$16*Assumptions!$C$10^LOG(MAX(1,SUM($D17:E17)),Assumptions!$C$41)) -> 20.425 | F16: =MAX($D$16*Assumptions!$C$40,$D$16*Assumptions!$C$10^LOG(MAX(1,SUM($D17:F17)),Assumptions!$C$41)) -> 20.425 | G16: =MAX($D$16*Assumptions!$C$40,$D$16*Assumptions!$C$10^LOG(MAX(1,SUM($D17:G17)),Assumptions!$C$41)) -> 20.425 | H16: =MAX($D$16*Assumptions!$C$40,$D$16*Assumptions!$C$10^LOG(MAX(1,SUM($D17:H17)),Assumptions!$C$41)) -> 20.425 | I16: =MAX($D$16*Assumptions!$C$40,$D$16*Assumptions!$C$10^LOG(MAX(1,SUM($D17:I17)),Assumptions!$C$41)) -> 18.791 | J16: =MAX($D$16*Assumptions!$C$40,$D$16*Assumptions!$C$10^LOG(MAX(1,SUM($D17:J17)),Assumptions!$C$41)) -> 17.28772 | K16: =MAX($D$16*Assumptions!$C$40,$D$16*Assumptions!$C$10^LOG(MAX(1,SUM($D17:K17)),Assumptions!$C$41)) -> 16.162243 | L16: =MAX($D$16*Assumptions!$C$40,$D$16*Assumptions!$C$10^LOG(MAX(1,SUM($D17:L17)),Assumptions!$C$41)) -> 15.483453 | M16: =MAX($D$16*Assumptions!$C$40,$D$16*Assumptions!$C$10^LOG(MAX(1,SUM($D17:M17)),Assumptions!$C$41)) -> 14.869264
B17: Units shipped (#) | C17: yellow = input | D17: 0 | E17: 0 | F17: 0 | G17: 0 | H17: 1 | I17: 1 | J17: 2 | K17: 3 | L17: 3 | M17: 4
B18: Revenue (units × ASP) | D18: =D15*D17 -> 0 | E18: =E15*E17 -> 0 | F18: =F15*F17 -> 0 | G18: =G15*G17 -> 0 | H18: =H15*H17 -> 60 | I18: =I15*I17 -> 57.549978 | J18: =J15*J17 -> 110.4 | K18: =K15*K17 -> 160.11879 | ... M18: =M15*M17 -> 204.77406
B19: COGS - BoM (units × BoM) | D19: =D16*D17 -> 0 | E19: =E16*E17 -> 0 | F19: =F16*F17 -> 0 | G19: =G16*G17 -> 0 | H19: =H16*H17 -> 20.425 | I19: =I16*I17 -> 18.791 | J19: =J16*J17 -> 34.57544 | K19: =K16*K17 -> 48.48673 | ... M19: =M16*M17 -> 59.477056
B20: Contribution margin / unit | D20: =IF(D15=0,0,1-D16/D15) -> 0.65958333 | E20: =IF(E15=0,0,1-E16/E15) -> 0.65958333 | F20: =IF(F15=0,0,1-F16/F15) -> 0.65958333 | G20: =IF(G15=0,0,1-G16/G15) -> 0.65958333 | H20: =IF(H15=0,0,1-H16/H15) -> 0.65958333 | I20: =IF(I15=0,0,1-I16/I15) -> 0.6734838 | J20: =IF(J15=0,0,1-J16/J15) -> 0.68681667 | K20: =IF(K15=0,0,1-K16/K15) -> 0.69718275 | ... M20: =IF(M15=0,0,1-M16/M15) -> 0.7095479
B22: USV-A - Mid-size USV (ISR / C-UAS host)
B23: ASP / unit (₹ Cr) | C23: yellow = input | D23: 45 | E23: =$D$23*(E24/$D$24)^Assumptions!$C$39 -> 45 | F23: =$D$23*(F24/$D$24)^Assumptions!$C$39 -> 45 | G23: =$D$23*(G24/$D$24)^Assumptions!$C$39 -> 42.122588 | H23: =$D$23*(H24/$D$24)^Assumptions!$C$39 -> 40.029697 | I23: =$D$23*(I24/$D$24)^Assumptions!$C$39 -> 38.56666 | J23: =$D$23*(J24/$D$24)^Assumptions!$C$39 -> 37.649701 | K23: =$D$23*(K24/$D$24)^Assumptions!$C$39 -> 37.649701 | L23: =$D$23*(L24/$D$24)^Assumptions!$C$39 -> 37.649701 | M23: =$D$23*(M24/$D$24)^Assumptions!$C$39 -> 37.649701
B24: BoM / unit (₹ Cr) | C24: yellow = input | D24: 15.39 | E24: =MAX($D$24*Assumptions!$C$40,$D$24*Assumptions!$C$10^LOG(MAX(1,SUM($D25:E25)),Assumptions!$C$41)) -> 15.39 | F24: =MAX($D$24*Assumptions!$C$40,$D$24*Assumptions!$C$10^LOG(MAX(1,SUM($D25:F25)),Assumptions!$C$41)) -> 15.39 | G24: =MAX($D$24*Assumptions!$C$40,$D$24*Assumptions!$C$10^LOG(MAX(1,SUM($D25:G25)),Assumptions!$C$41)) -> 13.484774 | H24: =MAX($D$24*Assumptions!$C$40,$D$24*Assumptions!$C$10^LOG(MAX(1,SUM($D25:H25)),Assumptions!$C$41)) -> 12.178063 | I24: =MAX($D$24*Assumptions!$C$40,$D$24*Assumptions!$C$10^LOG(MAX(1,SUM($D25:I25)),Assumptions!$C$41)) -> 11.304143 | J24: =MAX($D$24*Assumptions!$C$40,$D$24*Assumptions!$C$10^LOG(MAX(1,SUM($D25:J25)),Assumptions!$C$41)) -> 10.773 | K24: =MAX($D$24*Assumptions!$C$40,$D$24*Assumptions!$C$10^LOG(MAX(1,SUM($D25:K25)),Assumptions!$C$41)) -> 10.773 | L24: =MAX($D$24*Assumptions!$C$40,$D$24*Assumptions!$C$10^LOG(MAX(1,SUM($D25:L25)),Assumptions!$C$41)) -> 10.773 | M24: =MAX($D$24*Assumptions!$C$40,$D$24*Assumptions!$C$10^LOG(MAX(1,SUM($D25:M25)),Assumptions!$C$41)) -> 10.773
B25: Units shipped (#) | C25: yellow = input | D25: 0 | E25: 0 | F25: 1 | G25: 2 | H25: 4 | I25: 6 | J25: 9 | K25: 11 | L25: 13 | M25: 15
B26: Revenue (units × ASP) | D26: =D23*D25 -> 0 | E26: =E23*E25 -> 0 | F26: =F23*F25 -> 45 | G26: =G23*G25 -> 84.245176 | H26: =H23*H25 -> 160.11879 | I26: =I23*I25 -> 231.39996 | J26: =J23*J25 -> 338.84731 | K26: =K23*K25 -> 414.14671 | ... M26: =M23*M25 -> 564.74552
B27: COGS - BoM (units × BoM) | D27: =D24*D25 -> 0 | E27: =E24*E25 -> 0 | F27: =F24*F25 -> 15.39 | G27: =G24*G25 -> 26.969549 | H27: =H24*H25 -> 48.71225 | I27: =I24*I25 -> 67.82486 | J27: =J24*J25 -> 96.957 | K27: =K24*K25 -> 118.503 | ... M27: =M24*M25 -> 161.595
B28: Contribution margin / unit | D28: =IF(D23=0,0,1-D24/D23) -> 0.658 | E28: =IF(E23=0,0,1-E24/E23) -> 0.658 | F28: =IF(F23=0,0,1-F24/F23) -> 0.658 | G28: =IF(G23=0,0,1-G24/G23) -> 0.67986833 | H28: =IF(H23=0,0,1-H24/H23) -> 0.6957743 | I28: =IF(I23=0,0,1-I24/I23) -> 0.70689338 | J28: =IF(J23=0,0,1-J24/J23) -> 0.71386227 | K28: =IF(K23=0,0,1-K24/K23) -> 0.71386227 | ... M28: =IF(M23=0,0,1-M24/M23) -> 0.71386227
B30: V5 totals
B31: Total revenue | D31: =D10+D18+D26 -> 0 | E31: =E10+E18+E26 -> 0 | F31: =F10+F18+F26 -> 60 | G31: =G10+G18+G26 -> 125.64518 | H31: =H10+H18+H26 -> 311.01641 | I31: =I10+I18+I26 -> 439.54874 | J31: =J10+J18+J26 -> 675.14552 | K31: =K10+K18+K26 -> 875.46311 | ... M31: =M10+M18+M26 -> 1171.1164
B32: Total COGS (BoM) | D32: =D11+D19+D27 -> 0 | E32: =E11+E19+E27 -> 0 | F32: =F11+F19+F27 -> 19.475 | G32: =G11+G19+G27 -> 37.342181 | H32: =H11+H19+H27 -> 90.566973 | I32: =I11+I19+I27 -> 120.92986 | J32: =J11+J19+J27 -> 183.00344 | K32: =K11+K19+K27 -> 235.61773 | ... M32: =M11+M19+M27 -> 312.57606
B33: Total units shipped | D33: =D9+D17+D25 -> 0 | E33: =E9+E17+E25 -> 0 | F33: =F9+F17+F25 -> 2 | G33: =G9+G17+G25 -> 5 | H33: =H9+H17+H25 -> 12 | I33: =I9+I17+I25 -> 19 | J33: =J9+J17+J25 -> 29 | K33: =K9+K17+K25 -> 38 | ... M33: =M9+M17+M25 -> 51
B34: Gross profit (Revenue − BoM COGS) | D34: =D31-D32 -> 0 | E34: =E31-E32 -> 0 | F34: =F31-F32 -> 40.525 | G34: =G31-G32 -> 88.302995 | H34: =H31-H32 -> 220.44944 | I34: =I31-I32 -> 318.61888 | J34: =J31-J32 -> 492.14208 | K34: =K31-K32 -> 639.84538 | ... M34: =M31-M32 -> 858.54034
B35: Gross margin % | D35: =IFERROR((D31-D32)/D31,0) -> 0 | E35: =IFERROR((E31-E32)/E31,0) -> 0 | F35: =IFERROR((F31-F32)/F31,0) -> 0.67541667 | G35: =IFERROR((G31-G32)/G31,0) -> 0.70279654 | H35: =IFERROR((H31-H32)/H31,0) -> 0.70880323 | I35: =IFERROR((I31-I32)/I31,0) -> 0.72487725 | J35: =IFERROR((J31-J32)/J31,0) -> 0.72894223 | K35: =IFERROR((K31-K32)/K31,0) -> 0.73086504 | ... M35: =IFERROR((M31-M32)/M31,0) -> 0.73309565
B36: Cumulative revenue | D36: =D31 -> 0 | E36: =D36+E31 -> 0 | F36: =E36+F31 -> 60 | G36: =F36+G31 -> 185.64518 | H36: =G36+H31 -> 496.66159 | I36: =H36+I31 -> 936.21033 | J36: =I36+J31 -> 1611.3559 | K36: =J36+K31 -> 2486.819 | L36: =K36+L31 -> 3484.3826 | M36: =L36+M31 -> 4655.499

Sheet V6_MilAI
B1: READ ONLY SUPPORTING DETAIL - Revenue is recognized via Backlog!Section L (rows 89-95). Editing units/ASP here does NOT change consolidated revenue, but DOES rescale COGS (BoM x delivered_rev / V-sheet rev). Do not edit unless you intend to re-baseline the BoM ratio.
B2: V6 - Military AI Systems | Domain: Cross-domain (AI/SW) | Launch: Y1
B3: Description | C3: Software-led product family - Edge AI box + Cloud SaaS analytics + sensor-fusion middleware. Software-defined release cadence: shipping early, iterating quarterly.
B5: Line | C5: Driver | D5: Y1 | E5: Y2 | F5: Y3 | G5: Y4 | H5: Y5 | I5: Y6 | J5: Y7 | K5: Y8 | L5: Y9 | M5: Y10
B6: AI-A - Edge AI mission box (per-platform)
B7: ASP / unit (₹ Cr) | C7: yellow = input | D7: 3.8 | E7: =$D$7*(E8/$D$8)^Assumptions!$C$39 -> 3.3802855 | F7: =$D$7*(F8/$D$8)^Assumptions!$C$39 -> 3.2046134 | G7: =$D$7*(G8/$D$8)^Assumptions!$C$39 -> 3.1793081 | H7: =$D$7*(H8/$D$8)^Assumptions!$C$39 -> 3.1793081 | I7: =$D$7*(I8/$D$8)^Assumptions!$C$39 -> 3.1793081 | J7: =$D$7*(J8/$D$8)^Assumptions!$C$39 -> 3.1793081 | K7: =$D$7*(K8/$D$8)^Assumptions!$C$39 -> 3.1793081 | L7: =$D$7*(L8/$D$8)^Assumptions!$C$39 -> 3.1793081 | M7: =$D$7*(M8/$D$8)^Assumptions!$C$39 -> 3.1793081
B8: BoM / unit (₹ Cr) | C8: yellow = input | D8: 0.6175 | E8: =MAX($D$8*Assumptions!$C$40,$D$8*Assumptions!$C$10^LOG(MAX(1,SUM($D9:E9)),Assumptions!$C$41)) -> 0.48862596 | F8: =MAX($D$8*Assumptions!$C$40,$D$8*Assumptions!$C$10^LOG(MAX(1,SUM($D9:F9)),Assumptions!$C$41)) -> 0.43915826 | G8: =MAX($D$8*Assumptions!$C$40,$D$8*Assumptions!$C$10^LOG(MAX(1,SUM($D9:G9)),Assumptions!$C$41)) -> 0.43225 | H8: =MAX($D$8*Assumptions!$C$40,$D$8*Assumptions!$C$10^LOG(MAX(1,SUM($D9:H9)),Assumptions!$C$41)) -> 0.43225 | I8: =MAX($D$8*Assumptions!$C$40,$D$8*Assumptions!$C$10^LOG(MAX(1,SUM($D9:I9)),Assumptions!$C$41)) -> 0.43225 | J8: =MAX($D$8*Assumptions!$C$40,$D$8*Assumptions!$C$10^LOG(MAX(1,SUM($D9:J9)),Assumptions!$C$41)) -> 0.43225 | K8: =MAX($D$8*Assumptions!$C$40,$D$8*Assumptions!$C$10^LOG(MAX(1,SUM($D9:K9)),Assumptions!$C$41)) -> 0.43225 | L8: =MAX($D$8*Assumptions!$C$40,$D$8*Assumptions!$C$10^LOG(MAX(1,SUM($D9:L9)),Assumptions!$C$41)) -> 0.43225 | M8: =MAX($D$8*Assumptions!$C$40,$D$8*Assumptions!$C$10^LOG(MAX(1,SUM($D9:M9)),Assumptions!$C$41)) -> 0.43225
B9: Units shipped (#) | C9: yellow = input | D9: 2 | E9: 5 | F9: 10 | G9: 18 | H9: 25 | I9: 32 | J9: 40 | K9: 45 | L9: 50 | M9: 55
B10: Revenue (units × ASP) | D10: =D7*D9 -> 7.6 | E10: =E7*E9 -> 16.901428 | F10: =F7*F9 -> 32.046134 | G10: =G7*G9 -> 57.227546 | H10: =H7*H9 -> 79.482703 | I10: =I7*I9 -> 101.73786 | J10: =J7*J9 -> 127.17232 | K10: =K7*K9 -> 143.06886 | ... M10: =M7*M9 -> 174.86195
B11: COGS - BoM (units × BoM) | D11: =D8*D9 -> 1.235 | E11: =E8*E9 -> 2.4431298 | F11: =F8*F9 -> 4.3915826 | G11: =G8*G9 -> 7.7805 | H11: =H8*H9 -> 10.80625 | I11: =I8*I9 -> 13.832 | J11: =J8*J9 -> 17.29 | K11: =K8*K9 -> 19.45125 | ... M11: =M8*M9 -> 23.77375
B12: Contribution margin / unit | D12: =IF(D7=0,0,1-D8/D7) -> 0.8375 | E12: =IF(E7=0,0,1-E8/E7) -> 0.85544832 | F12: =IF(F7=0,0,1-F8/F7) -> 0.86296061 | G12: =IF(G7=0,0,1-G8/G7) -> 0.86404275 | H12: =IF(H7=0,0,1-H8/H7) -> 0.86404275 | I12: =IF(I7=0,0,1-I8/I7) -> 0.86404275 | J12: =IF(J7=0,0,1-J8/J7) -> 0.86404275 | K12: =IF(K7=0,0,1-K8/K7) -> 0.86404275 | ... M12: =IF(M7=0,0,1-M8/M7) -> 0.86404275
B14: AI-B - OIDSS (per yr/license)
B15: ASP / unit (₹ Cr) | C15: yellow = input | D15: 11.4 | E15: =$D$15*(E16/$D$16)^Assumptions!$C$39 -> 10.671056 | F15: =$D$15*(F16/$D$16)^Assumptions!$C$39 -> 10.140857 | G15: =$D$15*(G16/$D$16)^Assumptions!$C$39 -> 9.6864882 | H15: =$D$15*(H16/$D$16)^Assumptions!$C$39 -> 9.5379243 | I15: =$D$15*(I16/$D$16)^Assumptions!$C$39 -> 9.5379243 | J15: =$D$15*(J16/$D$16)^Assumptions!$C$39 -> 9.5379243 | K15: =$D$15*(K16/$D$16)^Assumptions!$C$39 -> 9.5379243 | L15: =$D$15*(L16/$D$16)^Assumptions!$C$39 -> 9.5379243 | M15: =$D$15*(M16/$D$16)^Assumptions!$C$39 -> 9.5379243
B16: BoM / unit (₹ Cr) | C16: yellow = input | D16: 0.475 | E16: =MAX($D$16*Assumptions!$C$40,$D$16*Assumptions!$C$10^LOG(MAX(1,SUM($D17:E17)),Assumptions!$C$41)) -> 0.41619674 | F16: =MAX($D$16*Assumptions!$C$40,$D$16*Assumptions!$C$10^LOG(MAX(1,SUM($D17:F17)),Assumptions!$C$41)) -> 0.37586613 | G16: =MAX($D$16*Assumptions!$C$40,$D$16*Assumptions!$C$10^LOG(MAX(1,SUM($D17:G17)),Assumptions!$C$41)) -> 0.34293879 | H16: =MAX($D$16*Assumptions!$C$40,$D$16*Assumptions!$C$10^LOG(MAX(1,SUM($D17:H17)),Assumptions!$C$41)) -> 0.3325 | I16: =MAX($D$16*Assumptions!$C$40,$D$16*Assumptions!$C$10^LOG(MAX(1,SUM($D17:I17)),Assumptions!$C$41)) -> 0.3325 | J16: =MAX($D$16*Assumptions!$C$40,$D$16*Assumptions!$C$10^LOG(MAX(1,SUM($D17:J17)),Assumptions!$C$41)) -> 0.3325 | K16: =MAX($D$16*Assumptions!$C$40,$D$16*Assumptions!$C$10^LOG(MAX(1,SUM($D17:K17)),Assumptions!$C$41)) -> 0.3325 | L16: =MAX($D$16*Assumptions!$C$40,$D$16*Assumptions!$C$10^LOG(MAX(1,SUM($D17:L17)),Assumptions!$C$41)) -> 0.3325 | M16: =MAX($D$16*Assumptions!$C$40,$D$16*Assumptions!$C$10^LOG(MAX(1,SUM($D17:M17)),Assumptions!$C$41)) -> 0.3325
B17: Units shipped (#) | C17: yellow = input | D17: 1 | E17: 2 | F17: 4 | G17: 8 | H17: 12 | I17: 18 | J17: 24 | K17: 28 | L17: 32 | M17: 35
B18: Revenue (units × ASP) | D18: =D15*D17 -> 11.4 | E18: =E15*E17 -> 21.342111 | F18: =F15*F17 -> 40.563426 | G18: =G15*G17 -> 77.491905 | H18: =H15*H17 -> 114.45509 | I18: =I15*I17 -> 171.68264 | J18: =J15*J17 -> 228.91018 | K18: =K15*K17 -> 267.06188 | ... M18: =M15*M17 -> 333.82735
B19: COGS - BoM (units × BoM) | D19: =D16*D17 -> 0.475 | E19: =E16*E17 -> 0.83239348 | F19: =F16*F17 -> 1.5034645 | G19: =G16*G17 -> 2.7435103 | H19: =H16*H17 -> 3.99 | I19: =I16*I17 -> 5.985 | J19: =J16*J17 -> 7.98 | K19: =K16*K17 -> 9.31 | ... M19: =M16*M17 -> 11.6375
B20: Contribution margin / unit | D20: =IF(D15=0,0,1-D16/D15) -> 0.95833333 | E20: =IF(E15=0,0,1-E16/E15) -> 0.9609976 | F20: =IF(F15=0,0,1-F16/F15) -> 0.96293547 | G20: =IF(G15=0,0,1-G16/G15) -> 0.96459617 | H20: =IF(H15=0,0,1-H16/H15) -> 0.96513917 | I20: =IF(I15=0,0,1-I16/I15) -> 0.96513917 | J20: =IF(J15=0,0,1-J16/J15) -> 0.96513917 | K20: =IF(K15=0,0,1-K16/K15) -> 0.96513917 | ... M20: =IF(M15=0,0,1-M16/M15) -> 0.96513917
B22: AI-C - Sensor-fusion middleware license
B23: ASP / unit (₹ Cr) | C23: yellow = input | D23: 5.7 | E23: =$D$23*(E24/$D$24)^Assumptions!$C$39 -> 5.1176585 | F23: =$D$23*(F24/$D$24)^Assumptions!$C$39 -> 4.863384 | G23: =$D$23*(G24/$D$24)^Assumptions!$C$39 -> 4.7689622 | H23: =$D$23*(H24/$D$24)^Assumptions!$C$39 -> 4.7689622 | I23: =$D$23*(I24/$D$24)^Assumptions!$C$39 -> 4.7689622 | J23: =$D$23*(J24/$D$24)^Assumptions!$C$39 -> 4.7689622 | K23: =$D$23*(K24/$D$24)^Assumptions!$C$39 -> 4.7689622 | L23: =$D$23*(L24/$D$24)^Assumptions!$C$39 -> 4.7689622 | M23: =$D$23*(M24/$D$24)^Assumptions!$C$39 -> 4.7689622
B24: BoM / unit (₹ Cr) | C24: yellow = input | D24: 0.19 | E24: =MAX($D$24*Assumptions!$C$40,$D$24*Assumptions!$C$10^LOG(MAX(1,SUM($D25:E25)),Assumptions!$C$41)) -> 0.1531604 | F24: =MAX($D$24*Assumptions!$C$40,$D$24*Assumptions!$C$10^LOG(MAX(1,SUM($D25:F25)),Assumptions!$C$41)) -> 0.13831873 | G24: =MAX($D$24*Assumptions!$C$40,$D$24*Assumptions!$C$10^LOG(MAX(1,SUM($D25:G25)),Assumptions!$C$41)) -> 0.133 | H24: =MAX($D$24*Assumptions!$C$40,$D$24*Assumptions!$C$10^LOG(MAX(1,SUM($D25:H25)),Assumptions!$C$41)) -> 0.133 | I24: =MAX($D$24*Assumptions!$C$40,$D$24*Assumptions!$C$10^LOG(MAX(1,SUM($D25:I25)),Assumptions!$C$41)) -> 0.133 | J24: =MAX($D$24*Assumptions!$C$40,$D$24*Assumptions!$C$10^LOG(MAX(1,SUM($D25:J25)),Assumptions!$C$41)) -> 0.133 | K24: =MAX($D$24*Assumptions!$C$40,$D$24*Assumptions!$C$10^LOG(MAX(1,SUM($D25:K25)),Assumptions!$C$41)) -> 0.133 | L24: =MAX($D$24*Assumptions!$C$40,$D$24*Assumptions!$C$10^LOG(MAX(1,SUM($D25:L25)),Assumptions!$C$41)) -> 0.133 | M24: =MAX($D$24*Assumptions!$C$40,$D$24*Assumptions!$C$10^LOG(MAX(1,SUM($D25:M25)),Assumptions!$C$41)) -> 0.133
B25: Units shipped (#) | C25: yellow = input | D25: 2 | E25: 4 | F25: 8 | G25: 15 | H25: 22 | I25: 30 | J25: 38 | K25: 42 | L25: 48 | M25: 52
B26: Revenue (units × ASP) | D26: =D23*D25 -> 11.4 | E26: =E23*E25 -> 20.470634 | F26: =F23*F25 -> 38.907072 | G26: =G23*G25 -> 71.534432 | H26: =H23*H25 -> 104.91717 | I26: =I23*I25 -> 143.06886 | J26: =J23*J25 -> 181.22056 | K26: =K23*K25 -> 200.29641 | ... M26: =M23*M25 -> 247.98603
B27: COGS - BoM (units × BoM) | D27: =D24*D25 -> 0.38 | E27: =E24*E25 -> 0.6126416 | F27: =F24*F25 -> 1.1065499 | G27: =G24*G25 -> 1.995 | H27: =H24*H25 -> 2.926 | I27: =I24*I25 -> 3.99 | J27: =J24*J25 -> 5.054 | K27: =K24*K25 -> 5.586 | ... M27: =M24*M25 -> 6.916
B28: Contribution margin / unit | D28: =IF(D23=0,0,1-D24/D23) -> 0.96666667 | E28: =IF(E23=0,0,1-E24/E23) -> 0.97007217 | F28: =IF(F23=0,0,1-F24/F23) -> 0.97155916 | G28: =IF(G23=0,0,1-G24/G23) -> 0.97211133 | H28: =IF(H23=0,0,1-H24/H23) -> 0.97211133 | I28: =IF(I23=0,0,1-I24/I23) -> 0.97211133 | J28: =IF(J23=0,0,1-J24/J23) -> 0.97211133 | K28: =IF(K23=0,0,1-K24/K23) -> 0.97211133 | ... M28: =IF(M23=0,0,1-M24/M23) -> 0.97211133
B30: V6 totals
B31: Total revenue | D31: =D10+D18+D26 -> 30.4 | E31: =E10+E18+E26 -> 58.714173 | F31: =F10+F18+F26 -> 111.51663 | G31: =G10+G18+G26 -> 206.25388 | H31: =H10+H18+H26 -> 298.85496 | I31: =I10+I18+I26 -> 416.48936 | J31: =J10+J18+J26 -> 537.30307 | K31: =K10+K18+K26 -> 610.42716 | ... M31: =M10+M18+M26 -> 756.67533
B32: Total COGS (BoM) | D32: =D11+D19+D27 -> 2.09 | E32: =E11+E19+E27 -> 3.8881649 | F32: =F11+F19+F27 -> 7.0015969 | G32: =G11+G19+G27 -> 12.51901 | H32: =H11+H19+H27 -> 17.72225 | I32: =I11+I19+I27 -> 23.807 | J32: =J11+J19+J27 -> 30.324 | K32: =K11+K19+K27 -> 34.34725 | ... M32: =M11+M19+M27 -> 42.32725
B33: Total units shipped | D33: =D9+D17+D25 -> 5 | E33: =E9+E17+E25 -> 11 | F33: =F9+F17+F25 -> 22 | G33: =G9+G17+G25 -> 41 | H33: =H9+H17+H25 -> 59 | I33: =I9+I17+I25 -> 80 | J33: =J9+J17+J25 -> 102 | K33: =K9+K17+K25 -> 115 | ... M33: =M9+M17+M25 -> 142
B34: Gross profit (Revenue − BoM COGS) | D34: =D31-D32 -> 28.31 | E34: =E31-E32 -> 54.826008 | F34: =F31-F32 -> 104.51503 | G34: =G31-G32 -> 193.73487 | H34: =H31-H32 -> 281.13271 | I34: =I31-I32 -> 392.68236 | J34: =J31-J32 -> 506.97907 | K34: =K31-K32 -> 576.07991 | ... M34: =M31-M32 -> 714.34808
B35: Gross margin % | D35: =IFERROR((D31-D32)/D31,0) -> 0.93125 | E35: =IFERROR((E31-E32)/E31,0) -> 0.93377809 | F35: =IFERROR((F31-F32)/F31,0) -> 0.93721477 | G35: =IFERROR((G31-G32)/G31,0) -> 0.93930291 | H35: =IFERROR((H31-H32)/H31,0) -> 0.9406995 | I35: =IFERROR((I31-I32)/I31,0) -> 0.94283888 | J35: =IFERROR((J31-J32)/J31,0) -> 0.94356258 | K35: =IFERROR((K31-K32)/K31,0) -> 0.94373243 | ... M35: =IFERROR((M31-M32)/M31,0) -> 0.94406154
B36: Cumulative revenue | D36: =D31 -> 30.4 | E36: =D36+E31 -> 89.114173 | F36: =E36+F31 -> 200.6308 | G36: =F36+G31 -> 406.88469 | H36: =G36+H31 -> 705.73965 | I36: =H36+I31 -> 1122.229 | J36: =I36+J31 -> 1659.5321 | K36: =J36+K31 -> 2269.9592 | L36: =K36+L31 -> 2963.0484 | M36: =L36+M31 -> 3719.7237

Sheet Revenue
B1: READ ONLY SUPPORTING DETAIL upstream - Revenue (rows 6-12) is sourced from Backlog!D89:M95 (Section L deliveries). V1-V6 sheets retained as unit/ASP analytics only; their edits do not flow into consolidated revenue.
B2: Consolidated Revenue & COGS by Vertical - Revenue now DERIVED from Backlog deliveries (% of opening backlog by vertical).
B3: V1-V6 unit-shipment plans retained as supporting detail; COGS scaled proportionally to preserve gross margin %.
B4: Vertical | C4: Stream | D4: Y1 | E4: Y2 | F4: Y3 | G4: Y4 | H4: Y5 | I4: Y6 | J4: Y7 | K4: Y8 | L4: Y9 | M4: Y10 | N4: Original V-sheet revenue (memo)
B5: A. Revenue by vertical (₹ Cr)
B6: V1 - AESA Radar | C6: Revenue | D6: =Backlog!D89 -> 0 | E6: =Backlog!E89 -> 50 | F6: =Backlog!F89 -> 125 | G6: =Backlog!G89 -> 206.05015 | H6: =Backlog!H89 -> 328.29602 | I6: =Backlog!I89 -> 452.63901 | J6: =Backlog!J89 -> 565.62771 | K6: =Backlog!K89 -> 677.77455 | ... M6: =Backlog!M89 -> 865.11599
B7: V2 - Electronic Warfare & SIGINT | C7: Revenue | D7: =Backlog!D90 -> 52.5 | E7: =Backlog!E90 -> 144.2875 | F7: =Backlog!F90 -> 265.399 | G7: =Backlog!G90 -> 337.14245 | H7: =Backlog!H90 -> 430.99717 | I7: =Backlog!I90 -> 538.13129 | J7: =Backlog!J90 -> 596.90129 | K7: =Backlog!K90 -> 681.07375 | ... M7: =Backlog!M90 -> 760.43114
B8: V3 - Counter-UAS (Anti-Drone) | C8: Revenue | D8: =Backlog!D91 -> 0 | E8: =Backlog!E91 -> 0 | F8: =Backlog!F91 -> 24.219657 | G8: =Backlog!G91 -> 106.54834 | H8: =Backlog!H91 -> 231.59856 | I8: =Backlog!I91 -> 380.9536 | J8: =Backlog!J91 -> 545.24509 | K8: =Backlog!K91 -> 707.92922 | ... M8: =Backlog!M91 -> 1036.5245
B9: V4 - MALE-class ISR UAS | C9: Revenue | D9: =Backlog!D92 -> 0 | E9: =Backlog!E92 -> 0 | F9: =Backlog!F92 -> 33 | G9: =Backlog!G92 -> 104.61 | H9: =Backlog!H92 -> 261.9507 | I9: =Backlog!I92 -> 496.71541 | J9: =Backlog!J92 -> 725.93928 | K9: =Backlog!K92 -> 963.54328 | ... M9: =Backlog!M92 -> 1386.2537
B10: V5 - Autonomous Systems (AUV/USV) | C10: Revenue | D10: =Backlog!D93 -> 0 | E10: =Backlog!E93 -> 0 | F10: =Backlog!F93 -> 18.9525 | G10: =Backlog!G93 -> 50.450875 | H10: =Backlog!H93 -> 100.33816 | I10: =Backlog!I93 -> 158.71214 | J10: =Backlog!J93 -> 225.99743 | K10: =Backlog!K93 -> 326.59582 | ... M10: =Backlog!M93 -> 549.15185
B11: V6 - Military AI Systems | C11: Revenue | D11: =Backlog!D94 -> 0 | E11: =Backlog!E94 -> 9.12 | F11: =Backlog!F94 -> 24.45425 | G11: =Backlog!G94 -> 50.401712 | H11: =Backlog!H94 -> 94.521109 | I11: =Backlog!I94 -> 153.07596 | J11: =Backlog!J94 -> 224.13542 | K11: =Backlog!K94 -> 302.42734 | ... M11: =Backlog!M94 -> 457.84278
B12: TOTAL REVENUE | D12: =SUM(D6:D11) -> 52.5 | E12: =SUM(E6:E11) -> 203.4075 | F12: =SUM(F6:F11) -> 491.02541 | G12: =SUM(G6:G11) -> 855.20352 | H12: =SUM(H6:H11) -> 1447.7017 | I12: =SUM(I6:I11) -> 2180.2274 | J12: =SUM(J6:J11) -> 2883.8462 | K12: =SUM(K6:K11) -> 3659.344 | ... M12: =SUM(M6:M11) -> 5055.32
B14: B. Revenue mix (% of total)
B15: V1 mix | D15: =IFERROR(D6/D12,0) -> 0 | E15: =IFERROR(E6/E12,0) -> 0.24581198 | F15: =IFERROR(F6/F12,0) -> 0.25456931 | G15: =IFERROR(G6/G12,0) -> 0.24093698 | H15: =IFERROR(H6/H12,0) -> 0.22677049 | I15: =IFERROR(I6/I12,0) -> 0.20761092 | J15: =IFERROR(J6/J12,0) -> 0.19613657 | K15: =IFERROR(K6/K12,0) -> 0.1852175 | ... M15: =IFERROR(M6/M12,0) -> 0.17112982
B16: V2 mix | D16: =IFERROR(D7/D12,0) -> 1 | E16: =IFERROR(E7/E12,0) -> 0.70935192 | F16: =IFERROR(F7/F12,0) -> 0.54049953 | G16: =IFERROR(G7/G12,0) -> 0.39422481 | H16: =IFERROR(H7/H12,0) -> 0.29771131 | I16: =IFERROR(I7/I12,0) -> 0.24682347 | J16: =IFERROR(J7/J12,0) -> 0.20698097 | K16: =IFERROR(K7/K12,0) -> 0.18611908 | ... M16: =IFERROR(M7/M12,0) -> 0.15042196
B17: V3 mix | D17: =IFERROR(D8/D12,0) -> 0 | E17: =IFERROR(E8/E12,0) -> 0 | F17: =IFERROR(F8/F12,0) -> 0.049324651 | G17: =IFERROR(G8/G12,0) -> 0.12458828 | H17: =IFERROR(H8/H12,0) -> 0.15997671 | I17: =IFERROR(I8/I12,0) -> 0.17473113 | J17: =IFERROR(J8/J12,0) -> 0.18906871 | K17: =IFERROR(K8/K12,0) -> 0.19345796 | ... M17: =IFERROR(M8/M12,0) -> 0.20503638
B18: V4 mix | D18: =IFERROR(D9/D12,0) -> 0 | E18: =IFERROR(E9/E12,0) -> 0 | F18: =IFERROR(F9/F12,0) -> 0.067206298 | G18: =IFERROR(G9/G12,0) -> 0.12232176 | H18: =IFERROR(H9/H12,0) -> 0.18094245 | I18: =IFERROR(I9/I12,0) -> 0.22782734 | J18: =IFERROR(J9/J12,0) -> 0.25172607 | K18: =IFERROR(K9/K12,0) -> 0.26331039 | ... M18: =IFERROR(M9/M12,0) -> 0.27421681
B19: V5 mix | D19: =IFERROR(D10/D12,0) -> 0 | E19: =IFERROR(E10/E12,0) -> 0 | F19: =IFERROR(F10/F12,0) -> 0.038597799 | G19: =IFERROR(G10/G12,0) -> 0.058992829 | H19: =IFERROR(H10/H12,0) -> 0.069308584 | I19: =IFERROR(I10/I12,0) -> 0.072796141 | J19: =IFERROR(J10/J12,0) -> 0.078366672 | K19: =IFERROR(K10/K12,0) -> 0.089249829 | ... M19: =IFERROR(M10/M12,0) -> 0.10862851
B20: V6 mix | D20: =IFERROR(D11/D12,0) -> 0 | E20: =IFERROR(E11/E12,0) -> 0.044836105 | F20: =IFERROR(F11/F12,0) -> 0.049802413 | G20: =IFERROR(G11/G12,0) -> 0.058935342 | H20: =IFERROR(H11/H12,0) -> 0.065290459 | I20: =IFERROR(I11/I12,0) -> 0.070211005 | J20: =IFERROR(J11/J12,0) -> 0.077721002 | K20: =IFERROR(K11/K12,0) -> 0.082645234 | ... M20: =IFERROR(M11/M12,0) -> 0.090566528
B22: C. COGS - BoM by vertical (₹ Cr)
B23: V1 - AESA Radar | C23: COGS BoM | D23: =IFERROR(V1_AESA!D32*(D6/V1_AESA!D31),0) -> 0 | E23: =IFERROR(V1_AESA!E32*(E6/V1_AESA!E31),0) -> 18.915007 | F23: =IFERROR(V1_AESA!F32*(F6/V1_AESA!F31),0) -> 45.209771 | G23: =IFERROR(V1_AESA!G32*(G6/V1_AESA!G31),0) -> 73.417961 | H23: =IFERROR(V1_AESA!H32*(H6/V1_AESA!H31),0) -> 116.01881 | I23: =IFERROR(V1_AESA!I32*(I6/V1_AESA!I31),0) -> 159.03762 | J23: =IFERROR(V1_AESA!J32*(J6/V1_AESA!J31),0) -> 197.9641 | K23: =IFERROR(V1_AESA!K32*(K6/V1_AESA!K31),0) -> 236.59516 | ... M23: =IFERROR(V1_AESA!M32*(M6/V1_AESA!M31),0) -> 302.44593
B24: V2 - Electronic Warfare & SIGINT | C24: COGS BoM | D24: =IFERROR(V2_EW_SIGINT!D40*(D7/V2_EW_SIGINT!D39),0) -> 23.458383 | E24: =IFERROR(V2_EW_SIGINT!E40*(E7/V2_EW_SIGINT!E39),0) -> 61.249682 | F24: =IFERROR(V2_EW_SIGINT!F40*(F7/V2_EW_SIGINT!F39),0) -> 107.14122 | G24: =IFERROR(V2_EW_SIGINT!G40*(G7/V2_EW_SIGINT!G39),0) -> 134.2399 | H24: =IFERROR(V2_EW_SIGINT!H40*(H7/V2_EW_SIGINT!H39),0) -> 168.58482 | I24: =IFERROR(V2_EW_SIGINT!I40*(I7/V2_EW_SIGINT!I39),0) -> 208.1537 | J24: =IFERROR(V2_EW_SIGINT!J40*(J7/V2_EW_SIGINT!J39),0) -> 226.77 | K24: =IFERROR(V2_EW_SIGINT!K40*(K7/V2_EW_SIGINT!K39),0) -> 268.04235 | ... M24: =IFERROR(V2_EW_SIGINT!M40*(M7/V2_EW_SIGINT!M39),0) -> 294.94718
B25: V3 - Counter-UAS (Anti-Drone) | C25: COGS BoM | D25: =IFERROR(V3_CUAS!D32*(D8/V3_CUAS!D31),0) -> 0 | E25: =IFERROR(V3_CUAS!E32*(E8/V3_CUAS!E31),0) -> 0 | F25: =IFERROR(V3_CUAS!F32*(F8/V3_CUAS!F31),0) -> 11.354906 | G25: =IFERROR(V3_CUAS!G32*(G8/V3_CUAS!G31),0) -> 48.274412 | H25: =IFERROR(V3_CUAS!H32*(H8/V3_CUAS!H31),0) -> 104.35138 | I25: =IFERROR(V3_CUAS!I32*(I8/V3_CUAS!I31),0) -> 170.96979 | J25: =IFERROR(V3_CUAS!J32*(J8/V3_CUAS!J31),0) -> 243.59919 | K25: =IFERROR(V3_CUAS!K32*(K8/V3_CUAS!K31),0) -> 315.41675 | ... M25: =IFERROR(V3_CUAS!M32*(M8/V3_CUAS!M31),0) -> 463.14628
B26: V4 - MALE-class ISR UAS | C26: COGS BoM | D26: =IFERROR(V4_UAS_MALE!D32*(D9/V4_UAS_MALE!D31),0) -> 0 | E26: =IFERROR(V4_UAS_MALE!E32*(E9/V4_UAS_MALE!E31),0) -> 0 | F26: =IFERROR(V4_UAS_MALE!F32*(F9/V4_UAS_MALE!F31),0) -> 0 | G26: =IFERROR(V4_UAS_MALE!G32*(G9/V4_UAS_MALE!G31),0) -> 34.640854 | H26: =IFERROR(V4_UAS_MALE!H32*(H9/V4_UAS_MALE!H31),0) -> 86.100613 | I26: =IFERROR(V4_UAS_MALE!I32*(I9/V4_UAS_MALE!I31),0) -> 154.33443 | J26: =IFERROR(V4_UAS_MALE!J32*(J9/V4_UAS_MALE!J31),0) -> 221.42763 | K26: =IFERROR(V4_UAS_MALE!K32*(K9/V4_UAS_MALE!K31),0) -> 284.64954 | ... M26: =IFERROR(V4_UAS_MALE!M32*(M9/V4_UAS_MALE!M31),0) -> 398.70831
B27: V5 - Autonomous Systems (AUV/USV) | C27: COGS BoM | D27: =IFERROR(V5_Autonomous!D32*(D10/V5_Autonomous!D31),0) -> 0 | E27: =IFERROR(V5_Autonomous!E32*(E10/V5_Autonomous!E31),0) -> 0 | F27: =IFERROR(V5_Autonomous!F32*(F10/V5_Autonomous!F31),0) -> 6.1516656 | G27: =IFERROR(V5_Autonomous!G32*(G10/V5_Autonomous!G31),0) -> 14.994174 | H27: =IFERROR(V5_Autonomous!H32*(H10/V5_Autonomous!H31),0) -> 29.218147 | I27: =IFERROR(V5_Autonomous!I32*(I10/V5_Autonomous!I31),0) -> 43.665321 | J27: =IFERROR(V5_Autonomous!J32*(J10/V5_Autonomous!J31),0) -> 61.25836 | K27: =IFERROR(V5_Autonomous!K32*(K10/V5_Autonomous!K31),0) -> 87.898354 | ... M27: =IFERROR(V5_Autonomous!M32*(M10/V5_Autonomous!M31),0) -> 146.57102
B28: V6 - Military AI Systems | C28: COGS BoM | D28: =IFERROR(V6_MilAI!D32*(D11/V6_MilAI!D31),0) -> 0 | E28: =IFERROR(V6_MilAI!E32*(E11/V6_MilAI!E31),0) -> 0.60394386 | F28: =IFERROR(V6_MilAI!F32*(F11/V6_MilAI!F31),0) -> 1.5353656 | G28: =IFERROR(V6_MilAI!G32*(G11/V6_MilAI!G31),0) -> 3.0592372 | H28: =IFERROR(V6_MilAI!H32*(H11/V6_MilAI!H31),0) -> 5.6051495 | I28: =IFERROR(V6_MilAI!I32*(I11/V6_MilAI!I31),0) -> 8.7499938 | J28: =IFERROR(V6_MilAI!J32*(J11/V6_MilAI!J31),0) -> 12.649625 | K28: =IFERROR(V6_MilAI!K32*(K11/V6_MilAI!K31),0) -> 17.01685 | ... M28: =IFERROR(V6_MilAI!M32*(M11/V6_MilAI!M31),0) -> 25.611018
B29: TOTAL COGS - BoM | D29: =SUM(D23:D28) -> 23.458383 | E29: =SUM(E23:E28) -> 80.768633 | F29: =SUM(F23:F28) -> 171.39293 | G29: =SUM(G23:G28) -> 308.62654 | H29: =SUM(H23:H28) -> 509.87891 | I29: =SUM(I23:I28) -> 744.91085 | J29: =SUM(J23:J28) -> 963.66891 | K29: =SUM(K23:K28) -> 1209.619 | ... M29: =SUM(M23:M28) -> 1631.4297
B31: D. Gross profit (Revenue − BoM COGS, before COGS personnel)
B32: Gross profit (BoM only) | D32: =D12-D29 -> 29.041617 | E32: =E12-E29 -> 122.63887 | F32: =F12-F29 -> 319.63247 | G32: =G12-G29 -> 546.57699 | H32: =H12-H29 -> 937.82281 | I32: =I12-I29 -> 1435.3166 | J32: =J12-J29 -> 1920.1773 | K32: =K12-K29 -> 2449.725 | ... M32: =M12-M29 -> 3423.8902
B33: Gross margin % | D33: =IFERROR((D12-D29)/D12,0) -> 0.55317365 | E33: =IFERROR((E12-E29)/E12,0) -> 0.60292205 | F33: =IFERROR((F12-F29)/F12,0) -> 0.65094895 | G33: =IFERROR((G12-G29)/G12,0) -> 0.63911919 | H33: =IFERROR((H12-H29)/H12,0) -> 0.64780113 | I33: =IFERROR((I12-I29)/I12,0) -> 0.65833342 | J33: =IFERROR((J12-J29)/J12,0) -> 0.66583901 | K33: =IFERROR((K12-K29)/K12,0) -> 0.66944375 | ... M33: =IFERROR((M12-M29)/M12,0) -> 0.67728458
B34: Note: Revenue = Backlog!Deliveries (rows 89-94). Edit per-vertical delivery rates in Backlog!D82:M87.
B35: COGS scaled: V-sheet BoM × (delivered revenue / V-sheet revenue) so gross margin % follows the underlying unit economics.

Sheet Backlog
B2: Backlog, Pipeline & Book-to-Bill - Defense Contract Mechanics
B3: Bookings = Backlog-driven contract awards. Backlog rolls forward (prior + bookings − recognized). Pipeline = Bookings / Pwin. Defense bookings typically lead revenue by 12-18 months for HW, 6-12 months for SW.
B4: Track | C4: Default | D4: Y1 | E4: Y2 | F4: Y3 | G4: Y4 | H4: Y5 | I4: Y6 | J4: Y7 | K4: Y8 | L4: Y9 | M4: Y10
B5: A. Target book-to-bill ratios (scenario checks)
B6: V1 - AESA Radar B:B | C6: =AVERAGE(D6:M6) -> 1.205 | D6: 1.5 | E6: 1.5 | F6: 1.4 | G6: 1.3 | H6: 1.2 | I6: 1.1 | J6: 1.05 | K6: 1 | L6: 1 | M6: 1
B7: V2 - Electronic Warfare & SIGINT B:B | C7: =AVERAGE(D7:M7) -> 1.03 | D7: 1.1 | E7: 1.1 | F7: 1.05 | G7: 1.05 | H7: 1 | I7: 1 | J7: 1 | K7: 1 | L7: 1 | M7: 1
B8: V3 - Counter-UAS (Anti-Drone) B:B | C8: =AVERAGE(D8:M8) -> 1.155 | D8: 1.5 | E8: 1.4 | F8: 1.3 | G8: 1.2 | H8: 1.1 | I8: 1.05 | J8: 1 | K8: 1 | L8: 1 | M8: 1
B9: V4 - MALE-class ISR UAS B:B | C9: =AVERAGE(D9:M9) -> 1.645 | D9: 3 | E9: 2.5 | F9: 2 | G9: 1.8 | H9: 1.5 | I9: 1.3 | J9: 1.2 | K9: 1.1 | L9: 1.05 | M9: 1
B10: V5 - Autonomous Systems (AUV/USV) B:B | C10: =AVERAGE(D10:M10) -> 1.245 | D10: 1.8 | E10: 1.6 | F10: 1.4 | G10: 1.3 | H10: 1.2 | I10: 1.1 | J10: 1.05 | K10: 1 | L10: 1 | M10: 1
B11: V6 - Military AI Systems B:B | C11: =AVERAGE(D11:M11) -> 1.08 | D11: 1.2 | E11: 1.2 | F11: 1.15 | G11: 1.1 | H11: 1.1 | I11: 1.05 | J11: 1 | K11: 1 | L11: 1 | M11: 1
B12: B. Probability of win (Pwin) on qualified pipeline (yellow inputs)
B13: V1 Pwin | C13: =AVERAGE(D13:M13) -> 0.325 | D13: 0.25 | E13: 0.28 | F13: 0.3 | G13: 0.32 | H13: 0.35 | I13: 0.35 | J13: 0.35 | K13: 0.35 | L13: 0.35 | M13: 0.35
B14: V2 Pwin | C14: =AVERAGE(D14:M14) -> 0.4 | D14: 0.4 | E14: 0.4 | F14: 0.4 | G14: 0.4 | H14: 0.4 | I14: 0.4 | J14: 0.4 | K14: 0.4 | L14: 0.4 | M14: 0.4
B15: V3 Pwin | C15: =AVERAGE(D15:M15) -> 0.325 | D15: 0.25 | E15: 0.28 | F15: 0.3 | G15: 0.32 | H15: 0.35 | I15: 0.35 | J15: 0.35 | K15: 0.35 | L15: 0.35 | M15: 0.35
B16: V4 Pwin | C16: =AVERAGE(D16:M16) -> 0.297 | D16: 0.2 | E16: 0.22 | F16: 0.25 | G16: 0.28 | H16: 0.3 | I16: 0.32 | J16: 0.35 | K16: 0.35 | L16: 0.35 | M16: 0.35
B17: V5 Pwin | C17: =AVERAGE(D17:M17) -> 0.312 | D17: 0.22 | E17: 0.25 | F17: 0.28 | G17: 0.3 | H17: 0.32 | I17: 0.35 | J17: 0.35 | K17: 0.35 | L17: 0.35 | M17: 0.35
B18: V6 Pwin | C18: =AVERAGE(D18:M18) -> 0.342 | D18: 0.3 | E18: 0.32 | F18: 0.35 | G18: 0.35 | H18: 0.35 | I18: 0.35 | J18: 0.35 | K18: 0.35 | L18: 0.35 | M18: 0.35
B19: C. Bookings (new contract awards) - input driver
B20: V1 bookings | D20: 100 | E20: 200 | F20: 287.1003 | G20: 450.5419 | H20: 576.982 | I20: 678.6164 | J20: 789.9214 | K20: 870.3356 | L20: 956.1769 | M20: 1011.8148
B21: V2 bookings | D21: 341.075 | E21: 386.5105 | F21: 408.8859 | G21: 524.8519 | H21: 645.2654 | I21: 655.6713 | J21: 765.2462 | K21: 781.5756 | L21: 789.5376 | M21: 829.5914
B22: V3 bookings | D22: 0 | E22: 73.3929 | F22: 273.7005 | G22: 485.4884 | H22: 684.1896 | I22: 878.8066 | J22: 1038.2273 | K22: 1239.9302 | L22: 1347.2318 | M22: 1494.2748
B23: V4 bookings | D23: 0 | E23: 100 | F23: 250 | G23: 581.4 | H23: 973.3589 | I23: 1191.3332 | J23: 1445.9514 | K23: 1600.6812 | L23: 1817.6016 | M23: 1985.6246
B24: V5 bookings | D24: 0 | E24: 75.81 | F24: 144.946 | G24: 250 | H24: 333.8341 | I24: 427.8533 | J24: 628.391 | K24: 774.4624 | L24: 880.92 | M24: 1036.2572
B25: V6 bookings | D25: 36.48 | E25: 70.457 | F25: 128.2441 | G25: 226.8793 | H25: 328.7405 | I25: 437.3138 | J25: 537.3031 | K25: 610.4272 | L25: 693.0892 | M25: 756.6753
B26: Σ Bookings (consolidated) | D26: =SUM(D20:D25) -> 477.555 | E26: =SUM(E20:E25) -> 906.1704 | F26: =SUM(F20:F25) -> 1492.8768 | G26: =SUM(G20:G25) -> 2519.1615 | H26: =SUM(H20:H25) -> 3542.3705 | I26: =SUM(I20:I25) -> 4269.5946 | J26: =SUM(J20:J25) -> 5205.0404 | K26: =SUM(K20:K25) -> 5877.4122 | ... M26: =SUM(M20:M25) -> 7114.2381
B28: D. Backlog roll-forward = prior + bookings − recognized revenue
B29: V1 closing backlog | D29: =(D20-D89) -> 100 | E29: =(D29+E20-E89) -> 250 | F29: =(E29+F20-F89) -> 412.1003 | G29: =(F29+G20-G89) -> 656.59205 | H29: =(G29+H20-H89) -> 905.27802 | I29: =(H29+I20-I89) -> 1131.2554 | J29: =(I29+J20-J89) -> 1355.5491 | K29: =(J29+K20-K89) -> 1548.1102 | L29: =(K29+L20-L89) -> 1730.232 | M29: =(L29+M20-M89) -> 1876.9308
B30: V2 closing backlog | D30: =(D21-D90) -> 288.575 | E30: =(D30+E21-E90) -> 530.798 | F30: =(E30+F21-F90) -> 674.2849 | G30: =(F30+G21-G90) -> 861.99435 | H30: =(G30+H21-H90) -> 1076.2626 | I30: =(H30+I21-I90) -> 1193.8026 | J30: =(I30+J21-J90) -> 1362.1475 | K30: =(J30+K21-K90) -> 1462.6493 | L30: =(K30+L21-L90) -> 1520.8623 | M30: =(L30+M21-M90) -> 1590.0225
B31: V3 closing backlog | D31: =(D22-D91) -> 0 | E31: =(D31+E22-E91) -> 73.3929 | F31: =(E31+F22-F91) -> 322.87374 | G31: =(F31+G22-G91) -> 701.81381 | H31: =(G31+H22-H91) -> 1154.4049 | I31: =(H31+I22-I91) -> 1652.2579 | J31: =(I31+J22-J91) -> 2145.2401 | K31: =(J31+K22-K91) -> 2677.241 | L31: =(K31+L22-L91) -> 3140.9833 | M31: =(L31+M22-M91) -> 3598.7336
B32: V4 closing backlog | D32: =(D23-D92) -> 0 | E32: =(D32+E23-E92) -> 100 | F32: =(E32+F23-F92) -> 317 | G32: =(F32+G23-G92) -> 793.79 | H32: =(G32+H23-H92) -> 1505.1982 | I32: =(H32+I23-I92) -> 2199.816 | J32: =(I32+J23-J92) -> 2919.8281 | K32: =(J32+K23-K92) -> 3556.966 | L32: =(K32+L23-L92) -> 4200.7688 | M32: =(L32+M23-M92) -> 4800.1397
B33: V5 closing backlog | D33: =(D24-D93) -> 0 | E33: =(D33+E24-E93) -> 75.81 | F33: =(E33+F24-F93) -> 201.8035 | G33: =(F33+G24-G93) -> 401.35262 | H33: =(G33+H24-H93) -> 634.84857 | I33: =(H33+I24-I93) -> 903.98973 | J33: =(I33+J24-J93) -> 1306.3833 | K33: =(J33+K24-K93) -> 1754.2499 | L33: =(K33+L24-L93) -> 2196.6074 | M33: =(L33+M24-M93) -> 2683.7128
B34: V6 closing backlog | D34: =(D25-D94) -> 36.48 | E34: =(D34+E25-E94) -> 97.817 | F34: =(E34+F25-F94) -> 201.60685 | G34: =(F34+G25-G94) -> 378.08444 | H34: =(G34+H25-H94) -> 612.30383 | I34: =(H34+I25-I94) -> 896.54167 | J34: =(I34+J25-J94) -> 1209.7094 | K34: =(J34+K25-K94) -> 1517.7092 | L34: =(K34+L25-L94) -> 1831.3711 | M34: =(L34+M25-M94) -> 2130.2036
B35: Σ Closing backlog (consolidated) | D35: =SUM(D29:D34) -> 425.055 | E35: =SUM(E29:E34) -> 1127.8179 | F35: =SUM(F29:F34) -> 2129.6693 | G35: =SUM(G29:G34) -> 3793.6273 | H35: =SUM(H29:H34) -> 5888.296 | I35: =SUM(I29:I34) -> 7977.6632 | J35: =SUM(J29:J34) -> 10298.857 | K35: =SUM(K29:K34) -> 12516.926 | ... M35: =SUM(M29:M34) -> 16679.743
B37: E. Consolidated KPIs
B38: Consolidated book-to-bill | D38: =IFERROR(D26/Revenue!D12,0) -> 9.0962857 | E38: =IFERROR(E26/Revenue!E12,0) -> 4.4549508 | F38: =IFERROR(F26/Revenue!F12,0) -> 3.040325 | G38: =IFERROR(G26/Revenue!G12,0) -> 2.9456865 | H38: =IFERROR(H26/Revenue!H12,0) -> 2.4468925 | I38: =IFERROR(I26/Revenue!I12,0) -> 1.9583254 | J38: =IFERROR(J26/Revenue!J12,0) -> 1.8048953 | K38: =IFERROR(K26/Revenue!K12,0) -> 1.6061382 | ... M38: =IFERROR(M26/Revenue!M12,0) -> 1.4072775
B39: Backlog coverage (months of revenue) | D39: =IFERROR(D35/Revenue!D12*12,0) -> 97.155429 | E39: =IFERROR(E35/Revenue!E12*12,0) -> 66.535476 | F39: =IFERROR(F35/Revenue!F12*12,0) -> 52.046251 | G39: =IFERROR(G35/Revenue!G12*12,0) -> 53.23122 | H39: =IFERROR(H35/Revenue!H12*12,0) -> 48.808088 | I39: =IFERROR(I35/Revenue!I12*12,0) -> 43.909162 | J39: =IFERROR(J35/Revenue!J12*12,0) -> 42.854674 | K39: =IFERROR(K35/Revenue!K12*12,0) -> 41.046458 | ... M39: =IFERROR(M35/Revenue!M12*12,0) -> 39.593323
B40: Backlog growth Y/Y | D40: =0 -> 0 | E40: =IFERROR(E35/D35-1,0) -> 1.6533458 | F40: =IFERROR(F35/E35-1,0) -> 0.88830953 | G40: =IFERROR(G35/F35-1,0) -> 0.78132224 | H40: =IFERROR(H35/G35-1,0) -> 0.55215461 | I40: =IFERROR(I35/H35-1,0) -> 0.35483392 | J40: =IFERROR(J35/I35-1,0) -> 0.29096167 | K40: =IFERROR(K35/J35-1,0) -> 0.21537032 | L40: =IFERROR(L35/K35-1,0) -> 0.16808434 | M40: =IFERROR(M35/L35-1,0) -> 0.14082093
B42: F. Derived book-to-bill (check = Bookings / Recognized Revenue)
B43: V1 AESA | D43: =IF(Revenue!D6=0,0,D20/Revenue!D6) -> 0 | E43: =IF(Revenue!E6=0,0,E20/Revenue!E6) -> 4 | F43: =IF(Revenue!F6=0,0,F20/Revenue!F6) -> 2.2968024 | G43: =IF(Revenue!G6=0,0,G20/Revenue!G6) -> 2.1865643 | H43: =IF(Revenue!H6=0,0,H20/Revenue!H6) -> 1.7575053 | I43: =IF(Revenue!I6=0,0,I20/Revenue!I6) -> 1.4992442 | J43: =IF(Revenue!J6=0,0,J20/Revenue!J6) -> 1.3965394 | K43: =IF(Revenue!K6=0,0,K20/Revenue!K6) -> 1.2841078 | ... M43: =IF(Revenue!M6=0,0,M20/Revenue!M6) -> 1.1695713
B44: V2 EW / SIGINT | D44: =IF(Revenue!D7=0,0,D21/Revenue!D7) -> 6.4966667 | E44: =IF(Revenue!E7=0,0,E21/Revenue!E7) -> 2.6787525 | F44: =IF(Revenue!F7=0,0,F21/Revenue!F7) -> 1.540646 | G44: =IF(Revenue!G7=0,0,G21/Revenue!G7) -> 1.556766 | H44: =IF(Revenue!H7=0,0,H21/Revenue!H7) -> 1.4971453 | I44: =IF(Revenue!I7=0,0,I21/Revenue!I7) -> 1.2184226 | J44: =IF(Revenue!J7=0,0,J21/Revenue!J7) -> 1.2820314 | K44: =IF(Revenue!K7=0,0,K21/Revenue!K7) -> 1.1475638 | ... M44: =IF(Revenue!M7=0,0,M21/Revenue!M7) -> 1.0909488
B45: V3 CUAS | D45: =IF(Revenue!D8=0,0,D22/Revenue!D8) -> 0 | E45: =IF(Revenue!E8=0,0,E22/Revenue!E8) -> 0 | F45: =IF(Revenue!F8=0,0,F22/Revenue!F8) -> 11.300759 | G45: =IF(Revenue!G8=0,0,G22/Revenue!G8) -> 4.5565085 | H45: =IF(Revenue!H8=0,0,H22/Revenue!H8) -> 2.9542049 | I45: =IF(Revenue!I8=0,0,I22/Revenue!I8) -> 2.3068599 | J45: =IF(Revenue!J8=0,0,J22/Revenue!J8) -> 1.9041479 | K45: =IF(Revenue!K8=0,0,K22/Revenue!K8) -> 1.7514889 | ... M45: =IF(Revenue!M8=0,0,M22/Revenue!M8) -> 1.4416204
B46: V4 MALE UAS | D46: =IF(Revenue!D9=0,0,D23/Revenue!D9) -> 0 | E46: =IF(Revenue!E9=0,0,E23/Revenue!E9) -> 0 | F46: =IF(Revenue!F9=0,0,F23/Revenue!F9) -> 7.5757576 | G46: =IF(Revenue!G9=0,0,G23/Revenue!G9) -> 5.5577861 | H46: =IF(Revenue!H9=0,0,H23/Revenue!H9) -> 3.7158095 | I46: =IF(Revenue!I9=0,0,I23/Revenue!I9) -> 2.3984221 | J46: =IF(Revenue!J9=0,0,J23/Revenue!J9) -> 1.9918352 | K46: =IF(Revenue!K9=0,0,K23/Revenue!K9) -> 1.6612447 | ... M46: =IF(Revenue!M9=0,0,M23/Revenue!M9) -> 1.4323674
B47: V5 Autonomous | D47: =IF(Revenue!D10=0,0,D24/Revenue!D10) -> 0 | E47: =IF(Revenue!E10=0,0,E24/Revenue!E10) -> 0 | F47: =IF(Revenue!F10=0,0,F24/Revenue!F10) -> 7.6478565 | G47: =IF(Revenue!G10=0,0,G24/Revenue!G10) -> 4.9553154 | H47: =IF(Revenue!H10=0,0,H24/Revenue!H10) -> 3.3270902 | I47: =IF(Revenue!I10=0,0,I24/Revenue!I10) -> 2.6957818 | J47: =IF(Revenue!J10=0,0,J24/Revenue!J10) -> 2.7805227 | K47: =IF(Revenue!K10=0,0,K24/Revenue!K10) -> 2.3713175 | ... M47: =IF(Revenue!M10=0,0,M24/Revenue!M10) -> 1.8870139
B48: V6 Military AI | D48: =IF(Revenue!D11=0,0,D25/Revenue!D11) -> 0 | E48: =IF(Revenue!E11=0,0,E25/Revenue!E11) -> 7.7255482 | F48: =IF(Revenue!F11=0,0,F25/Revenue!F11) -> 5.2442459 | G48: =IF(Revenue!G11=0,0,G25/Revenue!G11) -> 4.5014205 | H48: =IF(Revenue!H11=0,0,H25/Revenue!H11) -> 3.4779585 | I48: =IF(Revenue!I11=0,0,I25/Revenue!I11) -> 2.8568418 | J48: =IF(Revenue!J11=0,0,J25/Revenue!J11) -> 2.3972253 | K48: =IF(Revenue!K11=0,0,K25/Revenue!K11) -> 2.018426 | ... M48: =IF(Revenue!M11=0,0,M25/Revenue!M11) -> 1.6526968
B49: Σ Derived B:B | D49: =IFERROR(SUM(D20:D25)/SUM(Revenue!D6:D11),0) -> 9.0962857 | E49: =IFERROR(SUM(E20:E25)/SUM(Revenue!E6:E11),0) -> 4.4549508 | F49: =IFERROR(SUM(F20:F25)/SUM(Revenue!F6:F11),0) -> 3.040325 | G49: =IFERROR(SUM(G20:G25)/SUM(Revenue!G6:G11),0) -> 2.9456865 | H49: =IFERROR(SUM(H20:H25)/SUM(Revenue!H6:H11),0) -> 2.4468925 | I49: =IFERROR(SUM(I20:I25)/SUM(Revenue!I6:I11),0) -> 1.9583254 | J49: =IFERROR(SUM(J20:J25)/SUM(Revenue!J6:J11),0) -> 1.8048953 | K49: =IFERROR(SUM(K20:K25)/SUM(Revenue!K6:K11),0) -> 1.6061382 | ... M49: =IFERROR(SUM(M20:M25)/SUM(Revenue!M6:M11),0) -> 1.4072775
B51: G. Qualified pipeline (derived = Bookings / Pwin)
B52: Advance payment inflow (adv % × bookings) | D52: =Assumptions!$C$22*D26 -> 71.63325 | E52: =Assumptions!$C$22*E26 -> 135.92556 | F52: =Assumptions!$C$22*F26 -> 223.93152 | G52: =Assumptions!$C$22*G26 -> 377.87423 | H52: =Assumptions!$C$22*H26 -> 531.35557 | I52: =Assumptions!$C$22*I26 -> 640.43919 | J52: =Assumptions!$C$22*J26 -> 780.75606 | K52: =Assumptions!$C$22*K26 -> 881.61183 | ... M52: =Assumptions!$C$22*M26 -> 1067.1357
B53: Memo: revenue recognized (consolidated) | D53: =Revenue!D12 -> 52.5 | E53: =Revenue!E12 -> 203.4075 | F53: =Revenue!F12 -> 491.02541 | G53: =Revenue!G12 -> 855.20352 | H53: =Revenue!H12 -> 1447.7017 | I53: =Revenue!I12 -> 2180.2274 | J53: =Revenue!J12 -> 2883.8462 | K53: =Revenue!K12 -> 3659.344 | ... M53: =Revenue!M12 -> 5055.32
B54: Contract Liability - beginning balance | D54: =0 -> 0 | E54: =D56 -> 63.75825 | F54: =E56 -> 169.17268 | G54: =F56 -> 319.45039 | H54: =G56 -> 569.04409 | I54: =H56 -> 883.24441 | J54: =I56 -> 1196.6495 | K54: =J56 -> 1544.8286 | L54: =K56 -> 1877.5388 | M54: =L56 -> 2193.1237
B55: Advance amortized into recognized revenue | D55: =MIN(D54+D52,D53*Assumptions!$C$22) -> 7.875 | E55: =MIN(E54+E52,E53*Assumptions!$C$22) -> 30.511125 | F55: =MIN(F54+F52,F53*Assumptions!$C$22) -> 73.653811 | G55: =MIN(G54+G52,G53*Assumptions!$C$22) -> 128.28053 | H55: =MIN(H54+H52,H53*Assumptions!$C$22) -> 217.15526 | I55: =MIN(I54+I52,I53*Assumptions!$C$22) -> 327.03411 | J55: =MIN(J54+J52,J53*Assumptions!$C$22) -> 432.57693 | K55: =MIN(K54+K52,K53*Assumptions!$C$22) -> 548.90159 | ... M55: =MIN(M54+M52,M53*Assumptions!$C$22) -> 758.29799
B56: Contract Liability - ending balance (EoY) | D56: =MAX(0,D54+D52-D55) -> 63.75825 | E56: =MAX(0,E54+E52-E55) -> 169.17268 | F56: =MAX(0,F54+F52-F55) -> 319.45039 | G56: =MAX(0,G54+G52-G55) -> 569.04409 | H56: =MAX(0,H54+H52-H55) -> 883.24441 | I56: =MAX(0,I54+I52-I55) -> 1196.6495 | J56: =MAX(0,J54+J52-J55) -> 1544.8286 | K56: =MAX(0,K54+K52-K55) -> 1877.5388 | ... M56: =MAX(0,M54+M52-M55) -> 2501.9615
B57: Net change in contract liability (inflow − amortization) | D57: =D52-D55 -> 63.75825 | E57: =E52-E55 -> 105.41443 | F57: =F52-F55 -> 150.27771 | G57: =G52-G55 -> 249.5937 | H57: =H52-H55 -> 314.20032 | I57: =I52-I55 -> 313.40508 | J57: =J52-J55 -> 348.17913 | K57: =K52-K55 -> 332.71024 | ... M57: =M52-M55 -> 308.83772
B59: I. Bank guarantees (PBG + ABG) & restricted cash collateral
B60: Advance Bank Guarantee outstanding (= CL EoY) | D60: =D56 -> 63.75825 | E60: =E56 -> 169.17268 | F60: =F56 -> 319.45039 | G60: =G56 -> 569.04409 | H60: =H56 -> 883.24441 | I60: =I56 -> 1196.6495 | J60: =J56 -> 1544.8286 | K60: =K56 -> 1877.5388 | ... M60: =M56 -> 2501.9615
B61: Performance Bank Guarantee outstanding (PBG % × closing backlog) | D61: =Assumptions!$C$21*D35 -> 12.75165 | E61: =Assumptions!$C$21*E35 -> 33.834537 | F61: =Assumptions!$C$21*F35 -> 63.890079 | G61: =Assumptions!$C$21*G35 -> 113.80882 | H61: =Assumptions!$C$21*H35 -> 176.64888 | I61: =Assumptions!$C$21*I35 -> 239.3299 | J61: =Assumptions!$C$21*J35 -> 308.96572 | K61: =Assumptions!$C$21*K35 -> 375.50777 | ... M61: =Assumptions!$C$21*M35 -> 500.39229
B62: Total guarantees outstanding (ABG + PBG) | D62: =D60+D61 -> 76.5099 | E62: =E60+E61 -> 203.00722 | F62: =F60+F61 -> 383.34047 | G62: =G60+G61 -> 682.85291 | H62: =H60+H61 -> 1059.8933 | I62: =I60+I61 -> 1435.9794 | J62: =J60+J61 -> 1853.7943 | K62: =K60+K61 -> 2253.0466 | ... M62: =M60+M61 -> 3002.3537
B63: Restricted cash (collateral % x total guarantees) - schedule: Y1-Y2 100%, Y3 50%, Y4 30%, Y5+ 20% | D63: =0.1*D62 -> 7.65099 | E63: =0.1*E62 -> 20.300722 | F63: =0.1*F62 -> 38.334047 | G63: =0.1*G62 -> 68.285291 | H63: =0.1*H62 -> 105.98933 | I63: =0.1*I62 -> 143.59794 | J63: =0.1*J62 -> 185.37943 | K63: =0.1*K62 -> 225.30466 | ... M63: =0.1*M62 -> 300.23537
B64: Bank guarantee fee (annual % × outstanding) | D64: =Assumptions!$C$23*D62 -> 0.8416089 | E64: =Assumptions!$C$23*E62 -> 2.2330794 | F64: =Assumptions!$C$23*F62 -> 4.2167452 | G64: =Assumptions!$C$23*G62 -> 7.511382 | H64: =Assumptions!$C$23*H62 -> 11.658826 | I64: =Assumptions!$C$23*I62 -> 15.795773 | J64: =Assumptions!$C$23*J62 -> 20.391738 | K64: =Assumptions!$C$23*K62 -> 24.783513 | ... M64: =Assumptions!$C$23*M62 -> 33.025891
B66: Notes: Bookings are independent inputs. Closing backlog = opening + bookings − DELIVERIES (per-vertical % of opening backlog).
B67: B:B > 1 = backlog growing (healthy growth phase); B:B near 1 = mature steady-state; B:B < 1 = backlog shrinking.
B68: Defense HW typically has 12-18 month lag from award (booking) to delivery (recognized revenue); SW/SaaS 3-12 months.
B69: Pwin defaults are conservative new-age prime values - ESM higher (40%) due to existing customer relationships.
B70: Pipeline = Bookings / Pwin is the qualified opportunity value the BD org must keep loaded for the bookings plan.
B71: Edit yellow cells in sections A and B to model scenarios (e.g., aggressive growth: lift early B:B for V4 to 3.5).
B72: Advance payments (15%) collected at award generate a Contract Liability that amortizes as revenue is recognized.
B73: 'Parks cash at the bank (100% collateral) to back performance bank guarantees & advance bank guarantees
B74: K. Opening backlog (carried forward from prior-year closing)
B75: V1 - AESA Radar | D75: 0 | E75: =D29 -> 100 | F75: =E29 -> 250 | G75: =F29 -> 412.1003 | H75: =G29 -> 656.59205 | I75: =H29 -> 905.27802 | J75: =I29 -> 1131.2554 | K75: =J29 -> 1355.5491 | L75: =K29 -> 1548.1102 | M75: =L29 -> 1730.232
B76: V2 - EW & SIGINT | D76: 105 | E76: =D30 -> 288.575 | F76: =E30 -> 530.798 | G76: =F30 -> 674.2849 | H76: =G30 -> 861.99435 | I76: =H30 -> 1076.2626 | J76: =I30 -> 1193.8026 | K76: =J30 -> 1362.1475 | L76: =K30 -> 1462.6493 | M76: =L30 -> 1520.8623
B77: V3 - Counter-UAS | D77: 0 | E77: =D31 -> 0 | F77: =E31 -> 73.3929 | G77: =F31 -> 322.87374 | H77: =G31 -> 701.81381 | I77: =H31 -> 1154.4049 | J77: =I31 -> 1652.2579 | K77: =J31 -> 2145.2401 | L77: =K31 -> 2677.241 | M77: =L31 -> 3140.9833
B78: V4 - MALE UAS | D78: 0 | E78: =D32 -> 0 | F78: =E32 -> 100 | G78: =F32 -> 317 | H78: =G32 -> 793.79 | I78: =H32 -> 1505.1982 | J78: =I32 -> 2199.816 | K78: =J32 -> 2919.8281 | L78: =K32 -> 3556.966 | M78: =L32 -> 4200.7688
B79: V5 - Autonomous | D79: 0 | E79: =D33 -> 0 | F79: =E33 -> 75.81 | G79: =F33 -> 201.8035 | H79: =G33 -> 401.35262 | I79: =H33 -> 634.84857 | J79: =I33 -> 903.98973 | K79: =J33 -> 1306.3833 | L79: =K33 -> 1754.2499 | M79: =L33 -> 2196.6074
B80: V6 - Military AI | D80: 0 | E80: =D34 -> 36.48 | F80: =E34 -> 97.817 | G80: =F34 -> 201.60685 | H80: =G34 -> 378.08444 | I80: =H34 -> 612.30383 | J80: =I34 -> 896.54167 | K80: =J34 -> 1209.7094 | L80: =K34 -> 1517.7092 | M80: =L34 -> 1831.3711
B81: L. Delivery schedule - per-vertical % of opening backlog recognized as revenue
B82: V1 - AESA Radar delivery rate | D82: 0.5 | E82: 0.5 | F82: 0.5 | G82: 0.5 | H82: 0.5 | I82: 0.5 | J82: 0.5 | K82: 0.5 | L82: 0.5 | M82: 0.5
B83: V2 - EW & SIGINT delivery rate | D83: 0.5 | E83: 0.5 | F83: 0.5 | G83: 0.5 | H83: 0.5 | I83: 0.5 | J83: 0.5 | K83: 0.5 | L83: 0.5 | M83: 0.5
B84: V3 - Counter-UAS delivery rate | D84: 0.33 | E84: 0.33 | F84: 0.33 | G84: 0.33 | H84: 0.33 | I84: 0.33 | J84: 0.33 | K84: 0.33 | L84: 0.33 | M84: 0.33
B85: V4 - MALE UAS delivery rate | D85: 0.33 | E85: 0.33 | F85: 0.33 | G85: 0.33 | H85: 0.33 | I85: 0.33 | J85: 0.33 | K85: 0.33 | L85: 0.33 | M85: 0.33
B86: V5 - Autonomous delivery rate | D86: 0.25 | E86: 0.25 | F86: 0.25 | G86: 0.25 | H86: 0.25 | I86: 0.25 | J86: 0.25 | K86: 0.25 | L86: 0.25 | M86: 0.25
B87: V6 - Military AI delivery rate | D87: 0.25 | E87: 0.25 | F87: 0.25 | G87: 0.25 | H87: 0.25 | I87: 0.25 | J87: 0.25 | K87: 0.25 | L87: 0.25 | M87: 0.25
B89: Deliveries: V1 - AESA Radar | D89: =D75*D82 -> 0 | E89: =E75*E82 -> 50 | F89: =F75*F82 -> 125 | G89: =G75*G82 -> 206.05015 | H89: =H75*H82 -> 328.29602 | I89: =I75*I82 -> 452.63901 | J89: =J75*J82 -> 565.62771 | K89: =K75*K82 -> 677.77455 | ... M89: =M75*M82 -> 865.11599
B90: Deliveries: V2 - EW & SIGINT | D90: =D76*D83 -> 52.5 | E90: =E76*E83 -> 144.2875 | F90: =F76*F83 -> 265.399 | G90: =G76*G83 -> 337.14245 | H90: =H76*H83 -> 430.99717 | I90: =I76*I83 -> 538.13129 | J90: =J76*J83 -> 596.90129 | K90: =K76*K83 -> 681.07375 | ... M90: =M76*M83 -> 760.43114
B91: Deliveries: V3 - Counter-UAS | D91: =D77*D84 -> 0 | E91: =E77*E84 -> 0 | F91: =F77*F84 -> 24.219657 | G91: =G77*G84 -> 106.54834 | H91: =H77*H84 -> 231.59856 | I91: =I77*I84 -> 380.9536 | J91: =J77*J84 -> 545.24509 | K91: =K77*K84 -> 707.92922 | ... M91: =M77*M84 -> 1036.5245
B92: Deliveries: V4 - MALE UAS | D92: =D78*D85 -> 0 | E92: =E78*E85 -> 0 | F92: =F78*F85 -> 33 | G92: =G78*G85 -> 104.61 | H92: =H78*H85 -> 261.9507 | I92: =I78*I85 -> 496.71541 | J92: =J78*J85 -> 725.93928 | K92: =K78*K85 -> 963.54328 | ... M92: =M78*M85 -> 1386.2537
B93: Deliveries: V5 - Autonomous | D93: =D79*D86 -> 0 | E93: =E79*E86 -> 0 | F93: =F79*F86 -> 18.9525 | G93: =G79*G86 -> 50.450875 | H93: =H79*H86 -> 100.33816 | I93: =I79*I86 -> 158.71214 | J93: =J79*J86 -> 225.99743 | K93: =K79*K86 -> 326.59582 | ... M93: =M79*M86 -> 549.15185
B94: Deliveries: V6 - Military AI | D94: =D80*D87 -> 0 | E94: =E80*E87 -> 9.12 | F94: =F80*F87 -> 24.45425 | G94: =G80*G87 -> 50.401712 | H94: =H80*H87 -> 94.521109 | I94: =I80*I87 -> 153.07596 | J94: =J80*J87 -> 224.13542 | K94: =K80*K87 -> 302.42734 | ... M94: =M80*M87 -> 457.84278
B95: Σ Deliveries (revenue recognized) | D95: =SUM(D89:D94) -> 52.5 | E95: =SUM(E89:E94) -> 203.4075 | F95: =SUM(F89:F94) -> 491.02541 | G95: =SUM(G89:G94) -> 855.20352 | H95: =SUM(H89:H94) -> 1447.7017 | I95: =SUM(I89:I94) -> 2180.2274 | J95: =SUM(J89:J94) -> 2883.8462 | K95: =SUM(K89:K94) -> 3659.344 | ... M95: =SUM(M89:M94) -> 5055.32
B97: N. Notes on restructured Backlog flow
B98: Bookings are now INDEPENDENT static inputs (not derived from revenue).
B99: Closing backlog = Opening + Bookings - Deliveries.
B100: Delivery ratio bridges opening backlog to implied revenue.
B101: Revenue is now FULLY DERIVED from Backlog deliveries (Section L drives Revenue sheet).
B102: Edit yellow cells in Section L (D82:M87) to tune per-vertical recognition rates.

Sheet Headcount
B2: Headcount Plan & Fully-Loaded Personnel Cost
B4: Role | C4: Cost band (₹ L/yr) | D4: Y1 | E4: Y2 | F4: Y3 | G4: Y4 | H4: Y5 | I4: Y6 | J4: Y7 | K4: Y8 | L4: Y9 | M4: Y10
B5: A. Headcount (# people)
B6: RF / Microwave Engineers | C6: 18 | D6: 10 | E6: 14 | F6: 17 | G6: 19 | H6: 20 | I6: 21 | J6: 22 | K6: 22 | L6: 22 | M6: 22
B7: DSP / FPGA Engineers | C7: 25 | D7: 8 | E7: 11 | F7: 13 | G7: 15 | H7: 16 | I7: 17 | J7: 17 | K7: 18 | L7: 18 | M7: 18
B8: Antenna / Array Engineers | C8: 28 | D8: 4 | E8: 6 | F8: 7 | G8: 8 | H8: 9 | I8: 9 | J8: 10 | K8: 10 | L8: 10 | M8: 10
B9: Embedded / Firmware Engineers | C9: 18 | D9: 7 | E9: 10 | F9: 12 | G9: 13 | H9: 14 | I9: 15 | J9: 16 | K9: 16 | L9: 17 | M9: 17
B10: Systems Engineers (MIL-STD, ICD) | C10: 18 | D10: 5 | E10: 8 | F10: 10 | G10: 12 | H10: 13 | I10: 14 | J10: 14 | K10: 15 | L10: 15 | M10: 15
B11: Mechanical / Thermal Engineers | C11: 18 | D11: 4 | E11: 6 | F11: 8 | G11: 9 | H11: 10 | I11: 11 | J11: 11 | K11: 12 | L11: 12 | M11: 12
B12: Aerospace / Flight Systems Engineers | C12: 22 | D12: 0 | E12: 1 | F12: 3 | G12: 6 | H12: 9 | I12: 11 | J12: 12 | K12: 13 | L12: 13 | M12: 13
B13: Naval / Subsea Systems Engineers | C13: 32 | D13: 0 | E13: 1 | F13: 3 | G13: 5 | H13: 7 | I13: 9 | J13: 10 | K13: 11 | L13: 11 | M13: 11
B14: Autonomy / Controls Engineers | C14: 32 | D14: 2 | E14: 4 | F14: 6 | G14: 9 | H14: 11 | I14: 12 | J14: 13 | K14: 14 | L14: 14 | M14: 14
B15: Mission Software Engineers | C15: 40 | D15: 6 | E15: 9 | F15: 11 | G15: 13 | H15: 14 | I15: 15 | J15: 16 | K15: 17 | L15: 17 | M15: 17
B16: Cybersecurity Engineers | C16: 14 | D16: 2 | E16: 3 | F16: 4 | G16: 5 | H16: 6 | I16: 7 | J16: 7 | K16: 8 | L16: 8 | M16: 8
B17: AI / ML Engineers (CV, fusion, autonomy) | C17: 14 | D17: 4 | E17: 7 | F17: 10 | G17: 12 | H17: 14 | I17: 16 | J17: 17 | K17: 18 | L17: 19 | M17: 20
... B33: IT / DevOps / Cloud | C33: 12 | D33: 2 | E33: 3 | F33: 4 | G33: 5 | H33: 6 | I33: 6 | J33: 7 | K33: 7 | L33: 8 | M33: 8
B34: Total headcount (EoY) | C34: 18 | D34: =SUM(D6:D33) -> 91 | E34: =SUM(E6:E33) -> 156 | F34: =SUM(F6:F33) -> 216 | G34: =SUM(G6:G33) -> 287 | H34: =SUM(H6:H33) -> 349 | I34: =SUM(I6:I33) -> 414 | J34: =SUM(J6:J33) -> 475 | K34: =SUM(K6:K33) -> 506 | ... M34: =SUM(M6:M33) -> 543
B36: B. Personnel cost by role (INR lakhs, escalated - R&D separate from general)
B37: RF / Microwave Engineers - cost | C37: R&D | D37: =C6*(1+Assumptions!$C$9)^0*D6/100 -> 1.8 | E37: =C6*(1+Assumptions!$C$9)^1*E6/100 -> 2.6208 | F37: =C6*(1+Assumptions!$C$9)^2*F6/100 -> 3.309696 | G37: =C6*(1+Assumptions!$C$9)^3*G6/100 -> 3.8470349 | H37: =C6*(1+Assumptions!$C$9)^4*H6/100 -> 4.2114908 | I37: =C6*(1+Assumptions!$C$9)^5*I6/100 -> 4.598948 | J37: =C6*(1+Assumptions!$C$9)^6*J6/100 -> 5.0106633 | K37: =C6*(1+Assumptions!$C$9)^7*K6/100 -> 5.2110898 | L37: =C6*(1+Assumptions!$C$9)^8*L6/100 -> 5.4195334 | M37: =C6*(1+Assumptions!$C$9)^9*M6/100 -> 5.6363148
B38: DSP / FPGA Engineers - cost | C38: R&D | D38: =C7*(1+Assumptions!$C$9)^0*D7/100 -> 2 | E38: =C7*(1+Assumptions!$C$9)^1*E7/100 -> 2.86 | F38: =C7*(1+Assumptions!$C$9)^2*F7/100 -> 3.5152 | G38: =C7*(1+Assumptions!$C$9)^3*G7/100 -> 4.21824 | H38: =C7*(1+Assumptions!$C$9)^4*H7/100 -> 4.6794342 | I38: =C7*(1+Assumptions!$C$9)^5*I7/100 -> 5.1707748 | J38: =C7*(1+Assumptions!$C$9)^6*J7/100 -> 5.3776058 | K38: =C7*(1+Assumptions!$C$9)^7*K7/100 -> 5.921693 | L38: =C7*(1+Assumptions!$C$9)^8*L7/100 -> 6.1585607 | M38: =C7*(1+Assumptions!$C$9)^9*M7/100 -> 6.4049032
B39: Antenna / Array Engineers - cost | C39: R&D | D39: =C8*(1+Assumptions!$C$9)^0*D8/100 -> 1.12 | E39: =C8*(1+Assumptions!$C$9)^1*E8/100 -> 1.7472 | F39: =C8*(1+Assumptions!$C$9)^2*F8/100 -> 2.119936 | G39: =C8*(1+Assumptions!$C$9)^3*G8/100 -> 2.5196954 | H39: =C8*(1+Assumptions!$C$9)^4*H8/100 -> 2.9480436 | I39: =C8*(1+Assumptions!$C$9)^5*I8/100 -> 3.0659653 | J39: =C8*(1+Assumptions!$C$9)^6*J8/100 -> 3.5428933 | K39: =C8*(1+Assumptions!$C$9)^7*K8/100 -> 3.684609 | L39: =C8*(1+Assumptions!$C$9)^8*L8/100 -> 3.8319933 | M39: =C8*(1+Assumptions!$C$9)^9*M8/100 -> 3.9852731
B40: Embedded / Firmware Engineers - cost | C40: R&D | D40: =C9*(1+Assumptions!$C$9)^0*D9/100 -> 1.26 | E40: =C9*(1+Assumptions!$C$9)^1*E9/100 -> 1.872 | F40: =C9*(1+Assumptions!$C$9)^2*F9/100 -> 2.336256 | G40: =C9*(1+Assumptions!$C$9)^3*G9/100 -> 2.6321818 | H40: =C9*(1+Assumptions!$C$9)^4*H9/100 -> 2.9480436 | I40: =C9*(1+Assumptions!$C$9)^5*I9/100 -> 3.2849628 | J40: =C9*(1+Assumptions!$C$9)^6*J9/100 -> 3.6441188 | K40: =C9*(1+Assumptions!$C$9)^7*K9/100 -> 3.7898835 | L40: =C9*(1+Assumptions!$C$9)^8*L9/100 -> 4.1878213 | M40: =C9*(1+Assumptions!$C$9)^9*M9/100 -> 4.3553341
B41: Systems Engineers (MIL-STD, ICD) - cost | C41: R&D | D41: =C10*(1+Assumptions!$C$9)^0*D10/100 -> 0.9 | E41: =C10*(1+Assumptions!$C$9)^1*E10/100 -> 1.4976 | F41: =C10*(1+Assumptions!$C$9)^2*F10/100 -> 1.94688 | G41: =C10*(1+Assumptions!$C$9)^3*G10/100 -> 2.4297062 | H41: =C10*(1+Assumptions!$C$9)^4*H10/100 -> 2.737469 | I41: =C10*(1+Assumptions!$C$9)^5*I10/100 -> 3.0659653 | J41: =C10*(1+Assumptions!$C$9)^6*J10/100 -> 3.1886039 | K41: =C10*(1+Assumptions!$C$9)^7*K10/100 -> 3.5530158 | L41: =C10*(1+Assumptions!$C$9)^8*L10/100 -> 3.6951364 | M41: =C10*(1+Assumptions!$C$9)^9*M10/100 -> 3.8429419
B42: Mechanical / Thermal Engineers - cost | C42: R&D | D42: =C11*(1+Assumptions!$C$9)^0*D11/100 -> 0.72 | E42: =C11*(1+Assumptions!$C$9)^1*E11/100 -> 1.1232 | F42: =C11*(1+Assumptions!$C$9)^2*F11/100 -> 1.557504 | G42: =C11*(1+Assumptions!$C$9)^3*G11/100 -> 1.8222797 | H42: =C11*(1+Assumptions!$C$9)^4*H11/100 -> 2.1057454 | I42: =C11*(1+Assumptions!$C$9)^5*I11/100 -> 2.4089727 | J42: =C11*(1+Assumptions!$C$9)^6*J11/100 -> 2.5053317 | K42: =C11*(1+Assumptions!$C$9)^7*K11/100 -> 2.8424126 | L42: =C11*(1+Assumptions!$C$9)^8*L11/100 -> 2.9561091 | M42: =C11*(1+Assumptions!$C$9)^9*M11/100 -> 3.0743535
B43: Aerospace / Flight Systems Engineers - cost | C43: R&D | D43: =C12*(1+Assumptions!$C$9)^0*D12/100 -> 0 | E43: =C12*(1+Assumptions!$C$9)^1*E12/100 -> 0.2288 | F43: =C12*(1+Assumptions!$C$9)^2*F12/100 -> 0.713856 | G43: =C12*(1+Assumptions!$C$9)^3*G12/100 -> 1.4848205 | H43: =C12*(1+Assumptions!$C$9)^4*H12/100 -> 2.3163199 | I43: =C12*(1+Assumptions!$C$9)^5*I12/100 -> 2.9443 | J43: =C12*(1+Assumptions!$C$9)^6*J12/100 -> 3.3404422 | K43: =C12*(1+Assumptions!$C$9)^7*K12/100 -> 3.7635649 | L43: =C12*(1+Assumptions!$C$9)^8*L12/100 -> 3.9141075 | M43: =C12*(1+Assumptions!$C$9)^9*M12/100 -> 4.0706718
B44: Naval / Subsea Systems Engineers - cost | C44: R&D | D44: =C13*(1+Assumptions!$C$9)^0*D13/100 -> 0 | E44: =C13*(1+Assumptions!$C$9)^1*E13/100 -> 0.3328 | F44: =C13*(1+Assumptions!$C$9)^2*F13/100 -> 1.038336 | G44: =C13*(1+Assumptions!$C$9)^3*G13/100 -> 1.7997824 | H44: =C13*(1+Assumptions!$C$9)^4*H13/100 -> 2.6204832 | I44: =C13*(1+Assumptions!$C$9)^5*I13/100 -> 3.5039604 | J44: =C13*(1+Assumptions!$C$9)^6*J13/100 -> 4.0490209 | K44: =C13*(1+Assumptions!$C$9)^7*K13/100 -> 4.6320799 | L44: =C13*(1+Assumptions!$C$9)^8*L13/100 -> 4.8173631 | M44: =C13*(1+Assumptions!$C$9)^9*M13/100 -> 5.0100576
B45: Autonomy / GNC / Controls Engineers - cost | C45: R&D | D45: =C14*(1+Assumptions!$C$9)^0*D14/100 -> 0.64 | E45: =C14*(1+Assumptions!$C$9)^1*E14/100 -> 1.3312 | F45: =C14*(1+Assumptions!$C$9)^2*F14/100 -> 2.076672 | G45: =C14*(1+Assumptions!$C$9)^3*G14/100 -> 3.2396083 | H45: =C14*(1+Assumptions!$C$9)^4*H14/100 -> 4.1179021 | I45: =C14*(1+Assumptions!$C$9)^5*I14/100 -> 4.6719471 | J45: =C14*(1+Assumptions!$C$9)^6*J14/100 -> 5.2637271 | K45: =C14*(1+Assumptions!$C$9)^7*K14/100 -> 5.8953744 | L45: =C14*(1+Assumptions!$C$9)^8*L14/100 -> 6.1311893 | M45: =C14*(1+Assumptions!$C$9)^9*M14/100 -> 6.3764369
B46: Mission Software Engineers - cost | C46: R&D | D46: =C15*(1+Assumptions!$C$9)^0*D15/100 -> 2.4 | E46: =C15*(1+Assumptions!$C$9)^1*E15/100 -> 3.744 | F46: =C15*(1+Assumptions!$C$9)^2*F15/100 -> 4.75904 | G46: =C15*(1+Assumptions!$C$9)^3*G15/100 -> 5.8492928 | H46: =C15*(1+Assumptions!$C$9)^4*H15/100 -> 6.5512079 | I46: =C15*(1+Assumptions!$C$9)^5*I15/100 -> 7.2999174 | J46: =C15*(1+Assumptions!$C$9)^6*J15/100 -> 8.0980417 | K46: =C15*(1+Assumptions!$C$9)^7*K15/100 -> 8.9483361 | L46: =C15*(1+Assumptions!$C$9)^8*L15/100 -> 9.3062695 | M46: =C15*(1+Assumptions!$C$9)^9*M15/100 -> 9.6785203
B47: Cybersecurity Engineers - cost | C47: R&D | D47: =C16*(1+Assumptions!$C$9)^0*D16/100 -> 0.28 | E47: =C16*(1+Assumptions!$C$9)^1*E16/100 -> 0.4368 | F47: =C16*(1+Assumptions!$C$9)^2*F16/100 -> 0.605696 | G47: =C16*(1+Assumptions!$C$9)^3*G16/100 -> 0.7874048 | H47: =C16*(1+Assumptions!$C$9)^4*H16/100 -> 0.98268119 | I47: =C16*(1+Assumptions!$C$9)^5*I16/100 -> 1.1923198 | J47: =C16*(1+Assumptions!$C$9)^6*J16/100 -> 1.2400126 | K47: =C16*(1+Assumptions!$C$9)^7*K16/100 -> 1.4738436 | L47: =C16*(1+Assumptions!$C$9)^8*L16/100 -> 1.5327973 | M47: =C16*(1+Assumptions!$C$9)^9*M16/100 -> 1.5941092
B48: AI / ML Engineers (CV, fusion, autonomy) - cost | C48: R&D | D48: =C17*(1+Assumptions!$C$9)^0*D17/100 -> 0.56 | E48: =C17*(1+Assumptions!$C$9)^1*E17/100 -> 1.0192 | F48: =C17*(1+Assumptions!$C$9)^2*F17/100 -> 1.51424 | G48: =C17*(1+Assumptions!$C$9)^3*G17/100 -> 1.8897715 | H48: =C17*(1+Assumptions!$C$9)^4*H17/100 -> 2.2929228 | I48: =C17*(1+Assumptions!$C$9)^5*I17/100 -> 2.7253025 | J48: =C17*(1+Assumptions!$C$9)^6*J17/100 -> 3.0114593 | K48: =C17*(1+Assumptions!$C$9)^7*K17/100 -> 3.3161481 | L48: =C17*(1+Assumptions!$C$9)^8*L17/100 -> 3.6403937 | M48: =C17*(1+Assumptions!$C$9)^9*M17/100 -> 3.9852731
... B51: Certification / Airworthiness - cost | C51: R&D | D51: =C20*(1+Assumptions!$C$9)^0*D20/100 -> 0 | E51: =C20*(1+Assumptions!$C$9)^1*E20/100 -> 0.1248 | F51: =C20*(1+Assumptions!$C$9)^2*F20/100 -> 0.259584 | G51: =C20*(1+Assumptions!$C$9)^3*G20/100 -> 0.40495104 | H51: =C20*(1+Assumptions!$C$9)^4*H20/100 -> 0.56153211 | I51: =C20*(1+Assumptions!$C$9)^5*I20/100 -> 0.58399339 | J51: =C20*(1+Assumptions!$C$9)^6*J20/100 -> 0.75919141 | K51: =C20*(1+Assumptions!$C$9)^7*K20/100 -> 0.78955907 | L51: =C20*(1+Assumptions!$C$9)^8*L20/100 -> 0.82114143 | M51: =C20*(1+Assumptions!$C$9)^9*M20/100 -> 0.85398709
B52: Manufacturing / Production Engineers - cost | C52: COGS | D52: =C21*(1+Assumptions!$C$8)^0*D21/100 -> 0.66 | E52: =C21*(1+Assumptions!$C$8)^1*E21/100 -> 1.6016 | F52: =C21*(1+Assumptions!$C$8)^2*F21/100 -> 2.617472 | G52: =C21*(1+Assumptions!$C$8)^3*G21/100 -> 4.2069914 | H52: =C21*(1+Assumptions!$C$8)^4*H21/100 -> 5.6621154 | I52: =C21*(1+Assumptions!$C$8)^5*I21/100 -> 7.7622455 | J52: =C21*(1+Assumptions!$C$8)^6*J21/100 -> 10.021327 | K52: =C21*(1+Assumptions!$C$8)^7*K21/100 -> 11.00119 | L52: =C21*(1+Assumptions!$C$8)^8*L21/100 -> 12.043408 | M52: =C21*(1+Assumptions!$C$8)^9*M21/100 -> 12.525144
B53: Production Technicians - cost | C53: COGS | D53: =C22*(1+Assumptions!$C$8)^0*D22/100 -> 0.88 | E53: =C22*(1+Assumptions!$C$8)^1*E22/100 -> 2.0592 | F53: =C22*(1+Assumptions!$C$8)^2*F22/100 -> 3.450304 | G53: =C22*(1+Assumptions!$C$8)^3*G22/100 -> 5.5680768 | H53: =C22*(1+Assumptions!$C$8)^4*H22/100 -> 8.2358043 | I53: =C22*(1+Assumptions!$C$8)^5*I22/100 -> 11.509536 | J53: =C22*(1+Assumptions!$C$8)^6*J22/100 -> 15.31036 | K53: =C22*(1+Assumptions!$C$8)^7*K22/100 -> 17.370299 | L53: =C22*(1+Assumptions!$C$8)^8*L22/100 -> 19.269452 | M53: =C22*(1+Assumptions!$C$8)^9*M22/100 -> 21.292745
B54: Supply Chain / Procurement - cost | C54: COGS | D54: =C23*(1+Assumptions!$C$8)^0*D23/100 -> 0.27 | E54: =C23*(1+Assumptions!$C$8)^1*E23/100 -> 0.5616 | F54: =C23*(1+Assumptions!$C$8)^2*F23/100 -> 0.778752 | G54: =C23*(1+Assumptions!$C$8)^3*G23/100 -> 1.3160909 | H54: =C23*(1+Assumptions!$C$8)^4*H23/100 -> 1.6845963 | I54: =C23*(1+Assumptions!$C$8)^5*I23/100 -> 2.1899752 | J54: =C23*(1+Assumptions!$C$8)^6*J23/100 -> 2.7330891 | K54: =C23*(1+Assumptions!$C$8)^7*K23/100 -> 2.8424126 | L54: =C23*(1+Assumptions!$C$8)^8*L23/100 -> 3.2024516 | M54: =C23*(1+Assumptions!$C$8)^9*M23/100 -> 3.3305496
B55: Field Service / Customer Support - cost | C55: COGS | D55: =C24*(1+Assumptions!$C$8)^0*D24/100 -> 0.22 | E55: =C24*(1+Assumptions!$C$8)^1*E24/100 -> 0.6864 | F55: =C24*(1+Assumptions!$C$8)^2*F24/100 -> 1.308736 | G55: =C24*(1+Assumptions!$C$8)^3*G24/100 -> 2.2272307 | H55: =C24*(1+Assumptions!$C$8)^4*H24/100 -> 3.4744799 | I55: =C24*(1+Assumptions!$C$8)^5*I24/100 -> 5.0856091 | J55: =C24*(1+Assumptions!$C$8)^6*J24/100 -> 6.6808844 | K55: =C24*(1+Assumptions!$C$8)^7*K24/100 -> 7.8166348 | L55: =C24*(1+Assumptions!$C$8)^8*L24/100 -> 8.7314705 | M55: =C24*(1+Assumptions!$C$8)^9*M24/100 -> 9.393858
B56: Capture / BD Leads (regional) - cost | C56: S&M | D56: =C25*(1+Assumptions!$C$8)^0*D25/100 -> 0.36 | E56: =C25*(1+Assumptions!$C$8)^1*E25/100 -> 0.624 | F56: =C25*(1+Assumptions!$C$8)^2*F25/100 -> 0.908544 | G56: =C25*(1+Assumptions!$C$8)^3*G25/100 -> 1.2148531 | H56: =C25*(1+Assumptions!$C$8)^4*H25/100 -> 1.4038303 | I56: =C25*(1+Assumptions!$C$8)^5*I25/100 -> 1.6059818 | J56: =C25*(1+Assumptions!$C$8)^6*J25/100 -> 1.8220594 | K56: =C25*(1+Assumptions!$C$8)^7*K25/100 -> 2.0528536 | L56: =C25*(1+Assumptions!$C$8)^8*L25/100 -> 2.299196 | M56: =C25*(1+Assumptions!$C$8)^9*M25/100 -> 2.3911638
B57: Solution Architects (presales) - cost | C57: S&M | D57: =C26*(1+Assumptions!$C$8)^0*D26/100 -> 0.44 | E57: =C26*(1+Assumptions!$C$8)^1*E26/100 -> 0.9152 | F57: =C26*(1+Assumptions!$C$8)^2*F26/100 -> 1.427712 | G57: =C26*(1+Assumptions!$C$8)^3*G26/100 -> 1.7322906 | H57: =C26*(1+Assumptions!$C$8)^4*H26/100 -> 2.0589511 | I57: =C26*(1+Assumptions!$C$8)^5*I26/100 -> 2.4089727 | J57: =C26*(1+Assumptions!$C$8)^6*J26/100 -> 2.7837018 | K57: =C26*(1+Assumptions!$C$8)^7*K26/100 -> 3.1845549 | L57: =C26*(1+Assumptions!$C$8)^8*L26/100 -> 3.3119371 | M57: =C26*(1+Assumptions!$C$8)^9*M26/100 -> 3.7575432
B58: Marketing / Comms - cost | C58: S&M | D58: =C27*(1+Assumptions!$C$8)^0*D27/100 -> 0.22 | E58: =C27*(1+Assumptions!$C$8)^1*E27/100 -> 0.4576 | F58: =C27*(1+Assumptions!$C$8)^2*F27/100 -> 0.713856 | G58: =C27*(1+Assumptions!$C$8)^3*G27/100 -> 0.98988032 | H58: =C27*(1+Assumptions!$C$8)^4*H27/100 -> 1.2868444 | I58: =C27*(1+Assumptions!$C$8)^5*I27/100 -> 1.3383182 | J58: =C27*(1+Assumptions!$C$8)^6*J27/100 -> 1.6702211 | K58: =C27*(1+Assumptions!$C$8)^7*K27/100 -> 1.7370299 | L58: =C27*(1+Assumptions!$C$8)^8*L27/100 -> 2.1075963 | M58: =C27*(1+Assumptions!$C$8)^9*M27/100 -> 2.1919002
B59: Executive / Leadership - cost | C59: G&A | D59: =C28*(1+Assumptions!$C$8)^0*D28/100 -> 1 | E59: =C28*(1+Assumptions!$C$8)^1*E28/100 -> 1.248 | F59: =C28*(1+Assumptions!$C$8)^2*F28/100 -> 1.51424 | G59: =C28*(1+Assumptions!$C$8)^3*G28/100 -> 1.7997824 | H59: =C28*(1+Assumptions!$C$8)^4*H28/100 -> 1.8717737 | I59: =C28*(1+Assumptions!$C$8)^5*I28/100 -> 2.1899752 | J59: =C28*(1+Assumptions!$C$8)^6*J28/100 -> 2.2775742 | K59: =C28*(1+Assumptions!$C$8)^7*K28/100 -> 2.6318636 | L59: =C28*(1+Assumptions!$C$8)^8*L28/100 -> 2.7371381 | M59: =C28*(1+Assumptions!$C$8)^9*M28/100 -> 2.8466236
B60: Finance / Accounting - cost | C60: G&A | D60: =C29*(1+Assumptions!$C$8)^0*D29/100 -> 0.64 | E60: =C29*(1+Assumptions!$C$8)^1*E29/100 -> 0.9984 | F60: =C29*(1+Assumptions!$C$8)^2*F29/100 -> 1.384448 | G60: =C29*(1+Assumptions!$C$8)^3*G29/100 -> 1.7997824 | H60: =C29*(1+Assumptions!$C$8)^4*H29/100 -> 2.2461284 | I60: =C29*(1+Assumptions!$C$8)^5*I29/100 -> 2.3359736 | J60: =C29*(1+Assumptions!$C$8)^6*J29/100 -> 2.8343146 | K60: =C29*(1+Assumptions!$C$8)^7*K29/100 -> 2.9476872 | L60: =C29*(1+Assumptions!$C$8)^8*L29/100 -> 3.5035368 | M60: =C29*(1+Assumptions!$C$8)^9*M29/100 -> 3.6436782
B61: HR / People Ops - cost | C61: G&A | D61: =C30*(1+Assumptions!$C$8)^0*D30/100 -> 0.09 | E61: =C30*(1+Assumptions!$C$8)^1*E30/100 -> 0.1872 | F61: =C30*(1+Assumptions!$C$8)^2*F30/100 -> 0.292032 | G61: =C30*(1+Assumptions!$C$8)^3*G30/100 -> 0.40495104 | H61: =C30*(1+Assumptions!$C$8)^4*H30/100 -> 0.52643635 | I61: =C30*(1+Assumptions!$C$8)^5*I30/100 -> 0.54749381 | J61: =C30*(1+Assumptions!$C$8)^6*J30/100 -> 0.68327227 | K61: =C30*(1+Assumptions!$C$8)^7*K30/100 -> 0.71060316 | L61: =C30*(1+Assumptions!$C$8)^8*L30/100 -> 0.73902729 | M61: =C30*(1+Assumptions!$C$8)^9*M30/100 -> 0.76858838
B62: Legal / Contracts - cost | C62: G&A | D62: =C31*(1+Assumptions!$C$8)^0*D31/100 -> 0.1 | E62: =C31*(1+Assumptions!$C$8)^1*E31/100 -> 0.208 | F62: =C31*(1+Assumptions!$C$8)^2*F31/100 -> 0.21632 | G62: =C31*(1+Assumptions!$C$8)^3*G31/100 -> 0.3374592 | H62: =C31*(1+Assumptions!$C$8)^4*H31/100 -> 0.35095757 | I62: =C31*(1+Assumptions!$C$8)^5*I31/100 -> 0.48666116 | J62: =C31*(1+Assumptions!$C$8)^6*J31/100 -> 0.50612761 | K62: =C31*(1+Assumptions!$C$8)^7*K31/100 -> 0.52637271 | L62: =C31*(1+Assumptions!$C$8)^8*L31/100 -> 0.54742762 | M62: =C31*(1+Assumptions!$C$8)^9*M31/100 -> 0.56932472
B63: Export Control / Compliance - cost | C63: G&A | D63: =C32*(1+Assumptions!$C$8)^0*D32/100 -> 0.24 | E63: =C32*(1+Assumptions!$C$8)^1*E32/100 -> 0.3744 | F63: =C32*(1+Assumptions!$C$8)^2*F32/100 -> 0.389376 | G63: =C32*(1+Assumptions!$C$8)^3*G32/100 -> 0.53993472 | H63: =C32*(1+Assumptions!$C$8)^4*H32/100 -> 0.56153211 | I63: =C32*(1+Assumptions!$C$8)^5*I32/100 -> 0.72999174 | J63: =C32*(1+Assumptions!$C$8)^6*J32/100 -> 0.75919141 | K63: =C32*(1+Assumptions!$C$8)^7*K32/100 -> 0.78955907 | L63: =C32*(1+Assumptions!$C$8)^8*L32/100 -> 0.98536972 | M63: =C32*(1+Assumptions!$C$8)^9*M32/100 -> 1.0247845
B64: IT / DevOps / Cloud - cost | C64: G&A | D64: =C33*(1+Assumptions!$C$8)^0*D33/100 -> 0.24 | E64: =C33*(1+Assumptions!$C$8)^1*E33/100 -> 0.3744 | F64: =C33*(1+Assumptions!$C$8)^2*F33/100 -> 0.519168 | G64: =C33*(1+Assumptions!$C$8)^3*G33/100 -> 0.6749184 | H64: =C33*(1+Assumptions!$C$8)^4*H33/100 -> 0.84229816 | I64: =C33*(1+Assumptions!$C$8)^5*I33/100 -> 0.87599009 | J64: =C33*(1+Assumptions!$C$8)^6*J33/100 -> 1.062868 | K64: =C33*(1+Assumptions!$C$8)^7*K33/100 -> 1.1053827 | L64: =C33*(1+Assumptions!$C$8)^8*L33/100 -> 1.3138263 | M64: =C33*(1+Assumptions!$C$8)^9*M33/100 -> 1.3663793
B66: C. Personnel cost by category
B67: R&D personnel cost | D67: =D37+D38+D39+D40+D41+D42+D43+D44+D45+D46+D47+D48+D49+D50+D51 -> 12.51 | E67: =E37+E38+E39+E40+E41+E42+E43+E44+E45+E46+E47+E48+E49+E50+E51 -> 20.6648 | F67: =F37+F38+F39+F40+F41+F42+F43+F44+F45+F46+F47+F48+F49+F50+F51 -> 28.44608 | G67: =G37+G38+G39+G40+G41+G42+G43+G44+G45+G46+G47+G48+G49+G50+G51 -> 36.873042 | H67: =H37+H38+H39+H40+H41+H42+H43+H44+H45+H46+H47+H48+H49+H50+H51 -> 43.776107 | I67: =I37+I38+I39+I40+I41+I42+I43+I44+I45+I46+I47+I48+I49+I50+I51 -> 50.028767 | J67: =J37+J38+J39+J40+J41+J42+J43+J44+J45+J46+J47+J48+J49+J50+J51 -> 54.965458 | K67: =K37+K38+K39+K40+K41+K42+K43+K44+K45+K46+K47+K48+K49+K50+K51 -> 60.453906 | ... M67: =M37+M38+M39+M40+M41+M42+M43+M44+M45+M46+M47+M48+M49+M50+M51 -> 66.767557
B68: COGS personnel cost | D68: =D52+D53+D54+D55 -> 2.03 | E68: =E52+E53+E54+E55 -> 4.9088 | F68: =F52+F53+F54+F55 -> 8.155264 | G68: =G52+G53+G54+G55 -> 13.31839 | H68: =H52+H53+H54+H55 -> 19.056996 | I68: =I52+I53+I54+I55 -> 26.547366 | J68: =J52+J53+J54+J55 -> 34.74566 | K68: =K52+K53+K54+K55 -> 39.030537 | ... M68: =M52+M53+M54+M55 -> 46.542296
B69: S&M personnel cost | D69: =D56+D57+D58 -> 1.02 | E69: =E56+E57+E58 -> 1.9968 | F69: =F56+F57+F58 -> 3.050112 | G69: =G56+G57+G58 -> 3.937024 | H69: =H56+H57+H58 -> 4.7496258 | I69: =I56+I57+I58 -> 5.3532728 | J69: =J56+J57+J58 -> 6.2759823 | K69: =K56+K57+K58 -> 6.9744384 | ... M69: =M56+M57+M58 -> 8.3406072
B70: G&A personnel cost | D70: =D59+D60+D61+D62+D63+D64 -> 2.31 | E70: =E59+E60+E61+E62+E63+E64 -> 3.3904 | F70: =F59+F60+F61+F62+F63+F64 -> 4.315584 | G70: =G59+G60+G61+G62+G63+G64 -> 5.5568282 | H70: =H59+H60+H61+H62+H63+H64 -> 6.3991263 | I70: =I59+I60+I61+I62+I63+I64 -> 7.1660856 | J70: =J59+J60+J61+J62+J63+J64 -> 8.1233481 | K70: =K59+K60+K61+K62+K63+K64 -> 8.7114684 | ... M70: =M59+M60+M61+M62+M63+M64 -> 10.219379
B71: Note (M4 fix): Production headcount represents in-house core. Contract manufacturing at qualified partners absorbs ~30-40% of unit volumes (esp. V1 radar, V3 C-UAS) - embedded in COGS-BoM, not in this headcount table. | D71: =D67+D68+D69+D70 -> 17.87 | E71: =E67+E68+E69+E70 -> 30.9608 | F71: =F67+F68+F69+F70 -> 43.96704 | G71: =G67+G68+G69+G70 -> 59.685284 | H71: =H67+H68+H69+H70 -> 73.981855 | I71: =I67+I68+I69+I70 -> 89.095492 | J71: =J67+J68+J69+J70 -> 104.11045 | K71: =K67+K68+K69+K70 -> 115.17035 | ... M71: =M67+M68+M69+M70 -> 131.86984
B72: Note (M6): Production ratios should be computed against HW-platform units only (V1 AESA, V3 C-UAS, V4 UAS, V5 AUV/USV, V2 ESM hardware). V6 (AI/SaaS) and V2 small EW kits are not capacity-constrained by mfg HC. With M4 scale-up and ~30-40% contract mfg, in-house complex-platform throughput is ~2-3 units/FTE/yr - within defense-industry norms.

Sheet R&D_NRE
B2: R&D / NRE - Platform + Vertical-Specific (Post-Reuse) + R&D Personnel
B4: Line | C4: Source | D4: Y1 | E4: Y2 | F4: Y3 | G4: Y4 | H4: Y5 | I4: Y6 | J4: Y7 | K4: Y8 | L4: Y9 | M4: Y10
B5: Platform NRE (shared) | C5: Platform!Total | D5: =Platform!D11 -> 101 | E5: =Platform!E11 -> 210 | F5: =Platform!F11 -> 107 | G5: =Platform!G11 -> 69 | H5: =Platform!H11 -> 38 | I5: =Platform!I11 -> 20.5 | J5: =Platform!J11 -> 11.3 | K5: =Platform!K11 -> 8.4 | ... M5: =Platform!M11 -> 3.1
B6: Σ Leveraged vertical NRE (post-reuse) | C6: ReuseMatrix!Σ Leveraged | D6: =ReuseMatrix!D25+ReuseMatrix!D28+ReuseMatrix!D31+ReuseMatrix!D34+ReuseMatrix!D37+ReuseMatrix!D40 -> 141.82788 | E6: =ReuseMatrix!E25+ReuseMatrix!E28+ReuseMatrix!E31+ReuseMatrix!E34+ReuseMatrix!E37+ReuseMatrix!E40 -> 110.14918 | F6: =ReuseMatrix!F25+ReuseMatrix!F28+ReuseMatrix!F31+ReuseMatrix!F34+ReuseMatrix!F37+ReuseMatrix!F40 -> 59.139457 | G6: =ReuseMatrix!G25+ReuseMatrix!G28+ReuseMatrix!G31+ReuseMatrix!G34+ReuseMatrix!G37+ReuseMatrix!G40 -> 26.760075 | H6: =ReuseMatrix!H25+ReuseMatrix!H28+ReuseMatrix!H31+ReuseMatrix!H34+ReuseMatrix!H37+ReuseMatrix!H40 -> 10.307785 | I6: =ReuseMatrix!I25+ReuseMatrix!I28+ReuseMatrix!I31+ReuseMatrix!I34+ReuseMatrix!I37+ReuseMatrix!I40 -> 3.740853 | J6: =ReuseMatrix!J25+ReuseMatrix!J28+ReuseMatrix!J31+ReuseMatrix!J34+ReuseMatrix!J37+ReuseMatrix!J40 -> 1.6259535 | K6: =ReuseMatrix!K25+ReuseMatrix!K28+ReuseMatrix!K31+ReuseMatrix!K34+ReuseMatrix!K37+ReuseMatrix!K40 -> 0.65750925 | ... M6: =ReuseMatrix!M25+ReuseMatrix!M28+ReuseMatrix!M31+ReuseMatrix!M34+ReuseMatrix!M37+ReuseMatrix!M40 -> 0.087875
B7: R&D personnel cost (from Headcount) | C7: Headcount!R&D cost | D7: =Headcount!D67 -> 12.51 | E7: =Headcount!E67 -> 20.6648 | F7: =Headcount!F67 -> 28.44608 | G7: =Headcount!G67 -> 36.873042 | H7: =Headcount!H67 -> 43.776107 | I7: =Headcount!I67 -> 50.028767 | J7: =Headcount!J67 -> 54.965458 | K7: =Headcount!K67 -> 60.453906 | ... M7: =Headcount!M67 -> 66.767557
B8: Memo: Σ Gross NRE (standalone, no platform reuse) | C8: ReuseMatrix!Σ Gross | D8: =ReuseMatrix!D24+ReuseMatrix!D27+ReuseMatrix!D30+ReuseMatrix!D33+ReuseMatrix!D36+ReuseMatrix!D39 -> 261.725 | E8: =ReuseMatrix!E24+ReuseMatrix!E27+ReuseMatrix!E30+ReuseMatrix!E33+ReuseMatrix!E36+ReuseMatrix!E39 -> 308.75 | F8: =ReuseMatrix!F24+ReuseMatrix!F27+ReuseMatrix!F30+ReuseMatrix!F33+ReuseMatrix!F36+ReuseMatrix!F39 -> 270.085 | G8: =ReuseMatrix!G24+ReuseMatrix!G27+ReuseMatrix!G30+ReuseMatrix!G33+ReuseMatrix!G36+ReuseMatrix!G39 -> 206.53 | H8: =ReuseMatrix!H24+ReuseMatrix!H27+ReuseMatrix!H30+ReuseMatrix!H33+ReuseMatrix!H36+ReuseMatrix!H39 -> 133.475 | I8: =ReuseMatrix!I24+ReuseMatrix!I27+ReuseMatrix!I30+ReuseMatrix!I33+ReuseMatrix!I36+ReuseMatrix!I39 -> 75.43 | J8: =ReuseMatrix!J24+ReuseMatrix!J27+ReuseMatrix!J30+ReuseMatrix!J33+ReuseMatrix!J36+ReuseMatrix!J39 -> 47.5 | K8: =ReuseMatrix!K24+ReuseMatrix!K27+ReuseMatrix!K30+ReuseMatrix!K33+ReuseMatrix!K36+ReuseMatrix!K39 -> 27.1225 | ... M8: =ReuseMatrix!M24+ReuseMatrix!M27+ReuseMatrix!M30+ReuseMatrix!M33+ReuseMatrix!M36+ReuseMatrix!M39 -> 8.7875
B9: Memo (counterfactual): NRE avoided by platform reuse - vs. standalone build | D9: =D8-D6 -> 119.89713 | E9: =E8-E6 -> 198.60082 | F9: =F8-F6 -> 210.94554 | G9: =G8-G6 -> 179.76992 | H9: =H8-H6 -> 123.16721 | I9: =I8-I6 -> 71.689147 | J9: =J8-J6 -> 45.874046 | K9: =K8-K6 -> 26.464991 | ... M9: =M8-M6 -> 8.699625
B11: Total R&D / NRE expense (P&L line)
B12: TOTAL R&D / NRE EXPENSE (P&L) - excludes capitalized portion | C12: P&L line; capitalized portion flows to BS intangibles (row 16) and amortises through D&A on P&L row 19 (Capex!D39 + R&D_NRE!D18). No double-count. | D12: =D17+D6+D7+D19 -> 301.93624 | E12: =E17+E6+E7+E19 -> 347.80873 | F12: =F17+F6+F7+F19 -> 185.21737 | G12: =G17+G6+G7+G19 -> 118.02114 | H12: =H17+H6+H7+H19 -> 80.586228 | I12: =I17+I6+I7+I19 -> 66.911876 | J12: =J17+J6+J7+J19 -> 63.404198 | K12: =K17+K6+K7+K19 -> 65.917668 | ... M12: =M17+M6+M7+M19 -> 68.640795
B13: C4: Capitalize Platform NRE under Ind AS 38
B14: Weighted capitalisation rate (% Platform NRE) | C14: Annual rate from R&D_Buckets | D14: ='R&D_Buckets'!D89 -> 0.25990099 | E14: ='R&D_Buckets'!E89 -> 0.42404762 | F14: ='R&D_Buckets'!F89 -> 0.55336449 | G14: ='R&D_Buckets'!G89 -> 0.62811594 | H14: ='R&D_Buckets'!H89 -> 0.68394737 | I14: ='R&D_Buckets'!I89 -> 0.71365854 | J14: ='R&D_Buckets'!J89 -> 0.74026549 | K14: ='R&D_Buckets'!K89 -> 0.75130952 | ... M14: ='R&D_Buckets'!M89 -> 0.73258065
B15: Amortization life (years) | C15: =Assumptions!C58 -> 6 | D15: Straight-line, 6 years per tranche, starting same year capitalization is recognized.
B16: Development capitalised (intangibles addition) | D16: ='R&D_Buckets'!D88 -> 26.25 | E16: ='R&D_Buckets'!E88 -> 89.05 | F16: ='R&D_Buckets'!F88 -> 59.21 | G16: ='R&D_Buckets'!G88 -> 43.34 | H16: ='R&D_Buckets'!H88 -> 25.99 | I16: ='R&D_Buckets'!I88 -> 14.63 | J16: ='R&D_Buckets'!J88 -> 8.365 | K16: ='R&D_Buckets'!K88 -> 6.311 | ... M16: ='R&D_Buckets'!M88 -> 2.271
B17: Platform R&D expensed (research + non-eligible development) | D17: ='R&D_Buckets'!D87 -> 74.75 | E17: ='R&D_Buckets'!E87 -> 120.95 | F17: ='R&D_Buckets'!F87 -> 47.79 | G17: ='R&D_Buckets'!G87 -> 25.66 | H17: ='R&D_Buckets'!H87 -> 12.01 | I17: ='R&D_Buckets'!I87 -> 5.87 | J17: ='R&D_Buckets'!J87 -> 2.935 | K17: ='R&D_Buckets'!K87 -> 2.089 | ... M17: ='R&D_Buckets'!M87 -> 0.829
B18: Amortisation of capitalised R&D (this year, in D&A) | D18: ='R&D_Buckets'!D90 -> 4.375 | E18: ='R&D_Buckets'!E90 -> 19.216667 | F18: ='R&D_Buckets'!F90 -> 29.085 | G18: ='R&D_Buckets'!G90 -> 36.308333 | H18: ='R&D_Buckets'!H90 -> 40.64 | I18: ='R&D_Buckets'!I90 -> 43.078333 | J18: ='R&D_Buckets'!J90 -> 40.0975 | K18: ='R&D_Buckets'!K90 -> 26.307667 | ... M18: ='R&D_Buckets'!M90 -> 10.458833
B19: NRE contingency (30% uplift for realistic AESA/MALE/AUV costs) | C19: Adjustment | D19: =0.3*(D5+D6) -> 72.848362 | E19: =0.3*(E5+E6) -> 96.044753 | F19: =0.3*(F5+F6) -> 49.841837 | G19: =0.3*(G5+G6) -> 28.728022 | H19: =0.3*(H5+H6) -> 14.492335 | I19: =0.3*(I5+I6) -> 7.2722559 | J19: =0.3*(J5+J6) -> 3.8777861 | K19: =0.3*(K5+K6) -> 2.7172528 | ... M19: =0.3*(M5+M6) -> 0.9563625

Sheet Capex
B2: Capital Expenditure & Depreciation (Straight-line)
B4: Item | C4: Life (yr) | D4: Y1 | E4: Y2 | F4: Y3 | G4: Y4 | H4: Y5 | I4: Y6 | J4: Y7 | K4: Y8 | L4: Y9 | M4: Y10
B5: A. Capex - per-item spend (₹ L)
B6: Vector Network Analyzer (VNA) suite | C6: 7 | D6: 237.5 | E6: 142.5 | F6: 0 | G6: 0 | H6: 237.5 | I6: 0 | J6: 0 | K6: 0 | L6: 237.5 | M6: 0
B7: Anechoic Chamber + Near-field Range (own) | C7: 15 | D7: 0 | E7: 0 | F7: 2500 | G7: 2500 | H7: 1000 | I7: 0 | J7: 0 | K7: 0 | L7: 0 | M7: 0
B8: Cleanroom (SMT / GaN packaging) | C8: 10 | D8: 400 | E8: 700 | F8: 850 | G8: 500 | H8: 0 | I8: 0 | J8: 190 | K8: 0 | L8: 0 | M8: 0
B9: SMT / Assembly Production Line | C9: 7 | D9: 500 | E9: 1000 | F9: 1200 | G9: 600 | H9: 600 | I9: 1100 | J9: 0 | K9: 0 | L9: 475 | M9: 0
B10: HALT / HASS Environmental Test Chambers | C10: 10 | D10: 250 | E10: 400 | F10: 500 | G10: 380 | H10: 0 | I10: 0 | J10: 0 | K10: 190 | L10: 0 | M10: 0
